Workbook

Sheet Cover Notes
A1: Wipro Enterprises (P) Limited - Standalone Financial Statements
A2: FY 2020-21, FY 2021-22, FY 2022-23, FY 2023-24 and FY 2024-25
A4: This workbook compiles the Standalone financial statements as reported in the audited Annual Reports of
A5: Wipro Enterprises (P) Limited for FY2020-21, FY2021-22, FY2022-23, FY2023-24 and FY2024-25.
A7: Scope and basis of preparation:
A8: - All figures are STANDALONE (not consolidated), as reported in each year's Annual Report, in Rs. millions.
A9: - Figures are transcribed exactly as printed in the source PDFs - no figures have been altered, recalculated, or restated by
A10: this workbook. Where a later annual report restated a prior year (e.g. FY2021 figures restated for a merger in the
A11: FY2021-22 report, marked with *), both the original and the restated figures are preserved in their respective year's sheet.
A12: - "*" symbols used in source reports to denote amounts below Rs. 0.5 million (rounding) have been entered as 0.
A13: - Each statement/notes sheet cites its exact source document and page number.
A15: Sheets included per year: Balance Sheet, Statement of Profit and Loss, Statement of Cash Flows, and a Notes to Accounts
... A36: instruction not to change any figures.

Sheet PL 2020-21
A1: Wipro Enterprises (P) Limited (Standalone)
A2: Statement of Profit and Loss
A3: Statement of Profit and Loss for the year ended March 31, 2021 (Source: Annual Report 2020-21, p.59)
A4: (Amount Rs. in millions, unless otherwise stated)
A6: Particulars | B6: 2021 | C6: 2020
A7: REVENUE
A8: Revenue from operations | B8: 51658 | C8: 47775
A9: Other income | B9: 6905 | C9: 4900
A10: Total income | B10: 58563 | C10: 52675
A11: EXPENSES
A12: Cost of materials consumed | B12: 21255 | C12: 16125
A13: Purchases of stock-in-trade | B13: 8407 | C13: 9470
A14: Changes in inventories of finished products, WIP and stock-in-trade | B14: 341 | C14: -288
A15: Employee benefits expense | B15: 4518 | C15: 4077
A16: Finance costs | B16: 762 | C16: 113
A17: Depreciation and amortisation expense | B17: 914 | C17: 956
A18: Other expenses | B18: 11101 | C18: 11893
A19: Total expenses | B19: 47298 | C19: 42347
A20: Profit before tax | B20: 11265 | C20: 10328
A21: Tax expense
A22: Current tax | B22: 1910 | C22: 2179
A23: Deferred tax | B23: 225 | C23: -26
A24: Total tax expenses | B24: 2135 | C24: 2153
A25: Profit for the year | B25: 9130 | C25: 8175
A26: Other comprehensive income, net of taxes
A27: Items not reclassified to P&L - Remeasurement of defined benefit liability/asset (net of tax) | B27: -1 | C27: 24
A28: Items reclassified to P&L - Net change in FV of financial instruments through OCI (net of tax) | B28: 408 | C28: 349
A29: Net change in FV of cash flow hedge (net of tax) | B29: 65 | C29: -36
A30: Total other comprehensive income for the year, net of taxes | B30: 472 | C30: 337
A31: Total comprehensive income for the year | B31: 9602 | C31: 8512
A32: Earnings per equity share (par value Rs.10 each)
A33: Weighted average equity shares for computing basic and diluted EPS | B33: 483662163 | C33: 483662163
A34: Basic and diluted EPS (Rs.) | B34: 18.88 | C34: 16.9

Sheet CF 2020-21
A1: Wipro Enterprises (P) Limited (Standalone)
A2: Statement of Cash Flows
A3: Statement of Cash Flows for the year ended March 31, 2021 (Source: Annual Report 2020-21, p.61)
A4: (Amount Rs. in millions, unless otherwise stated)
A6: ` | B6: 2021 | C6: 2020
A7: A. Cash flows from operating activities
A8: Profit before tax | B8: 11264 | C8: 10328
A9: Depreciation and amortization | B9: 915 | C9: 956
A10: Interest on borrowings | B10: 762 | C10: 113
A11: Unrealized (gain)/loss on investments | B11: -1718 | C11: -658
A12: Dividend / interest income | B12: -2030 | C12: -1877
A13: Net (gain)/loss on sale of current investments | B13: -998 | C13: -915
A14: Net (gain)/loss on sale of associates | B14: -1762 | C14: -1185
A15: Net (gain)/loss on sale of PP&E and intangible assets | B15: -32 | C15: -2
A16: Allowance for doubtful receivables | B16: -5 | C16: 129
A17: Net foreign exchange differences on non-operating items | B17: -7 | C17: 11
A18: Working capital changes - Trade receivables | B18: -3137 | C18: 1351
A19: Working capital changes - Other assets | B19: 922 | C19: -1299
... A24: Net cash generated from operating activities | B24: 4670 | C24: 3728
A25: B. Cash flows from investing activities
A26: Acquisition of PP&E including capital advances | B26: -511 | C26: -851
A27: Proceeds from sale of PP&E | B27: 32 | C27: 2
A28: Investment in associates | B28: -105 | C28: -40
A29: Purchase of current investments | B29: -100542 | C29: -110863
A30: Purchase of non-current investments | B30: -150 | C30: -534
A31: Proceeds from sale/maturity of current investments | B31: 102688 | C31: 106374
A32: Proceeds from sale of investment in associates | B32: 1774 | C32: 1195
A33: Investment in subsidiaries | B33: -5398 | C33: -125
A34: Loan to subsidiaries | B34: -16448 | C34: 0
A35: Inter-corporate deposits placed | B35: -3518 | C35: 0
A36: Dividend / interest income received | B36: 1047 | C36: 1218
A37: Net cash used in investing activities | B37: -21131 | C37: -3624
A38: C. Cash flows from financing activities
A39: Interest paid on borrowings | B39: -742 | C39: -88
A40: Proceeds from borrowings / debentures | B40: 17677 | C40: 161
A41: Repayment of lease liabilities | B41: -77 | C41: -86
A42: Repayment of borrowings / loans | B42: -201 | C42: -310
A43: Net cash generated from/(used in) financing activities | B43: 16657 | C43: -323
A44: Net increase/(decrease) in cash and cash equivalents during the year | B44: 197 | C44: -220
A45: Cash and cash equivalents at the beginning of the year | B45: 1350 | C45: 1570
A46: Cash and cash equivalents at the end of the year | B46: 1547 | C46: 1350
A47: Components of cash and cash equivalents
A48: Balances with banks - in current accounts | B48: 691 | C48: 1135
A49: Balances with banks - in deposit accounts | B49: 80 | C49: 90
A50: Cheques, drafts on hand | B50: 768 | C50: 120
A51: Remittance in transit | B51: 7 | C51: 4
A52: Cash in hand (rounded to nil, below Rs.0.5 mn) | B52: 0 | C52: 0

Sheet BS 2020-21
A1: Wipro Enterprises (P) Limited (Standalone)
A2: Balance Sheet
A3: Balance Sheet as at March 31, 2021 (Source: Annual Report 2020-21, WEL-Annual-Report-High-Res.pdf, p.58)
A4: (Amount Rs. in millions, unless otherwise stated)
A6: Particulars | B6: 2021 | C6: 2020
A7: ASSETS
A8: Non-current assets
A9: Property, plant and equipment | B9: 6172 | C9: 6866
A10: Capital work-in-progress | B10: 984 | C10: 578
A11: Right of use assets | B11: 853 | C11: 948
A12: Goodwill | B12: 497 | C12: 497
A13: Other intangible assets | B13: 766 | C13: 791
A14: Financial assets - Investments | B14: 30726 | C14: 24560
A15: Financial assets - Loans | B15: 16979 | C15: 483
A16: Financial assets - Other financial assets | B16: 18 | C16: 0
A17: Other non-current assets | B17: 112 | C17: 120
A18: Total non-current assets | B18: 57107 | C18: 34843
A19: Current assets
A20: Inventories | B20: 5778 | C20: 5846
A21: Financial assets - Investments | B21: 49294 | C21: 47238
A22: Financial assets - Trade receivables | B22: 7451 | C22: 4309
A23: Financial assets - Derivative instruments | B23: 95 | C23: 2
A24: Financial assets - Cash and cash equivalents | B24: 1547 | C24: 1350
A25: Financial assets - Loans | B25: 3956 | C25: 237 | F25: =SUM(C18,C29) -> 98321
A26: Financial assets - Other financial assets | B26: 737 | C26: 251
A27: Current tax assets (net) | B27: 243 | C27: 304
A28: Other assets | B28: 2832 | C28: 3941
A29: Total current assets | B29: 71933 | C29: 63478
A30: TOTAL ASSETS | B30: 129040 | C30: 98321
A31: EQUITY AND LIABILITIES
A32: Equity
A33: Share capital | B33: 4837 | C33: 4837
A34: Other equity | B34: 87753 | C34: 78152
A35: Total equity | B35: 92590 | C35: 82989
A36: Non-current liabilities
A37: Financial liabilities - Borrowings | B37: 17375 | C37: 1192
A38: Financial liabilities - Lease liabilities | B38: 61 | C38: 130
A39: Financial liabilities - Other financial liabilities | B39: 1023 | C39: 28
A40: Provisions | B40: 105 | C40: 183
A41: Deferred tax liabilities (net) | B41: 1488 | C41: 1224
A42: Total non-current liabilities | B42: 20052 | C42: 2757
A43: Current assets
A44: Financial liabilities - Borrowings | B44: 1414 | C44: 761 | G44: =SUM(C44,C49) -> 1555
A45: Financial liabilities - Lease liabilities | B45: 130 | C45: 118 | G45: =SUM(C47:C48) -> 8909
A46: Financial liabilities - Derivative liabilities | B46: 151 | C46: 11 | G46: =SUM(C45:C46,C50:C53) -> 2111
A47: Trade payables - dues of micro & small enterprises | B47: 1154 | C47: 179 | G47: =SUM(G44:G46) -> 12575
A48: Trade payables - dues of other creditors | B48: 10054 | C48: 8730
A49: Current maturities of long-term debt | B49: 816 | C49: 794
A50: Financial liabilities - Other financial liabilities | B50: 1115 | C50: 469
A51: Other current liabilities | B51: 1108 | C51: 1099
A52: Provisions | B52: 94 | C52: 203
A53: Current tax liabilities (net) | B53: 362 | C53: 211
A54: Total current liabilities | B54: 16398 | C54: 12575
A55: TOTAL EQUITY AND LIABILITIES | B55: 129040 | C55: 98321

Sheet Notes 2020-21
A1: Wipro Enterprises (P) Limited (Standalone)
A2: Notes to the Standalone Financial Statements (Selected Notes)
A3: Notes to the Standalone Financial Statements, year ended March 31, 2021 (Source: Annual Report 2020-21, pp.75-107)
A4: (Amount Rs. in millions, unless otherwise stated)
A6: Note 4. Property, plant and equipment - Net carrying value
B7: 2021 | C7: 2020
A8: Land | B8: 208 | C8: 310
A9: Buildings | B9: 1902 | C9: 2010
A10: Plant and Machinery | B10: 3921 | C10: 4396
A11: Furniture and Fixtures | B11: 43 | C11: 42
A12: Office Equipment | B12: 100 | C12: 102
A13: Vehicles | B13: 2 | C13: 7
A14: Total | B14: 6174 | C14: 6867
A15: (Total gross carrying value as at March 31, 2021: 14,469; accumulated depreciation: 8,297; March 31, 2020 gross: 14,619, accumulated depreciation: 7,753)
A17: Note 5. Right-of-use Assets - Net carrying value
B18: 2021 | C18: 2020
A19: Land | B19: 683 | C19: 715
A20: Buildings | B20: 152 | C20: 202
A21: Furniture and Fixtures | B21: 13 | C21: 21
A22: Vehicles | B22: 5 | C22: 9
A23: Total | B23: 853 | C23: 948
A25: Note 6. Goodwill and intangible assets - movement in Goodwill
B26: 2021 | C26: 2020
A27: Amount at the beginning of the year | B27: 497 | C27: 362
A28: Addition due to acquisition | B28: 0 | C28: 135
A29: Amount at the end of the year | B29: 497 | C29: 497
A30: Net block of other intangible assets: 766 (2021), 791 (2020) [Technical know-how 191/206; Brands, patents, trademarks & others 575/585]
A32: Note 7. Investments
B33: 2021 | C33: 2020
A34: Investment in subsidiaries - Equity shares | B34: 26467 | C34: 21142
A35: Investment in subsidiaries - Preference shares | B35: 1658 | C35: 562
A36: Investment in Associates - Equity shares | B36: 686 | C36: 668
A37: Investment in Associates - Compulsorily Convertible Preference Shares | B37: 315 | C37: 240
A38: Financial instruments at FVTPL - Liquid and short-term mutual funds | B38: 31340 | C38: 32108
A39: Financial instruments at FVTPL - Equity linked debentures | B39: 1558 | C39: 0
A40: Financial instruments at FVTPL - Convertible preference shares | B40: 150 | C40: 0
A41: Financial instruments at FVTOCI - Non-convertible debentures and bonds | B41: 16395 | C41: 15125
A42: Financial instruments at amortized cost - Tax saving bond | B42: 0 | C42: 5
A43: Financial instruments at amortized cost - Redeemable preference shares (net of impairment) | B43: 1450 | C43: 1955
A44: Total investments | B44: 80020 | C44: 71798
A45: Current | B45: 49294 | C45: 47238
... A49: Aggregate impairment in value of investments | B49: 0 | C49: 250
A51: Note 8. Loan (unsecured, considered good)
B52: 2021 | C52: 2020
A53: Non-current - Security deposits | B53: 2 | C53: 99
A54: Non-current - Loans to subsidiaries | B54: 16977 | C54: 384
A55: Total non-current | B55: 16979 | C55: 483
A56: Current - Security deposits | B56: 100 | C56: 0
A57: Current - Inter corporate deposits | B57: 3518 | C57: 0
A58: Current - Receivables from related parties | B58: 338 | C58: 237
A59: Total current | B59: 3956 | C59: 237
A61: Note 9. Other financial assets
B62: 2021 | C62: 2020
A63: Non-current - Finance lease receivables | B63: 18 | C63: 0
A64: Current - Contract assets | B64: 278 | C64: 226
A65: Current - Interest receivable | B65: 452 | C65: 23
A66: Current - Loans and advances to employees | B66: 3 | C66: 2
A67: Current - Finance lease receivables | B67: 4 | C67: 0
A68: Total current | B68: 737 | C68: 251
A70: Note 10. Other Assets
B71: 2021 | C71: 2020
A72: Non-current - Capital advances | B72: 105 | C72: 108
A73: Non-current - Prepaid expenses | B73: 7 | C73: 7
A74: Non-current - Others | B74: 0 | C74: 5
A75: Total non-current | B75: 112 | C75: 120
A76: Current - Advance to suppliers | B76: 427 | C76: 263
A77: Current - Balances with government/statutory authorities | B77: 1014 | C77: 1996
A78: Current - Prepaid expenses | B78: 131 | C78: 152
A79: Current - Others (incl. claims receivable) | B79: 1259 | C79: 1529
A80: Total current (net of allowance) | B80: 2832 | C80: 3941
A82: Note 11. Inventories
B83: 2021 | C83: 2020
A84: Raw materials | B84: 2011 | C84: 1742
A85: Work in progress | B85: 1790 | C85: 1578
A86: Finished products | B86: 375 | C86: 854
A87: Traded products | B87: 1281 | C87: 1354
A88: Stores and spares | B88: 321 | C88: 318
A89: Total inventories | B89: 5778 | C89: 5846
A91: Note 12. Trade receivables
B92: 2021 | C92: 2020
A93: Considered good | B93: 7451 | C93: 4309
A94: Credit impaired | B94: 352 | C94: 357
A95: Less: Allowance for doubtful receivables | B95: -352 | C95: -357
A96: Net trade receivables | B96: 7451 | C96: 4309
A97: Allowance movement - Balance at beginning of year | B97: 357 | C97: 228
A98: Allowance movement - Addition during the year, net | B98: 35 | C98: 188
A99: Allowance movement - Uncollectable receivables charged against allowance | B99: 40 | C99: 59
A100: Allowance movement - Balance at end of year | B100: 352 | C100: 357
A102: Note 13. Derivative assets
B103: 2021 | C103: 2020
A104: FVTOCI - Foreign exchange forward contracts | B104: 16 | C104: 1
A105: FVTOCI - Interest rate swaps | B105: 79 | C105: 0
A106: FVTPL - Foreign exchange forward contracts | B106: 0 | C106: 1
A107: Total | B107: 95 | C107: 2
A109: Note 14. Cash and cash equivalents
B110: 2021 | C110: 2020
A111: Balances with banks - in current account | B111: 691 | C111: 1135
A112: Balances with banks - in deposit account | B112: 80 | C112: 90
A113: Cheques, drafts on hand | B113: 768 | C113: 120
A114: Remittance in transit | B114: 7 | C114: 4
...

Sheet BS 2021-22
A1: Wipro Enterprises (P) Limited (Standalone)
A2: Balance Sheet
A3: Balance Sheet as at March 31, 2022 (Source: Annual Report 2021-22, Wipro-Enterprises-AR-2021-2022_LowRez-2.pdf, p.60). *2021 figures restated for merger, refer Note 46.
A4: (Amount Rs. in millions, unless otherwise stated)
A6: Particulars | B6: 2022 | C6: 2021*
A7: ASSETS
A8: Non-current assets
A9: Property, plant and equipment | B9: 8897 | C9: 6857
A10: Capital work-in-progress | B10: 1200 | C10: 2270
A11: Right of use assets | B11: 807 | C11: 853
A12: Goodwill | B12: 362 | C12: 497
A13: Other intangible assets | B13: 1101 | C13: 766
A14: Financial assets - Investments | B14: 32460 | C14: 30628
A15: Financial assets - Trade receivables | B15: 272 | C15: 250
A16: Financial assets - Loans | B16: 17133 | C16: 15247
A17: Financial assets - Other financial assets | B17: 58 | C17: 26
A18: Other assets | B18: 135 | C18: 388
A19: Total non-current assets | B19: 62425 | C19: 57782
A20: Current assets
A21: Inventories | B21: 8616 | C21: 5896
A22: Financial assets - Investments | B22: 54972 | C22: 49403
A23: Financial assets - Trade receivables | B23: 6017 | C23: 7201
A24: Financial assets - Derivative instruments | B24: 304 | C24: 95
A25: Financial assets - Cash and cash equivalents | B25: 2742 | C25: 1654
A26: Financial assets - Loans | B26: 251 | C26: 3518
A27: Financial assets - Other financial assets | B27: 1638 | C27: 897
A28: Current tax assets (net) | B28: 720 | C28: 243
A29: Other assets | B29: 2914 | C29: 3213
A30: Total current assets | B30: 78174 | C30: 72120
A31: TOTAL ASSETS | B31: 140599 | C31: 129902
A32: EQUITY AND LIABILITIES
A33: Equity
A34: Share capital | B34: 4837 | C34: 4837
A35: Other equity | B35: 96046 | C35: 88351
A36: Total equity | B36: 100883 | C36: 93188
A37: Non-current liabilities
A38: Financial liabilities - Borrowings | B38: 18967 | C38: 17375
A39: Financial liabilities - Lease liabilities | B39: 32 | C39: 61
A40: Financial liabilities - Other financial liabilities | B40: 1103 | C40: 1023
A41: Provisions | B41: 138 | C41: 105
A42: Deferred tax liabilities (net) | B42: 1294 | C42: 1500
A43: Total non-current liabilities | B43: 21534 | C43: 20064
A44: Current liabilities
A45: Financial liabilities - Borrowings | B45: 2862 | C45: 2230
A46: Financial liabilities - Lease liabilities | B46: 119 | C46: 128
A47: Financial liabilities - Derivative liabilities | B47: 633 | C47: 151
A48: Trade payables - dues of micro & small enterprises | B48: 1262 | C48: 1154
A49: Trade payables - dues of other creditors | B49: 9146 | C49: 9984
A50: Financial liabilities - Other financial liabilities | B50: 1470 | C50: 1242
A51: Other liabilities | B51: 1419 | C51: 1293
A52: Provisions | B52: 97 | C52: 94
A53: Current tax liabilities (net) | B53: 1174 | C53: 374
A54: Total current liabilities | B54: 18182 | C54: 16650
A55: TOTAL EQUITY AND LIABILITIES | B55: 140599 | C55: 129902

Sheet PL 2021-22
A1: Wipro Enterprises (P) Limited (Standalone)
A2: Statement of Profit and Loss
A3: Statement of Profit and Loss for the year ended March 31, 2022 (Source: Annual Report 2021-22, p.61). *2021 figures restated for merger, refer Note 46.
A4: (Amount Rs. in millions, unless otherwise stated)
A6: Particulars | B6: 2022 | C6: 2021*
A7: REVENUE
A8: Revenue from operations | B8: 57884 | C8: 50849
A9: Other income | B9: 5900 | C9: 6895
A10: Total income | B10: 63784 | C10: 57743
A11: EXPENSES
A12: Cost of materials consumed | B12: 19806 | C12: 19375
A13: Purchases of stock-in-trade | B13: 16070 | C13: 8407
A14: Changes in inventories of finished products, WIP and stock-in-trade | B14: -1762 | C14: 313
A15: Employee benefits expense | B15: 4944 | C15: 4556
A16: Finance costs | B16: 1129 | C16: 784
A17: Depreciation and amortisation expense | B17: 990 | C17: 940
A18: Other expenses | B18: 12035 | C18: 11273
A19: Total expenses | B19: 53210 | C19: 45647
A20: Profit before tax | B20: 10574 | C20: 12096
A21: Tax expense
A22: Current tax | B22: 2411 | C22: 2125
A23: Deferred tax | B23: -14 | C23: 237
A24: Total tax expenses | B24: 2397 | C24: 2362
A25: Profit for the year | B25: 8177 | C25: 9734
A26: Other comprehensive income, net of taxes
A27: Remeasurement of defined benefit liability/asset (net of tax) | B27: -6 | C27: -1
A28: Net change in FV of financial instruments through OCI (net of tax) | B28: -624 | C28: 408
A29: Net change in FV of cash flow hedge (net of tax) | B29: 147 | C29: 65
A30: Total other comprehensive income for the year, net of taxes | B30: -483 | C30: 472
A31: Total comprehensive income for the year | B31: 7694 | C31: 10206
A32: Earnings per equity share (par value Rs.10 each)
A33: Weighted average equity shares for computing basic and diluted EPS | B33: 483662163 | C33: 483662163
A34: Basic and diluted EPS (Rs.) | B34: 16.91 | C34: 20.13

Sheet CF 2021-22
A1: Wipro Enterprises (P) Limited (Standalone)
A2: Statement of Cash Flows
A3: Statement of Cash Flows for the year ended March 31, 2022 (Source: Annual Report 2021-22, p.63). *2021 figures restated for merger, refer Note 46.
A4: (Amount Rs. in millions, unless otherwise stated)
A6: Particulars | B6: 2022 | C6: 2021*
A7: A. Cash flows from operating activities
A8: Profit before tax | B8: 10574 | C8: 12096
A9: Depreciation and amortization | B9: 990 | C9: 940
A10: Interest on borrowings | B10: 1129 | C10: 784
A11: Unrealized (gain)/loss on investments | B11: 189 | C11: -1719
A12: Dividend / interest income | B12: -2447 | C12: -2016
A13: Net (gain)/loss on sale of current investments | B13: -2938 | C13: -1001
A14: Net (gain)/loss on sale of associates | B14: 0 | C14: -1762
A15: Net (gain)/loss on sale of PP&E and intangible assets | B15: -31 | C15: -32
A16: Allowance for doubtful receivables | B16: -19 | C16: -5
A17: Net foreign exchange differences on non-operating items | B17: -54 | C17: -6
A18: Working capital changes - Trade receivables | B18: 1181 | C18: -3246
A19: Working capital changes - Other assets | B19: -397 | C19: 953
... A24: Net cash generated from operating activities | B24: 3121 | C24: 5377
A25: B. Cash flows from investing activities
A26: Acquisition of PP&E including capital advances | B26: -2192 | C26: -1601
A27: Proceeds from sale of PP&E | B27: 31 | C27: 32
A28: Investment in associates | B28: -255 | C28: -105
A29: Purchase of current investments | B29: -90543 | C29: -101201
A30: Purchase of non-current investments | B30: -75 | C30: -150
A31: Proceeds from sale/maturity of current investments | B31: 87684 | C31: 103271
A32: Proceeds from sale of investment in associates | B32: 450 | C32: 1774
A33: Investment in subsidiaries | B33: -1659 | C33: -5348
A34: Loan to subsidiaries | B34: -2136 | C34: -16448
A35: Inter-corporate deposits placed | B35: 3518 | C35: -3518
A36: Dividend / interest income received | B36: 2077 | C36: 1047
A37: Net cash used in investing activities | B37: -3100 | C37: -22247
A38: C. Cash flows from financing activities
A39: Interest paid on borrowings | B39: -1114 | C39: -778
A40: Proceeds from borrowings / debentures | B40: 11326 | C40: 19407
A41: Repayment of lease liabilities | B41: -56 | C41: -77
A42: Repayment of borrowings / loans | B42: -9090 | C42: -1407
A43: Net cash generated from/(used in) financing activities | B43: 1066 | C43: 17145
A44: Net increase/(decrease) in cash and cash equivalents during the year | B44: 1088 | C44: 275
A45: Cash and cash equivalents at the beginning of the year | B45: 1654 | C45: 1379
A46: Cash and cash equivalents at the end of the year | B46: 2742 | C46: 1654
A47: Components of cash and cash equivalents
A48: Balances with banks - in current accounts | B48: 1390 | C48: 798
A49: Balances with banks - in deposit accounts | B49: 120 | C49: 80
A50: Cheques, drafts on hand | B50: 1214 | C50: 768
A51: Remittance in transit | B51: 18 | C51: 7
A52: Cash in hand (rounded to nil, below Rs.0.5 mn) | B52: 0 | C52: 0

Sheet _Combined Balance Sheet
B2: Particulars | C2: 2020 | D2: 2021
B3: ASSETS
B4: Non-current assets
B5: Property, plant and equipment | C5: 6866 | D5: =IFERROR(INDEX('BS 2021-22'!C9:C18,MATCH('_Combined Balance Sheet'!B5,'BS 2021-22'!A9:A19,0)),0) -> 6857
B6: Capital work-in-progress | C6: 578 | D6: =IFERROR(INDEX('BS 2021-22'!C10:C19,MATCH('_Combined Balance Sheet'!B6,'BS 2021-22'!A10:A20,0)),0) -> 2270
B7: Right of use assets | C7: 948 | D7: =IFERROR(INDEX('BS 2021-22'!C11:C20,MATCH('_Combined Balance Sheet'!B7,'BS 2021-22'!A11:A21,0)),0) -> 853
B8: Goodwill | C8: 497 | D8: =IFERROR(INDEX('BS 2021-22'!C12:C21,MATCH('_Combined Balance Sheet'!B8,'BS 2021-22'!A12:A22,0)),0) -> 497
B9: Other intangible assets | C9: 791 | D9: =IFERROR(INDEX('BS 2021-22'!C13:C22,MATCH('_Combined Balance Sheet'!B9,'BS 2021-22'!A13:A23,0)),0) -> 766
B10: Financial assets - Investments | C10: 24560 | D10: =IFERROR(INDEX('BS 2021-22'!C14:C23,MATCH('_Combined Balance Sheet'!B10,'BS 2021-22'!A14:A24,0)),0) -> 30628
B11: Financial assets - Loans | C11: 483 | D11: =IFERROR(INDEX('BS 2021-22'!C15:C24,MATCH('_Combined Balance Sheet'!B11,'BS 2021-22'!A15:A25,0)),0) -> 15247
B12: Financial assets - Other financial assets | C12: 0 | D12: =IFERROR(INDEX('BS 2021-22'!C16:C25,MATCH('_Combined Balance Sheet'!B12,'BS 2021-22'!A16:A26,0)),0) -> 26
B13: Other non-current assets | C13: 120 | D13: =IFERROR(INDEX('BS 2021-22'!C17:C26,MATCH('_Combined Balance Sheet'!B13,'BS 2021-22'!A17:A27,0)),0) -> 0
B14: Total non-current assets | C14: 34843 | D14: =IFERROR(INDEX('BS 2021-22'!C18:C27,MATCH('_Combined Balance Sheet'!B14,'BS 2021-22'!A18:A28,0)),0) -> 57782
B15: Current assets
B16: Inventories | C16: 5846 | D16: =IFERROR(INDEX('BS 2021-22'!C21:C31,MATCH('_Combined Balance Sheet'!B16,'BS 2021-22'!A21:A31,0)),0) -> 5896
B17: Financial assets - Investments | C17: 47238 | D17: =IFERROR(INDEX('BS 2021-22'!C22:C32,MATCH('_Combined Balance Sheet'!B17,'BS 2021-22'!A22:A32,0)),0) -> 49403
B18: Financial assets - Trade receivables | C18: 4309 | D18: =IFERROR(INDEX('BS 2021-22'!C23:C33,MATCH('_Combined Balance Sheet'!B18,'BS 2021-22'!A23:A33,0)),0) -> 7201
B19: Financial assets - Derivative instruments | C19: 2 | D19: =IFERROR(INDEX('BS 2021-22'!C24:C34,MATCH('_Combined Balance Sheet'!B19,'BS 2021-22'!A24:A34,0)),0) -> 95
B20: Financial assets - Cash and cash equivalents | C20: 1350 | D20: =IFERROR(INDEX('BS 2021-22'!C25:C35,MATCH('_Combined Balance Sheet'!B20,'BS 2021-22'!A25:A35,0)),0) -> 1654
B21: Financial assets - Loans | C21: 237 | D21: =IFERROR(INDEX('BS 2021-22'!C26:C36,MATCH('_Combined Balance Sheet'!B21,'BS 2021-22'!A26:A36,0)),0) -> 3518
B22: Financial assets - Other financial assets | C22: 251 | D22: =IFERROR(INDEX('BS 2021-22'!C27:C37,MATCH('_Combined Balance Sheet'!B22,'BS 2021-22'!A27:A37,0)),0) -> 897
B23: Current tax assets (net) | C23: 304 | D23: =IFERROR(INDEX('BS 2021-22'!C28:C38,MATCH('_Combined Balance Sheet'!B23,'BS 2021-22'!A28:A38,0)),0) -> 243
B24: Other assets | C24: 3941 | D24: =IFERROR(INDEX('BS 2021-22'!C29:C39,MATCH('_Combined Balance Sheet'!B24,'BS 2021-22'!A29:A39,0)),0) -> 3213
B25: Total current assets | C25: 63478 | D25: =IFERROR(INDEX('BS 2021-22'!C30:C40,MATCH('_Combined Balance Sheet'!B25,'BS 2021-22'!A30:A40,0)),0) -> 72120
B26: TOTAL ASSETS | C26: 98321 | D26: =IFERROR(INDEX('BS 2021-22'!C31:C41,MATCH('_Combined Balance Sheet'!B26,'BS 2021-22'!A31:A41,0)),0) -> 129902
B27: EQUITY AND LIABILITIES
B28: Equity
B29: Share capital | C29: 4837 | D29: =IFERROR(INDEX('BS 2021-22'!C34:C36,MATCH('_Combined Balance Sheet'!B29,'BS 2021-22'!A34:A35,0)),0) -> 4837
B30: Other equity | C30: 78152 | D30: =IFERROR(INDEX('BS 2021-22'!C35:C37,MATCH('_Combined Balance Sheet'!B30,'BS 2021-22'!A35:A36,0)),0) -> 88351
B31: Total equity | C31: 82989
B32: Non-current liabilities
B33: Financial liabilities - Borrowings | C33: 1192 | D33: =IFERROR(INDEX('BS 2020-21'!C37:C42,MATCH('_Combined Balance Sheet'!B33,'BS 2020-21'!A37:A42,0)),0) -> 1192
B34: Financial liabilities - Lease liabilities | C34: 130 | D34: =IFERROR(INDEX('BS 2020-21'!C38:C43,MATCH('_Combined Balance Sheet'!B34,'BS 2020-21'!A38:A43,0)),0) -> 130
B35: Financial liabilities - Other financial liabilities | C35: 28 | D35: =IFERROR(INDEX('BS 2020-21'!C39:C44,MATCH('_Combined Balance Sheet'!B35,'BS 2020-21'!A39:A44,0)),0) -> 28
B36: Provisions | C36: 183 | D36: =IFERROR(INDEX('BS 2020-21'!C40:C45,MATCH('_Combined Balance Sheet'!B36,'BS 2020-21'!A40:A45,0)),0) -> 183
B37: Deferred tax liabilities (net) | C37: 1224 | D37: =IFERROR(INDEX('BS 2020-21'!C41:C46,MATCH('_Combined Balance Sheet'!B37,'BS 2020-21'!A41:A46,0)),0) -> 1224
B38: Total non-current liabilities | C38: 2757 | D38: =IFERROR(INDEX('BS 2020-21'!C42:C47,MATCH('_Combined Balance Sheet'!B38,'BS 2020-21'!A42:A47,0)),0) -> 2757
B39: Current assets
B40: Financial liabilities - Borrowings | C40: 761 | D40: =IFERROR(INDEX('BS 2020-21'!C44:C55,MATCH('_Combined Balance Sheet'!B40,'BS 2020-21'!A44:A55,0)),0) -> 761
B41: Financial liabilities - Lease liabilities | C41: 118 | D41: =IFERROR(INDEX('BS 2020-21'!C45:C56,MATCH('_Combined Balance Sheet'!B41,'BS 2020-21'!A45:A56,0)),0) -> 118
B42: Financial liabilities - Derivative liabilities | C42: 11 | D42: =IFERROR(INDEX('BS 2020-21'!C46:C57,MATCH('_Combined Balance Sheet'!B42,'BS 2020-21'!A46:A57,0)),0) -> 11
B43: Trade payables - dues of micro & small enterprises | C43: 179 | D43: =IFERROR(INDEX('BS 2020-21'!C47:C58,MATCH('_Combined Balance Sheet'!B43,'BS 2020-21'!A47:A58,0)),0) -> 179
B44: Trade payables - dues of other creditors | C44: 8730 | D44: =IFERROR(INDEX('BS 2020-21'!C48:C59,MATCH('_Combined Balance Sheet'!B44,'BS 2020-21'!A48:A59,0)),0) -> 8730
B45: Current maturities of long-term debt | C45: 794 | D45: =IFERROR(INDEX('BS 2020-21'!C49:C60,MATCH('_Combined Balance Sheet'!B45,'BS 2020-21'!A49:A60,0)),0) -> 794
B46: Financial liabilities - Other financial liabilities | C46: 469 | D46: =IFERROR(INDEX('BS 2020-21'!C50:C61,MATCH('_Combined Balance Sheet'!B46,'BS 2020-21'!A50:A61,0)),0) -> 469
B47: Other current liabilities | C47: 1099 | D47: =IFERROR(INDEX('BS 2020-21'!C51:C62,MATCH('_Combined Balance Sheet'!B47,'BS 2020-21'!A51:A62,0)),0) -> 1099
B48: Provisions | C48: 203 | D48: =IFERROR(INDEX('BS 2020-21'!C52:C63,MATCH('_Combined Balance Sheet'!B48,'BS 2020-21'!A52:A63,0)),0) -> 203
B49: Current tax liabilities (net) | C49: 211 | D49: =IFERROR(INDEX('BS 2020-21'!C53:C64,MATCH('_Combined Balance Sheet'!B49,'BS 2020-21'!A53:A64,0)),0) -> 211
B50: Total current liabilities | C50: 12575 | D50: =IFERROR(INDEX('BS 2020-21'!C54:C65,MATCH('_Combined Balance Sheet'!B50,'BS 2020-21'!A54:A65,0)),0) -> 12575
B51: TOTAL EQUITY AND LIABILITIES | C51: 98321 | D51: =IFERROR(INDEX('BS 2020-21'!C55:C66,MATCH('_Combined Balance Sheet'!B51,'BS 2020-21'!A55:A66,0)),0) -> 98321

Sheet Notes 2021-22
A1: Wipro Enterprises (P) Limited (Standalone)
A2: Notes to the Standalone Financial Statements (Selected Notes)
A3: Notes to the Standalone Financial Statements, year ended March 31, 2022 (Source: Annual Report 2021-22, pp.75-110)
A4: (Amount Rs. in millions, unless otherwise stated)
A6: Note 4. Property, plant and equipment - Net carrying value (*restated for merger)
B7: 2022 | C7: 2021*
A8: Land | B8: 491 | C8: 208
A9: Buildings | B9: 3708 | C9: 2137
A10: Plant and Machinery | B10: 4525 | C10: 4366
A11: Furniture and Fixtures | B11: 70 | C11: 44
A12: Office Equipment | B12: 100 | C12: 102
A13: Vehicles | B13: 3 | C13: 1
A14: Total | B14: 8897 | C14: 6858
A16: Note 5. Capital work-in-progress - ageing (Projects in progress)
B17: 2022 | C17: 2021*
A18: Less than 1 year | B18: 756 | C18: 1769
A19: 1-2 years | B19: 419 | C19: 281
A20: 2-3 years | B20: 22 | C20: 103
A21: More than 3 years | B21: 3 | C21: 117
A22: Total CWIP | B22: 1200 | C22: 2270
A24: Note 6. Right-of-use assets - Net carrying value
B25: 2022 | C25: 2021*
A26: Land | B26: 675 | C26: 683
A27: Buildings | B27: 123 | C27: 152
A28: Furniture and Fixtures | B28: 7 | C28: 13
A29: Vehicles | B29: 4 | C29: 6
A30: Total | B30: 807 | C30: 853
A32: Note 7. Goodwill and intangible assets - movement in Goodwill
B33: 2022 | C33: 2021*
A34: Amount at the beginning of the year | B34: 497 | C34: 497
A35: Deletion during the year (sale of automation division) | B35: -135 | C35: 0
A36: Amount at the end of the year | B36: 362 | C36: 497
A37: Net block of other intangible assets: 1,101 (2022), 766 (2021) [Technical know-how 177/191; Brands, patents, trademarks & others 924/575]
A39: Note 8. Investments
B40: 2022 | C40: 2021*
A41: Investments in subsidiaries - Equity shares | B41: 28071 | C41: 26369
A42: Investments in subsidiaries - Preference shares | B42: 1658 | C42: 1658
A43: Investments in Associates - Equity shares | B43: 741 | C43: 686
A44: Investments in Associates - Compulsorily convertible preference shares | B44: 515 | C44: 315
A45: FVTPL - Liquid and short-term mutual funds | B45: 34618 | C45: 31448
A46: FVTPL - Equity-linked debentures | B46: 2185 | C46: 1558
A47: FVTPL - Compulsorily convertible preference shares | B47: 525 | C47: 150
A48: FVTOCI - Non-convertible debentures and bonds | B48: 18169 | C48: 16396
A49: Amortized cost - Redeemable preference shares | B49: 950 | C49: 1450
A50: Total investments | B50: 87432 | C50: 80031
A51: Current | B51: 54972 | C51: 49403
A52: Non-current | B52: 32460 | C52: 30628
... A55: Aggregate impairment in value of investments | B55: 0 | C55: 0
A57: Note 9. Loan (unsecured, considered good)
B58: 2022 | C58: 2021*
A59: Non-current - Loans to subsidiaries | B59: 17133 | C59: 15247
A60: Current - Loans to subsidiaries | B60: 251 | C60: 0
A61: Current - Inter corporate deposits | B61: 0 | C61: 3518
A63: Note 10. Other financial assets
B64: 2022 | C64: 2021*
A65: Non-current - Security deposits | B65: 18 | C65: 2
A66: Non-current - Others | B66: 40 | C66: 24
A67: Total non-current | B67: 58 | C67: 26
A68: Current - Security deposits | B68: 100 | C68: 100
A69: Current - Interest receivable | B69: 530 | C69: 452
A70: Current - Loans and advances to employees | B70: 7 | C70: 3
A71: Current - Receivables from related parties | B71: 988 | C71: 338
A72: Current - Others | B72: 13 | C72: 4
A73: Total current | B73: 1638 | C73: 897
A75: Note 11. Other Assets
B76: 2022 | C76: 2021*
A77: Non-current - Capital advances | B77: 128 | C77: 381
A78: Non-current - Prepaid expenses | B78: 7 | C78: 7
A79: Total non-current | B79: 135 | C79: 388
A80: Current - Advance to suppliers | B80: 522 | C80: 427
A81: Current - Balances with government/statutory authorities | B81: 1095 | C81: 1014
A82: Current - Prepaid expenses | B82: 233 | C82: 131
A83: Current - Contract assets | B83: 119 | C83: 278
A84: Current - Others (incl. claims receivable) | B84: 945 | C84: 1363
A85: Total current (net of allowance) | B85: 2914 | C85: 3213
A87: Note 12. Inventories
B88: 2022 | C88: 2021*
A89: Raw materials | B89: 3051 | C89: 2101
A90: Work in progress | B90: 2189 | C90: 1804
A91: Finished products | B91: 1256 | C91: 389
A92: Traded products | B92: 1791 | C92: 1281
A93: Stores and spares | B93: 329 | C93: 321
A94: Total inventories | B94: 8616 | C94: 5896
A96: Note 13. Trade receivables
B97: 2022 | C97: 2021*
A98: Non-current - Considered good | B98: 272 | C98: 250
A99: Current - Considered good | B99: 6186 | C99: 7373
A100: Current - Credit impaired - Disputed receivables | B100: 164 | C100: 180
A101: Current - Less: Allowance for doubtful receivables | B101: -333 | C101: -352
A102: Net current trade receivables | B102: 6017 | C102: 7201
A103: Allowance movement - Balance at beginning of year | B103: 352 | C103: 357
A104: Allowance movement - Addition during the year, net | B104: 20 | C104: 35
A105: Allowance movement - Uncollectable receivables charged against allowance | B105: -39 | C105: -40
A106: Allowance movement - Balance at end of year | B106: 333 | C106: 352
A108: Note 14. Derivative assets
B109: 2022 | C109: 2021*
A110: FVTOCI - Foreign exchange forward contracts | B110: 9 | C110: 16
A111: FVTOCI - Interest rate swaps | B111: 295 | C111: 79
A112: Total | B112: 304 | C112: 95
A114: Note 15. Cash and cash equivalents
...

Sheet BS 2022-23
A1: Wipro Enterprises (P) Limited (Standalone)
A2: Balance Sheet
A3: Balance Sheet as at March 31, 2023 (Source: Annual Report 2022-23, New-Annual_Report_Wipro_Enterprises_2022-2023.pdf, p.72)
A4: (Amount Rs. in millions, unless otherwise stated)
A6: Particulars | B6: 2023 | C6: 2022
A7: ASSETS
A8: Non-current assets
A9: Property, plant and equipment | B9: 9793 | C9: 8897
A10: Capital work-in-progress | B10: 304 | C10: 1200
A11: Right of use assets | B11: 800 | C11: 807
A12: Goodwill | B12: 362 | C12: 362
A13: Other intangible assets | B13: 1723 | C13: 1101
A14: Financial assets - Investments | B14: 33415 | C14: 32785
A15: Financial assets - Trade receivables | B15: 99 | C15: 272
A16: Financial assets - Derivative instruments | B16: 1 | C16: 0 | G16: =B9 -> 9793
A17: Financial assets - Loans | B17: 15048 | C17: 17366 | G17: =SUM(B10) -> 304
A18: Financial assets - Other financial assets | B18: 4 | C18: 58 | G18: =SUM(C14) -> 32785
A19: Non current tax assets (net) | B19: 661 | C19: 720 | G19: =SUM(B11:B13,B15:B20) -> 19592
A20: Other assets | B20: 894 | C20: 839
A21: Total non-current assets | B21: 63104 | C21: 64407
A22: Current assets
A23: Inventories | B23: 8069 | C23: 8616
A24: Financial assets - Investments | B24: 67114 | C24: 54972
A25: Financial assets - Trade receivables | B25: 6799 | C25: 5784
A26: Financial assets - Derivative instruments | B26: 0 | C26: 9
A27: Financial assets - Cash and cash equivalents | B27: 1597 | C27: 2742
A28: Financial assets - Loans | B28: 5324 | C28: 251
A29: Financial assets - Other financial assets | B29: 2017 | C29: 1313
A30: Other assets | B30: 1764 | C30: 2210
A31: Assets held for sale | B31: 53 | C31: 0
A32: Total current assets | B32: 92737 | C32: 75897
A33: TOTAL ASSETS | B33: 155841 | C33: 140304
A34: EQUITY AND LIABILITIES
A35: Equity
A36: Share capital | B36: 4837 | C36: 4837
A37: Other equity | B37: 106557 | C37: 96046
A38: Total equity | B38: 111394 | C38: 100883
A39: Non-current liabilities
A40: Financial liabilities - Borrowings | B40: 14985 | C40: 18967
A41: Financial liabilities - Lease liabilities | B41: 22 | C41: 32
A42: Financial liabilities - Derivative instruments | B42: 1571 | C42: 338
A43: Provisions | B43: 10 | C43: 75
A44: Deferred tax liabilities (net) | B44: 1018 | C44: 1294
A45: Total non-current liabilities | B45: 17606 | C45: 20706
A46: Current liabilities
A47: Financial liabilities - Borrowings | B47: 9850 | C47: 2862
A48: Financial liabilities - Lease liabilities | B48: 83 | C48: 119
A49: Financial liabilities - Derivative liabilities | B49: 516 | C49: 0
A50: Trade payables - dues of micro & small enterprises | B50: 1214 | C50: 1262
A51: Trade payables - dues of other creditors | B51: 11061 | C51: 9716
A52: Financial liabilities - Other financial liabilities | B52: 1706 | C52: 2002
A53: Other liabilities | B53: 1109 | C53: 1419
A54: Provisions | B54: 199 | C54: 161
A55: Current tax liabilities (net) | B55: 1103 | C55: 1174
A56: Total current liabilities | B56: 26841 | C56: 18715
A57: TOTAL EQUITY AND LIABILITIES | B57: 155841 | C57: 140304

Sheet PL 2022-23
A1: Wipro Enterprises (P) Limited (Standalone)
A2: Statement of Profit and Loss
A3: Statement of Profit and Loss for the year ended March 31, 2023 (Source: Annual Report 2022-23, p.73)
A4: (Amount Rs. in millions, unless otherwise stated)
A6: Particulars | B6: 2023 | C6: 2022
A7: REVENUE
A8: Revenue from operations | B8: 70052 | C8: 57884
A9: Other income | B9: 7572 | C9: 5711
A10: Total income | B10: 77624 | C10: 63595
A11: EXPENSES
A12: Cost of materials consumed | B12: 37573 | C12: 29030
A13: Purchases of stock-in-trade | B13: 3163 | C13: 6846
A14: Changes in inventories of finished products, WIP and stock-in-trade | B14: 594 | C14: -1762
A15: Employee benefits expense | B15: 5585 | C15: 4944
A16: Finance costs | B16: 1254 | C16: 1129
A17: Depreciation and amortisation expense | B17: 1151 | C17: 990
A18: Other expenses | B18: 15329 | C18: 11844
A19: Total Expenses | B19: 64649 | C19: 53021
A20: Profit before tax | B20: 12975 | C20: 10574
A21: Tax expense
A22: Current tax | B22: 2501 | C22: 2411
A23: Deferred tax | B23: -214 | C23: -14
A24: Total tax expenses | B24: 2287 | C24: 2397
A25: Profit for the year | B25: 10688 | C25: 8177
A26: Other comprehensive income, net of taxes
A27: Remeasurement of defined benefit liability/asset (net of tax) | B27: 9 | C27: -6
A28: Net change in FV of financial instruments through OCI (net of tax) | B28: -213 | C28: -624
A29: Net change in FV of cash flow hedge (net of tax) | B29: 27 | C29: 147
A30: Total other comprehensive income for the year, net of taxes | B30: -177 | C30: -483
A31: Total comprehensive income for the year | B31: 10511 | C31: 7694
A32: Earnings per equity share (par value Rs.10 each)
A33: Weighted average equity shares for computing basic and diluted EPS | B33: 483662163 | C33: 483662163
A34: Basic and diluted EPS (Rs.) | B34: 22.1 | C34: 16.91

Sheet CF 2022-23
A1: Wipro Enterprises (P) Limited (Standalone)
A2: Statement of Cash Flows
A3: Statement of Cash Flows for the year ended March 31, 2023 (Source: Annual Report 2022-23, p.75)
A4: (Amount Rs. in millions, unless otherwise stated)
A6: Particulars | B6: 2023 | C6: 2022
A7: A. Cash flows from operating activities
A8: Profit before tax | B8: 12975 | C8: 10574
A9: Depreciation and amortization | B9: 1151 | C9: 990
A10: Interest on borrowings | B10: 1254 | C10: 1129
A11: Dividend / interest income | B11: -3258 | C11: -2447
A12: Net (gain)/loss on sale of current investments | B12: -1397 | C12: -2749
A13: Net (gain)/loss on sale of associates | B13: -2206 | C13: 0
A14: Net (gain)/loss on sale of PP&E and intangible assets | B14: -13 | C14: -31
A15: Allowance for doubtful receivables | B15: 102 | C15: -19
A16: Net foreign exchange differences on non-operating items | B16: -116 | C16: -54
A17: Working capital changes - Trade receivables | B17: -595 | C17: 1181
A18: Working capital changes - Other assets | B18: 73 | C18: -397
A19: Working capital changes - Inventories | B19: 547 | C19: -2720
... A23: Net cash generated from operating activities | B23: 6874 | C23: 3121
A24: B. Cash flows from investing activities
A25: Acquisition of PP&E including capital advances | B25: -1662 | C25: -2158
A26: Proceeds from sale of PP&E | B26: 13 | C26: 31
A27: Investment in associates | B27: -5 | C27: -255
A28: Purchase of current investments | B28: -104256 | C28: -90543
A29: Purchase of non-current investments | B29: -335 | C29: -75
A30: Proceeds from sale/maturity of current investments | B30: 95771 | C30: 87684
A31: Proceeds from sale of investment in associates | B31: 2217 | C31: 450
A32: Investment in subsidiaries | B32: -572 | C32: -1659
A33: Loan to subsidiaries | B33: -3313 | C33: -2136
A34: Inter-corporate deposits placed | B34: 0 | C34: 3518
A35: Dividend / interest income received | B35: 2460 | C35: 2077
A36: Net cash used in investing activities | B36: -9682 | C36: -3066
A37: C. Cash flows from financing activities
A38: Interest paid on borrowings | B38: -1242 | C38: -1114
A39: Proceeds from borrowings / debentures | B39: 5520 | C39: 11326
A40: Repayment of lease liabilities | B40: -101 | C40: -90
A41: Repayment of borrowings / loans | B41: -2514 | C41: -9090
A42: Net cash generated from/(used in) financing activities | B42: 1663 | C42: 1032
A43: Net increase/(decrease) in cash and cash equivalents during the year | B43: -1145 | C43: 1088
A44: Cash and cash equivalents at the beginning of the year | B44: 2742 | C44: 1654
A45: Cash and cash equivalents at the end of the year | B45: 1597 | C45: 2742
A46: Components of cash and cash equivalents
A47: Balances with banks - in current accounts | B47: 262 | C47: 1390
A48: Balances with banks - in deposit accounts | B48: 0 | C48: 120
A49: Cheques, drafts on hand | B49: 1184 | C49: 1214
A50: Remittance in transit | B50: 151 | C50: 18
A51: Cash in hand (rounded to nil, below Rs.0.5 mn) | B51: 0 | C51: 0

Sheet Notes 2022-23
A1: Wipro Enterprises (P) Limited (Standalone)
A2: Notes to the Standalone Financial Statements (Selected Notes)
A3: Notes to the Standalone Financial Statements, year ended March 31, 2023 (Source: Annual Report 2022-23, pp.90-136)
A4: (Amount Rs. in millions, unless otherwise stated)
A6: Note 4. Property, plant and equipment - Net carrying value
B7: 2023 | C7: 2022
A8: Land | B8: 425 | C8: 491
A9: Buildings | B9: 3803 | C9: 3708
A10: Plant and Machinery | B10: 5287 | C10: 4525
A11: Furniture and Fixtures | B11: 149 | C11: 70
A12: Office Equipment | B12: 122 | C12: 100
A13: Vehicles | B13: 7 | C13: 3
A14: Total | B14: 9793 | C14: 8897
A16: Note 5. Capital work-in-progress - ageing (Projects in progress)
B17: 2023 | C17: 2022
A18: Less than 1 year | B18: 284 | C18: 756
A19: 1-2 years | B19: 16 | C19: 419
A20: 2-3 years | B20: 4 | C20: 22
A21: More than 3 years | B21: 0 | C21: 3
A22: Total CWIP | B22: 304 | C22: 1200
A24: Note 6. Right-of-use assets - Net carrying value
B25: 2023 | C25: 2022
A26: Land | B26: 699 | C26: 675
A27: Buildings | B27: 96 | C27: 123
A28: Furniture and Fixtures | B28: 1 | C28: 7
A29: Vehicles | B29: 4 | C29: 2
A30: Total | B30: 800 | C30: 807
A32: Note 7. Goodwill and intangible assets - movement in Goodwill
B33: 2023 | C33: 2022
A34: Amount at the beginning of the year | B34: 362 | C34: 497
A35: Deletion during the year | B35: 0 | C35: -135
A36: Amount at the end of the year | B36: 362 | C36: 362
A37: Net block of other intangible assets: 1,723 (2023), 1,101 (2022) [Technical know-how 157/177; Brands, patents, trademarks & others 1,566/924]
A39: Note 8. Investment
B40: 2023 | C40: 2022
A41: Non-current - Investments in subsidiaries - Equity shares | B41: 28133 | C41: 28071
A42: Non-current - Investments in subsidiaries - Redeemable preference shares | B42: 2140 | C42: 1983
A43: Non-current - Investments in Associates - Equity shares | B43: 735 | C43: 741
A44: Non-current - Investments in Associates - Compulsorily convertible preference shares | B44: 595 | C44: 515
A45: Non-current - FVTPL - Compulsorily convertible preference shares | B45: 604 | C45: 524
A46: Non-current - FVTPL - Equity shares | B46: 1 | C46: 1
A47: Non-current - FVTPL - Fixed maturity mutual funds | B47: 257 | C47: 0
A48: Non-current - Amortized cost - Redeemable preference shares | B48: 950 | C48: 950
A49: Total non-current investments | B49: 33415 | C49: 32785
A50: Current - FVTPL - Liquid and short-term mutual funds | B50: 34294 | C50: 34618
A51: Current - FVTPL - Equity-linked debentures | B51: 2108 | C51: 2185
A52: Current - FVTPL - Government securities | B52: 50 | C52: 0
... A57: Aggregate impairment in value of investments | B57: 0 | C57: 0
A59: Note 9. Loan
B60: 2023 | C60: 2022
A61: Non-current - Loans to subsidiaries | B61: 15048 | C61: 17366
A62: Current - Loans to subsidiaries | B62: 5324 | C62: 251
A64: Note 10. Other financial assets
B65: 2023 | C65: 2022
A66: Non-current - Security deposits | B66: 4 | C66: 18
A67: Non-current - Others | B67: 0 | C67: 40
A68: Total non-current | B68: 4 | C68: 58
A69: Current - Security deposits | B69: 123 | C69: 100
A70: Current - Interest receivable | B70: 638 | C70: 530
A71: Current - Loans and advances to employees | B71: 16 | C71: 7
A72: Current - Receivables from related parties | B72: 656 | C72: 663
A73: Current - Receivable on sale of financial instruments | B73: 500 | C73: 0
A74: Current - Others | B74: 84 | C74: 13
A75: Total current | B75: 2017 | C75: 1313
A77: Note 11. Other Assets
B78: 2023 | C78: 2022
A79: Non-current - Capital advances | B79: 72 | C79: 128
A80: Non-current - Prepaid expenses | B80: 5 | C80: 7
A81: Non-current - Deferred trade receivable | B81: 21 | C81: 0
A82: Non-current - Balances with government/statutory authorities | B82: 796 | C82: 704
A83: Total non-current | B83: 894 | C83: 839
A84: Current - Balances with government/statutory authorities | B84: 470 | C84: 1095
A85: Current - Advance to suppliers | B85: 826 | C85: 522
A86: Current - Prepaid expenses | B86: 201 | C86: 233
A87: Current - Contract assets | B87: 71 | C87: 119
A88: Current - Others (incl. claims receivable) | B88: 196 | C88: 241
A89: Total current (net of allowance) | B89: 1764 | C89: 2210
A90: Assets held for sale | B90: 53 | C90: 0
A92: Note 12. Inventories
B93: 2023 | C93: 2022
A94: Raw materials | B94: 3047 | C94: 3051
A95: Work in progress | B95: 2059 | C95: 2189
A96: Finished products | B96: 1588 | C96: 1256
A97: Traded products | B97: 995 | C97: 1791
A98: Stores and spares | B98: 380 | C98: 329
A99: Total inventories | B99: 8069 | C99: 8616
A101: Note 13. Trade receivables
B102: 2023 | C102: 2022
A103: Non-current - Considered good | B103: 99 | C103: 272
A104: Current - Considered good | B104: 7117 | C104: 5953
A105: Current - Credit impaired - Disputed receivables | B105: 117 | C105: 164
A106: Current - Less: Allowance for doubtful receivables | B106: -435 | C106: -333
A107: Net current trade receivables | B107: 6799 | C107: 5784
A108: Allowance movement - Balance at beginning of year | B108: 333 | C108: 352
A109: Allowance movement - Addition during the year, net | B109: 102 | C109: 20
A110: Allowance movement - Uncollectable receivables charged against allowance | B110: 0 | C110: -39
A111: Allowance movement - Balance at end of year | B111: 435 | C111: 333
A113: Note 14. Derivative assets
B114: 2023 | C114: 2022
A115: Non-current - Non designated hedge | B115: 1 | C115: 0
...

Sheet BS 2023-24
A1: Wipro Enterprises (P) Limited (Standalone)
A2: Balance Sheet
A3: Balance Sheet as at March 31, 2024 (Source: Annual Report 2023-24, Annual-Report-2023-24v1.pdf, p.82)
A4: (Amount Rs. in millions, unless otherwise stated)
A6: Particulars | B6: 2024 | C6: 2023
A7: ASSETS
A8: Non-current assets
A9: Property, plant and equipment | B9: 9724 | C9: 9793
A10: Capital work-in-progress | B10: 141 | C10: 195
A11: Intangible asset under development | B11: 140 | C11: 109
A12: Right of use assets | B12: 810 | C12: 800
A13: Goodwill | B13: 1268 | C13: 362
A14: Other intangible assets | B14: 3983 | C14: 1723
A15: Financial assets - Investments | B15: 33176 | C15: 33415
A16: Financial assets - Trade receivables | B16: 45 | C16: 99
A17: Financial assets - Derivative assets | B17: 0 | C17: 1
A18: Financial assets - Loans | B18: 18265 | C18: 15048
A19: Financial assets - Other financial assets | B19: 106 | C19: 4
A20: Non current tax assets (net) | B20: 788 | C20: 661
... A22: Total non-current assets | B22: 69586 | C22: 63104
A23: Current assets
A24: Inventories | B24: 6402 | C24: 8069
A25: Financial assets - Investments | B25: 73332 | C25: 67114
A26: Financial assets - Trade receivables | B26: 7345 | C26: 6799
A27: Financial assets - Derivative assets | B27: 5 | C27: 0
A28: Financial assets - Cash and cash equivalents | B28: 3309 | C28: 1597
A29: Financial assets - Loans | B29: 2727 | C29: 5324
A30: Financial assets - Other financial assets | B30: 1319 | C30: 2017
A31: Other assets | B31: 2063 | C31: 1764
A32: Assets held for sale | B32: 53 | C32: 53
A33: Total current assets | B33: 96555 | C33: 92737
A34: TOTAL ASSETS | B34: 166141 | C34: 155841
A35: EQUITY AND LIABILITIES
A36: Equity
A37: Share capital | B37: 4837 | C37: 4837
A38: Other equity | B38: 119159 | C38: 106557
A39: Total equity | B39: 123996 | C39: 111394
A40: Non-current liabilities
A41: Financial liabilities - Borrowings | B41: 11967 | C41: 14985
A42: Financial liabilities - Lease liabilities | B42: 79 | C42: 22
A43: Financial liabilities - Derivative liabilities | B43: 1255 | C43: 1571
A44: Provisions | B44: 320 | C44: 57
A45: Deferred tax liabilities (net) | B45: 1620 | C45: 1018
A46: Total non-current liabilities | B46: 15241 | C46: 17653
A47: Current liabilities
A48: Financial liabilities - Borrowings | B48: 11032 | C48: 9850
A49: Financial liabilities - Lease liabilities | B49: 27 | C49: 83
A50: Financial liabilities - Derivative liabilities | B50: 452 | C50: 516
A51: Trade payables - dues of micro & small enterprises | B51: 1003 | C51: 1214
A52: Trade payables - dues of other creditors | B52: 11695 | C52: 11061
A53: Financial liabilities - Other financial liabilities | B53: 703 | C53: 1706
A54: Other liabilities | B54: 721 | C54: 1109
A55: Provisions | B55: 163 | C55: 152
A56: Current tax liabilities (net) | B56: 1108 | C56: 1103
A57: Total current liabilities | B57: 26904 | C57: 26794
A58: TOTAL EQUITY AND LIABILITIES | B58: 166141 | C58: 155841

Sheet PL 2023-24
A1: Wipro Enterprises (P) Limited (Standalone)
A2: Statement of Profit and Loss
A3: Statement of Profit and Loss for the year ended March 31, 2024 (Source: Annual Report 2023-24, p.83)
A4: (Amount Rs. in millions, unless otherwise stated)
A6: Particulars | B6: 2024 | C6: 2023
A7: REVENUE
A8: Revenue from operations | B8: 71763 | C8: 70052
A9: Other income | B9: 9583 | C9: 7531
A10: Total income | B10: 81346 | C10: 77583
A11: EXPENSES
A12: Cost of materials consumed | B12: 38297 | C12: 37573
A13: Purchases of stock-in-trade | B13: 530 | C13: 3163
A14: Changes in inventories of finished products, WIP and stock-in-trade | B14: 697 | C14: 594
A15: Employee benefits expense | B15: 6264 | C15: 5585
A16: Finance costs | B16: 1478 | C16: 1213
A17: Depreciation and amortisation expense | B17: 1830 | C17: 1151
A18: Other expenses | B18: 16243 | C18: 15329
A19: Total Expenses | B19: 65339 | C19: 64608
A20: Profit before tax | B20: 16007 | C20: 12975
A21: Tax expense
A22: Current tax | B22: 2766 | C22: 2501
A23: Deferred tax | B23: 609 | C23: -214
A24: Total tax expenses | B24: 3375 | C24: 2287
A25: Profit for the year | B25: 12632 | C25: 10688
A26: Other comprehensive income, net of taxes
A27: Remeasurement of defined benefit liability/asset (net of tax) | B27: -85 | C27: 9
A28: Net change in FV of financial instruments through OCI (net of tax) | B28: 122 | C28: -213
A29: Net change in FV of cash flow hedge (net of tax) | B29: -67 | C29: 27
A30: Total other comprehensive income for the year, net of taxes | B30: -30 | C30: -177
A31: Total comprehensive income for the year | B31: 12602 | C31: 10511
A32: Earnings per equity share (par value Rs.10 each)
A33: Weighted average equity shares for computing basic and diluted EPS | B33: 483662163 | C33: 483662163
A34: Basic and diluted EPS (Rs.) | B34: 26.12 | C34: 22.1

Sheet CF 2023-24
A1: Wipro Enterprises (P) Limited (Standalone)
A2: Statement of Cash Flows
A3: Statement of Cash Flows for the year ended March 31, 2024 (Source: Annual Report 2023-24, p.85)
A4: (Amount Rs. in millions, unless otherwise stated)
A6: Particulars | B6: 2024 | C6: 2023
A7: A. Cash flows from operating activities
A8: Profit before tax | B8: 16007 | C8: 12975
A9: Depreciation and amortization | B9: 1830 | C9: 1151
A10: Interest on borrowings | B10: 1478 | C10: 1254
A11: Changes in fair value of investment accounted at FVTPL | B11: -174 | C11: 0
A12: Dividend / interest income | B12: -4008 | C12: -3258
A13: Net (gain)/loss on sale of current investments | B13: -2729 | C13: -1397
A14: Net (gain)/loss on sale of associates | B14: -1392 | C14: -2206
A15: Net (gain)/loss on sale of PP&E and intangible assets | B15: -1 | C15: -13
A16: Change in fair value of contingent consideration | B16: -614 | C16: 0
A17: Allowance for doubtful receivables | B17: 41 | C17: 102
A18: Net foreign exchange differences on non-operating items | B18: -93 | C18: -116
A19: Working capital changes - Trade receivables | B19: -439 | C19: -595
... A25: Net cash generated from operating activities | B25: 8621 | C25: 6874
A26: B. Cash flows from investing activities
A27: Acquisition of PP&E including capital advances | B27: -861 | C27: -1428
A28: Proceeds from sale of PP&E | B28: 28 | C28: 13
A29: Investment in associates | B29: -150 | C29: -5
A30: Purchase of investments | B30: -75423 | C30: -104591
A31: Proceeds from sale/maturity of investments | B31: 72957 | C31: 95771
A32: Proceeds from sale of investment in associates | B32: 1495 | C32: 2217
A33: Payment for business acquisitions, net of cash acquired | B33: -3388 | C33: 0
A34: Investment in subsidiaries | B34: 0 | C34: -572
A35: Loan to subsidiaries | B35: -620 | C35: -3313
A36: Amount received on liquidation of subsidiary | B36: 48 | C36: 0
A37: Interest income received | B37: 3235 | C37: 2389
A38: Dividend received | B38: 70 | C38: 71
A39: Net cash used in investing activities | B39: -2609 | C39: -9448
A40: C. Cash flows from financing activities
A41: Interest paid on borrowings | B41: -1608 | C41: -1242
A42: Payment of contingent consideration | B42: -733 | C42: -234
A43: Proceeds from borrowings | B43: 7481 | C43: 11174
A44: Payment of lease liabilities | B44: -123 | C44: -101
A45: Repayment of borrowings | B45: -9317 | C45: -8168
A46: Net cash generated from/(used in) financing activities | B46: -4300 | C46: 1429
A47: Net increase/(decrease) in cash and cash equivalents during the year | B47: 1712 | C47: -1145
A48: Cash and cash equivalents at the beginning of the year | B48: 1597 | C48: 2742
A49: Cash and cash equivalents at the end of the year | B49: 3309 | C49: 1597
A50: Components of cash and cash equivalents
A51: Balances with banks - in current accounts | B51: 314 | C51: 262
A52: Balances with banks - in deposit accounts | B52: 1300 | C52: 0
A53: Cheques, drafts on hand | B53: 1295 | C53: 1184
A54: Remittance in transit | B54: 400 | C54: 151
A55: Cash in hand (rounded to nil, below Rs.0.5 mn) | B55: 0 | C55: 0

Sheet Notes 2023-24
A1: Wipro Enterprises (P) Limited (Standalone)
A2: Notes to the Standalone Financial Statements (Selected Notes)
A3: Notes to the Standalone Financial Statements, year ended March 31, 2024 (Source: Annual Report 2023-24, pp.101-143)
A4: (Amount Rs. in millions, unless otherwise stated)
A6: Note 4. Property, plant and equipment - Net carrying value
B7: 2024 | C7: 2023
A8: Land | B8: 527 | C8: 425
A9: Buildings | B9: 3816 | C9: 3803
A10: Plant and Machinery | B10: 5085 | C10: 5287
A11: Furniture and Fixtures | B11: 152 | C11: 149
A12: Office Equipment | B12: 132 | C12: 122
A13: Vehicles | B13: 12 | C13: 7
A14: Total | B14: 9724 | C14: 9793
A16: Note 5. Capital work-in-progress - ageing (Projects in progress)
B17: 2024 | C17: 2023
A18: Less than 1 year | B18: 119 | C18: 172
A19: 1-2 years | B19: 15 | C19: 16
A20: 2-3 years | B20: 0 | C20: 7
A21: More than 3 years | B21: 7 | C21: 0
A22: Total CWIP | B22: 141 | C22: 195
A23: Intangible asset under development: 140 (2024), 109 (2023)
A25: Note 6. Right-of-use assets - Net carrying value
B26: 2024 | C26: 2023
A27: Land | B27: 714 | C27: 699
A28: Buildings | B28: 62 | C28: 96
A29: Furniture and Fixtures | B29: 31 | C29: 1
A30: Vehicles | B30: 3 | C30: 4
A31: Total | B31: 810 | C31: 800
A33: Note 7. Goodwill and intangible assets - movement in Goodwill
B34: 2024 | C34: 2023
A35: Amount at the beginning of the year | B35: 362 | C35: 362
A36: Addition during the year (business combinations) | B36: 906 | C36: 0
A37: Amount at the end of the year | B37: 1268 | C37: 362
A38: Net block of other intangible assets: 3,983 (2024), 1,723 (2023). Impairment charge of 568 recognized in FY2024 on brand/distribution intangibles.
A40: Note 8. Investment
B41: 2024 | C41: 2023
A42: Non-current - Investments in subsidiaries - Equity shares | B42: 28085 | C42: 28133
A43: Non-current - Investments in subsidiaries - Redeemable preference shares | B43: 2170 | C43: 2140
A44: Non-current - Investments in Associates - Equity Instruments | B44: 729 | C44: 735
A45: Non-current - Investments in Associates - Compulsorily convertible preference shares | B45: 475 | C45: 595
A46: Non-current - FVTPL - Compulsorily convertible preference shares | B46: 778 | C46: 604
A47: Non-current - FVTPL - Equity Instruments | B47: 213 | C47: 1
A48: Non-current - FVTPL - Fixed maturity mutual funds | B48: 276 | C48: 257
A49: Non-current - Amortized cost - Redeemable preference shares | B49: 450 | C49: 950
A50: Total non-current investments | B50: 33176 | C50: 33415
A51: Current - FVTPL - Liquid and short-term mutual funds | B51: 29132 | C51: 34294
A52: Current - FVTPL - Equity-linked debentures | B52: 0 | C52: 2108
A53: Current - FVTPL - Equity Instruments (quoted) | B53: 420 | C53: 0
... A62: Aggregate impairment in value of investments | B62: 0 | C62: 0
A64: Note 9. Loan
B65: 2024 | C65: 2023
A66: Non-current - Loans to subsidiaries | B66: 18265 | C66: 15048
A67: Current - Loans to subsidiaries | B67: 2727 | C67: 5324
A69: Note 10. Other financial assets
B70: 2024 | C70: 2023
A71: Non-current - Security deposits | B71: 4 | C71: 4
A72: Non-current - Finance lease receivables | B72: 102 | C72: 0
A73: Total non-current | B73: 106 | C73: 4
A74: Current - Security deposits | B74: 137 | C74: 123
A75: Current - Interest receivable | B75: 394 | C75: 638
A76: Current - Loans and advances to employees | B76: 6 | C76: 16
A77: Current - Receivables from related parties | B77: 746 | C77: 656
A78: Current - Receivable on sale of financial instruments | B78: 0 | C78: 500
A79: Current - Finance lease receivables | B79: 36 | C79: 84
A80: Total current | B80: 1319 | C80: 2017
A82: Note 11. Other Assets
B83: 2024 | C83: 2023
A84: Non-current - Capital advances | B84: 26 | C84: 72
A85: Non-current - Prepaid expenses | B85: 14 | C85: 5
A86: Non-current - Balances with government/statutory authorities | B86: 1088 | C86: 796
A87: Non-current - Others | B87: 12 | C87: 21
A88: Total non-current | B88: 1140 | C88: 894
A89: Current - Balances with government/statutory authorities | B89: 594 | C89: 470
A90: Current - Advance to suppliers | B90: 972 | C90: 826
A91: Current - Prepaid expenses | B91: 176 | C91: 201
A92: Current - Contract assets | B92: 46 | C92: 71
A93: Current - Others | B93: 275 | C93: 196
A94: Total current | B94: 2063 | C94: 1764
A95: Assets held for sale | B95: 53 | C95: 53
A97: Note 12. Inventories
B98: 2024 | C98: 2023
A99: Raw materials | B99: 2101 | C99: 3047
A100: Work in progress | B100: 1642 | C100: 2059
A101: Finished products | B101: 1426 | C101: 1588
A102: Traded products | B102: 877 | C102: 995
A103: Stores and spares | B103: 356 | C103: 380
A104: Total inventories | B104: 6402 | C104: 8069
A106: Note 13. Trade receivables
B107: 2024 | C107: 2023
A108: Non-current - Considered good | B108: 45 | C108: 99
A109: Current - Considered good | B109: 7693 | C109: 7117
A110: Current - Credit impaired - Disputed receivables | B110: 128 | C110: 117
A111: Current - Less: Allowance for lifetime expected credit losses | B111: -476 | C111: -435
A112: Net current trade receivables | B112: 7345 | C112: 6799
A113: Allowance movement - Balance at beginning of year | B113: 435 | C113: 333
A114: Allowance movement - Addition during the year, net | B114: 57 | C114: 102
A115: Allowance movement - Uncollectable receivables charged against allowance | B115: -16 | C115: 0
A116: Allowance movement - Balance at end of year | B116: 476 | C116: 435
A118: Note 14. Derivative assets
B119: 2024 | C119: 2023
...

Sheet Notes 2024-25
A1: Wipro Enterprises (P) Limited (Standalone)
A2: Notes to the Standalone Financial Statements (Selected Notes)
A3: Notes to the Standalone Financial Statements, year ended March 31, 2025 (Source: Annual Report 2024-25, pp.98-137)
A4: (Amount Rs. in millions, unless otherwise stated)
A6: Note 4. Property, plant and equipment - Net carrying value
B7: 2025 | C7: 2024
A8: Land | B8: 527 | C8: 527
A9: Buildings | B9: 3788 | C9: 3816
A10: Plant and Machinery | B10: 4952 | C10: 5085
A11: Furniture and Fixtures | B11: 155 | C11: 152
A12: Office Equipment | B12: 175 | C12: 132
A13: Vehicles | B13: 8 | C13: 12
A14: Total | B14: 9605 | C14: 9724
A16: Note 5. Capital work-in-progress & Intangible asset under development - ageing
B17: 2025 | C17: 2024
A18: CWIP - Less than 1 year | B18: 73 | C18: 102
A19: CWIP - 1-2 years | B19: 77 | C19: 25
A20: CWIP - 2-3 years | B20: 0 | C20: 1
A21: CWIP - More than 3 years | B21: 6 | C21: 13
A22: Total CWIP | B22: 156 | C22: 141
A23: Intangible asset under development - Less than 1 year | B23: 11 | C23: 86
A24: Intangible asset under development - 1-2 years | B24: 5 | C24: 37
A25: Intangible asset under development - 2-3 years | B25: 12 | C25: 11
A26: Intangible asset under development - More than 3 years | B26: 5 | C26: 6
A27: Total Intangible asset under development | B27: 33 | C27: 140
A29: Note 6. Right-of-use assets - movement
B30: 2025 | C30: 2024
A31: Balance at beginning of year | B31: 810 | C31: 800
A32: Additions | B32: 165 | C32: 111
A33: Deletions | B33: -44 | C33: 0
A34: Depreciation | B34: -85 | C34: -101
A35: Balance at end of year | B35: 846 | C35: 810
A37: Note 7. Goodwill and intangible assets - movement in Goodwill
B38: 2025 | C38: 2024
A39: Amount at the beginning of the year | B39: 1268 | C39: 362
A40: Addition during the year | B40: 0 | C40: 906
A41: Amount at the end of the year | B41: 1268 | C41: 1268
A42: Goodwill by segment: Consumer care and lighting 906/906; Infrastructure engineering 362/362.
A43: Net block of other intangible assets: 4,426 (2025), 3,983 (2024) [Technical know-how 92/100; Brands, patents, trademarks, distribution network & others 4,334/3,883]
A45: Note 8. Investments
B46: 2025 | C46: 2024
A47: Non-current - Investments in subsidiaries - Equity shares (unquoted) | B47: 30810 | C47: 28085
A48: Non-current - Investments in subsidiaries - Redeemable preference shares (unquoted) | B48: 2170 | C48: 2170
A49: Non-current - Investments in Associates - Equity Instruments, net of impairment (unquoted) | B49: 634 | C49: 729
A50: Non-current - Investments in Associates - Compulsorily convertible preference shares (unquoted) | B50: 475 | C50: 475
A51: Non-current - Investments in Associates - Compulsorily convertible debentures (unquoted) | B51: 20 | C51: 0
A52: Non-current - FVTPL - Compulsorily convertible preference shares, net of impairment (unquoted) | B52: 217 | C52: 778
A53: Non-current - FVTPL - Equity Instruments (unquoted) | B53: 286 | C53: 213
A54: Non-current - FVTPL - Fixed maturity mutual funds (unquoted) | B54: 296 | C54: 276
A55: Non-current - FVTOCI - Equity Instruments (unquoted) | B55: 23535 | C55: 0
A56: Non-current - Amortized cost - Redeemable preference shares (quoted) | B56: 450 | C56: 450
A57: Non-current - Amortized cost - Fixed deposits with NBFCs (unquoted) | B57: 50 | C57: 0
A58: Total non-current investments | B58: 58943 | C58: 33176
... A73: Current - Aggregate impairment in value of investments | B73: 0 | C73: 0
A75: Note 9. Loans
B76: 2025 | C76: 2024
A77: Non-current - Loans to subsidiaries | B77: 16522 | C77: 18265
A78: Current - Loans to subsidiaries | B78: 5749 | C78: 2727
A80: Note 10. Other financial assets
B81: 2025 | C81: 2024
A82: Non-current - Security deposits | B82: 4 | C82: 4
A83: Non-current - Finance lease receivables | B83: 140 | C83: 102
A84: Total non-current | B84: 144 | C84: 106
A85: Current - Security deposits | B85: 210 | C85: 137
A86: Current - Interest receivable | B86: 357 | C86: 394
A87: Current - Loans and advances to employees | B87: 23 | C87: 6
A88: Current - Receivables from related parties | B88: 595 | C88: 746
A89: Current - Finance lease receivables | B89: 28 | C89: 36
A90: Total current | B90: 1213 | C90: 1319
A92: Note 11. Other Assets
B93: 2025 | C93: 2024
A94: Non-current - Capital advances | B94: 44 | C94: 26
A95: Non-current - Prepaid expenses | B95: 10 | C95: 14
A96: Non-current - Balances with government/statutory authorities | B96: 1260 | C96: 1088
A97: Non-current - Others (Deferred trade receivable) | B97: 3 | C97: 12
A98: Total non-current | B98: 1317 | C98: 1140
A99: Current - Balances with government/statutory authorities | B99: 776 | C99: 594
A100: Current - Advance to suppliers | B100: 345 | C100: 972
A101: Current - Prepaid expenses | B101: 182 | C101: 176
A102: Current - Contract assets | B102: 57 | C102: 46
A103: Current - Others | B103: 318 | C103: 275
A104: Total current | B104: 1678 | C104: 2063
A105: Assets held for sale | B105: 8 | C105: 53
A107: Note 12. Inventories
B108: 2025 | C108: 2024
A109: Raw materials | B109: 2600 | C109: 2101
A110: Work in progress | B110: 1821 | C110: 1642
A111: Finished products | B111: 1667 | C111: 1426
A112: Traded products | B112: 750 | C112: 877
A113: Stores and spares | B113: 281 | C113: 356
A114: Total inventories | B114: 7119 | C114: 6402
A116: Note 13. Trade receivables
B117: 2025 | C117: 2024
A118: Non-current - Considered good | B118: 0 | C118: 45
A119: Current - Considered good | B119: 6128 | C119: 7693
A120: Current - Credit impaired - Disputed receivables | B120: 22 | C120: 128
A121: Current - Less: Allowance for lifetime expected credit losses | B121: -218 | C121: -476
A122: Net current trade receivables | B122: 5932 | C122: 7345
A123: Allowance movement - Balance at beginning of year | B123: 476 | C123: 435
A124: Allowance movement - Addition during the year, net | B124: 114 | C124: 57
...

Sheet BS 2024-25
A1: Wipro Enterprises (P) Limited (Standalone)
A2: Balance Sheet
A3: Balance Sheet as at March 31, 2025 (Source: Annual Report 2024-25, Wipro-Annual-Report-2024-25.pdf, p.80)
A4: (Amount Rs. in millions, unless otherwise stated)
A6: Particulars | B6: 2025 | C6: 2024
A7: ASSETS
A8: Non-current assets
A9: Property, plant and equipment | B9: 9605 | C9: 9724 | E9: =B9 -> 9605
A10: Capital work-in-progress | B10: 156 | C10: 141 | E10: =SUM(B10:B11) -> 189
A11: Intangible asset under development | B11: 33 | C11: 140 | E11: =B15 -> 58943
A12: Right of use assets | B12: 846 | C12: 810 | E12: =SUM(B12:B14,B16:B21) -> 25292
A13: Goodwill | B13: 1268 | C13: 1268
A14: Other intangible assets | B14: 4426 | C14: 3983
A15: Financial assets - Investments | B15: 58943 | C15: 33176
A16: Financial assets - Trade receivables | B16: 0 | C16: 45
A17: Financial assets - Derivative instruments | B17: 7 | C17: 0
A18: Financial assets - Loans | B18: 16522 | C18: 18265
A19: Financial assets - Other financial assets | B19: 144 | C19: 106
A20: Non current tax assets (net) | B20: 762 | C20: 788
A21: Other assets | B21: 1317 | C21: 1140
A22: Total non-current assets | B22: 94029 | C22: 69586
A23: Current assets
A24: Inventories | B24: 7119 | C24: 6402
A25: Financial assets - Investments | B25: 70625 | C25: 73332
A26: Financial assets - Trade receivables | B26: 5932 | C26: 7345
A27: Financial assets - Derivative instruments | B27: 10 | C27: 5
A28: Financial assets - Cash and cash equivalents | B28: 3278 | C28: 3309
A29: Financial assets - Loans | B29: 5749 | C29: 2727
A30: Financial assets - Other financial assets | B30: 1213 | C30: 1319
A31: Other assets | B31: 1678 | C31: 2063
A32: Assets held for sale | B32: 8 | C32: 53
A33: Total current assets | B33: 95612 | C33: 96555
A34: TOTAL ASSETS | B34: 189641 | C34: 166141
A35: EQUITY AND LIABILITIES
A36: Equity
A37: Share capital | B37: 4837 | C37: 4837
A38: Other equity | B38: 128849 | C38: 119159
A39: Total equity | B39: 133686 | C39: 123996
A40: Non-current liabilities
A41: Financial liabilities - Borrowings | B41: 21551 | C41: 11967
A42: Financial liabilities - Lease liabilities | B42: 109 | C42: 79
A43: Financial liabilities - Derivative instruments | B43: 0 | C43: 1255
A44: Provisions | B44: 155 | C44: 320
A45: Deferred tax liabilities (net) | B45: 1667 | C45: 1620
A46: Total non-current liabilities | B46: 23482 | C46: 15241
A47: Current liabilities
A48: Financial liabilities - Borrowings | B48: 16419 | C48: 11032
A49: Financial liabilities - Lease liabilities | B49: 15 | C49: 27
A50: Financial liabilities - Derivative liabilities | B50: 1706 | C50: 452
A51: Trade payables - dues of micro & small enterprises | B51: 1938 | C51: 1003
A52: Trade payables - dues of other creditors | B52: 7373 | C52: 10100
A53: Financial liabilities - Other financial liabilities | B53: 2163 | C53: 2164
A54: Other liabilities | B54: 1400 | C54: 855
A55: Provisions | B55: 208 | C55: 163
A56: Current tax liabilities (net) | B56: 1251 | C56: 1108
A57: Total current liabilities | B57: 32473 | C57: 26904
A58: TOTAL EQUITY AND LIABILITIES | B58: 189641 | C58: 166141

Sheet combined BS
B2: Particulars | C2: =2020+4 -> 2024 | D2: =2020+5 -> 2025 | E2: Particulars | F2: 2023 | G2: 2022
B3: ASSETS | E3: ASSETS
B4: Non-current assets | E4: Non-current assets
B5: Property, plant and equipment | C5: =IFERROR(INDEX('BS 2024-25'!C9:C58,MATCH(B5,'BS 2024-25'!A9:A58,0)),0) -> 9724 | E5: Property, plant and equipment
B6: Capital work-in-progress | C6: =IFERROR(INDEX('BS 2024-25'!C10:C59,MATCH(B6,'BS 2024-25'!A10:A59,0)),0) -> 141 | E6: Capital work-in-progress
B7: Intangible asset under development | C7: =IFERROR(INDEX('BS 2024-25'!C11:C60,MATCH(B7,'BS 2024-25'!A11:A60,0)),0) -> 140 | E7: Right of use assets
B8: Right of use assets | C8: =IFERROR(INDEX('BS 2024-25'!C12:C61,MATCH(B8,'BS 2024-25'!A12:A61,0)),0) -> 810 | E8: Goodwill
B9: Goodwill | C9: =IFERROR(INDEX('BS 2024-25'!C13:C62,MATCH(B9,'BS 2024-25'!A13:A62,0)),0) -> 1268 | E9: Other intangible assets
B10: Other intangible assets | C10: =IFERROR(INDEX('BS 2024-25'!C14:C63,MATCH(B10,'BS 2024-25'!A14:A63,0)),0) -> 3983 | E10: Financial assets - Investments
B11: Financial assets - Investments | C11: =IFERROR(INDEX('BS 2024-25'!C15:C64,MATCH(B11,'BS 2024-25'!A15:A64,0)),0) -> 33176 | E11: Financial assets - Trade receivables
B12: Financial assets - Trade receivables | C12: =IFERROR(INDEX('BS 2024-25'!C16:C65,MATCH(B12,'BS 2024-25'!A16:A65,0)),0) -> 45 | E12: Financial assets - Derivative instruments
B13: Financial assets - Derivative instruments | C13: =IFERROR(INDEX('BS 2024-25'!C17:C66,MATCH(B13,'BS 2024-25'!A17:A66,0)),0) -> 0 | E13: Financial assets - Loans
B14: Financial assets - Loans | C14: =IFERROR(INDEX('BS 2024-25'!C18:C67,MATCH(B14,'BS 2024-25'!A18:A67,0)),0) -> 18265 | E14: Financial assets - Other financial assets
B15: Financial assets - Other financial assets | C15: =IFERROR(INDEX('BS 2024-25'!C19:C68,MATCH(B15,'BS 2024-25'!A19:A68,0)),0) -> 106 | E15: Non current tax assets (net)
B16: Non current tax assets (net) | C16: =IFERROR(INDEX('BS 2024-25'!C20:C69,MATCH(B16,'BS 2024-25'!A20:A69,0)),0) -> 788 | E16: Other assets
... B30: TOTAL ASSETS | C30: =IFERROR(INDEX('BS 2024-25'!C34:C83,MATCH(B30,'BS 2024-25'!A34:A83,0)),0) -> 166141 | E30: EQUITY AND LIABILITIES
B31: EQUITY AND LIABILITIES | E31: Equity
B32: Equity | E32: Share capital
B33: Share capital | C33: =IFERROR(INDEX('BS 2024-25'!C37:C86,MATCH(B33,'BS 2024-25'!A37:A86,0)),0) -> 4837 | E33: Other equity
B34: Other equity | C34: =IFERROR(INDEX('BS 2024-25'!C38:C87,MATCH(B34,'BS 2024-25'!A38:A87,0)),0) -> 119159 | E34: Total equity
B35: Total equity | C35: =IFERROR(INDEX('BS 2024-25'!C39:C88,MATCH(B35,'BS 2024-25'!A39:A88,0)),0) -> 123996 | E35: Non-current liabilities
B36: Non-current liabilities | E36: Financial liabilities - Borrowings
B37: Financial liabilities - Borrowings | C37: =IFERROR(INDEX('BS 2024-25'!C41:C90,MATCH(B37,'BS 2024-25'!A41:A90,0)),0) -> 11967 | E37: Financial liabilities - Lease liabilities
B38: Financial liabilities - Lease liabilities | C38: =IFERROR(INDEX('BS 2024-25'!C42:C91,MATCH(B38,'BS 2024-25'!A42:A91,0)),0) -> 79 | E38: Financial liabilities - Derivative instruments
B39: Financial liabilities - Derivative instruments | C39: =IFERROR(INDEX('BS 2024-25'!C43:C92,MATCH(B39,'BS 2024-25'!A43:A92,0)),0) -> 1255 | E39: Provisions
B40: Provisions | C40: =IFERROR(INDEX('BS 2024-25'!C44:C93,MATCH(B40,'BS 2024-25'!A44:A93,0)),0) -> 320 | E40: Deferred tax liabilities (net)
B41: Deferred tax liabilities (net) | C41: =IFERROR(INDEX('BS 2024-25'!C45:C94,MATCH(B41,'BS 2024-25'!A45:A94,0)),0) -> 1620 | E41: Total non-current liabilities
B42: Total non-current liabilities | C42: =IFERROR(INDEX('BS 2024-25'!C46:C95,MATCH(B42,'BS 2024-25'!A46:A95,0)),0) -> 15241 | E42: Current liabilities
B43: Current liabilities | E43: Financial liabilities - Borrowings
B44: Financial liabilities - Borrowings | C44: =IFERROR(INDEX('BS 2024-25'!C48:C97,MATCH(B44,'BS 2024-25'!A48:A97,0)),0) -> 11032 | E44: Financial liabilities - Lease liabilities
B45: Financial liabilities - Lease liabilities | C45: =IFERROR(INDEX('BS 2024-25'!C49:C98,MATCH(B45,'BS 2024-25'!A49:A98,0)),0) -> 27 | E45: Financial liabilities - Derivative liabilities
B46: Financial liabilities - Derivative liabilities | C46: =IFERROR(INDEX('BS 2024-25'!C50:C99,MATCH(B46,'BS 2024-25'!A50:A99,0)),0) -> 452 | E46: Trade payables - dues of micro & small enterprises
B47: Trade payables - dues of micro & small enterprises | C47: =IFERROR(INDEX('BS 2024-25'!C51:C100,MATCH(B47,'BS 2024-25'!A51:A100,0)),0) -> 1003 | E47: Trade payables - dues of other creditors
B48: Trade payables - dues of other creditors | C48: =IFERROR(INDEX('BS 2024-25'!C52:C101,MATCH(B48,'BS 2024-25'!A52:A101,0)),0) -> 10100 | E48: Financial liabilities - Other financial liabilities
B49: Financial liabilities - Other financial liabilities | C49: =IFERROR(INDEX('BS 2024-25'!C53:C102,MATCH(B49,'BS 2024-25'!A53:A102,0)),0) -> 2164 | E49: Other liabilities
B50: Other liabilities | C50: =IFERROR(INDEX('BS 2024-25'!C54:C103,MATCH(B50,'BS 2024-25'!A54:A103,0)),0) -> 855 | E50: Provisions
B51: Provisions | C51: =IFERROR(INDEX('BS 2024-25'!C55:C104,MATCH(B51,'BS 2024-25'!A55:A104,0)),0) -> 163 | E51: Current tax liabilities (net)
B52: Current tax liabilities (net) | C52: =IFERROR(INDEX('BS 2024-25'!C56:C105,MATCH(B52,'BS 2024-25'!A56:A105,0)),0) -> 1108 | E52: Total current liabilities
B53: Total current liabilities | C53: =IFERROR(INDEX('BS 2024-25'!C57:C106,MATCH(B53,'BS 2024-25'!A57:A106,0)),0) -> 26904 | E53: TOTAL EQUITY AND LIABILITIES
B54: TOTAL EQUITY AND LIABILITIES | C54: =IFERROR(INDEX('BS 2024-25'!C58:C107,MATCH(B54,'BS 2024-25'!A58:A107,0)),0) -> 166141

Sheet CF 2024-25
A1: Wipro Enterprises (P) Limited (Standalone)
A2: Statement of Cash Flows
A3: Statement of Cash Flows for the year ended March 31, 2025 (Source: Annual Report 2024-25, pp.83-84)
A4: (Amount Rs. in millions, unless otherwise stated)
A6: Particulars | B6: 2025 | C6: 2024
A7: A. Cash flows from operating activities
A8: Profit before tax | B8: 13006 | C8: 16007
A9: Depreciation and amortization | B9: 1311 | C9: 1830
A10: Interest on borrowings | B10: 2223 | C10: 1478
A11: FV change of Investment | B11: 710 | C11: -174
A12: Dividend / interest income | B12: -4285 | C12: -4008
A13: Net (gain)/loss on sale of current investments | B13: -3462 | C13: -2729
A14: Net (gain)/loss on sale of associates | B14: -1452 | C14: -1392
A15: Net (gain)/loss on sale of PP&E and intangible assets | B15: -98 | C15: -1
A16: Change in fair value of consideration | B16: 14 | C16: -614
A17: Allowance for doubtful receivables | B17: -258 | C17: 41
A18: Net foreign exchange differences on non-operating items | B18: 952 | C18: -93
A19: Working capital changes - Trade receivables | B19: 764 | C19: -439
... A25: Net cash generated from operating activities | B25: 4558 | C25: 8621
A26: B. Cash flows from investing activities
A27: Acquisition of PP&E including capital advances | B27: -1410 | C27: -861
A28: Proceeds from sale of PP&E | B28: 125 | C28: 28
A29: Investment in associates | B29: -20 | C29: -150
A30: Purchase of investments | B30: -159319 | C30: -75423
A31: Proceeds from sale/maturity of current investments | B31: 144341 | C31: 72957
A32: Proceeds from sale of investment in associates | B32: 1457 | C32: 1495
A33: Payment for business acquisitions, net of cash acquired | B33: 0 | C33: -3388
A34: Investment in subsidiaries | B34: -2725 | C34: 0
A35: Loan to subsidiaries | B35: -3072 | C35: -3820
A36: Loan from subsidiaries | B36: 1793 | C36: 3200
A37: Amount received on liquidation of subsidiary | B37: 0 | C37: 48
A38: Interest income received | B38: 1587 | C38: 3235
... A40: Net cash used in investing activities | B40: -17204 | C40: -2609
A41: C. Cash flows from financing activities
A42: Interest paid on borrowings | B42: -2256 | C42: -1608
A43: Payment for contingent consideration | B43: 0 | C43: -733
A44: Proceeds from borrowings | B44: 21342 | C44: 7481
A45: Payment towards share capital reduction | B45: -7 | C45: 0
A46: Repayment of lease liabilities | B46: -93 | C46: -123
A47: Repayment of borrowings | B47: -6371 | C47: -9317
A48: Net cash generated from/(used in) financing activities | B48: 12615 | C48: -4300
A49: Net increase/(decrease) in cash and cash equivalents during the year | B49: -31 | C49: 1712
A50: Cash and cash equivalents at the beginning of the year | B50: 3309 | C50: 1597
A51: Cash and cash equivalents at the end of the year | B51: 3278 | C51: 3309
A52: Components of cash and cash equivalents
A53: Balances with banks - in current accounts | B53: 204 | C53: 314
A54: Balances with banks - in deposit accounts | B54: 430 | C54: 1300
A55: Cheques, drafts on hand | B55: 1513 | C55: 1295
A56: Remittance in transit | B56: 1131 | C56: 400
A57: Cash in hand (rounded to nil, below Rs.0.5 mn) | B57: 0 | C57: 0

Sheet PL 2024-25
A1: Wipro Enterprises (P) Limited (Standalone)
A2: Statement of Profit and Loss
A3: Statement of Profit and Loss for the year ended March 31, 2025 (Source: Annual Report 2024-25, p.81). Revenue from operations and Other expenses for 2024 shown as restated per Note 49 in this report; figures may therefore differ slightly from the FY2023-24 report's originally reported figures.
A4: (Amount Rs. in millions, unless otherwise stated)
A6: Particulars | B6: 2025 | C6: 2024
A7: REVENUE
A8: Revenue from operations (Restated for 2024, refer Note 49) | B8: 72308 | C8: 71475
A9: Other income | B9: 9191 | C9: 9583
A10: Total income | B10: 81499 | C10: 81058
A11: EXPENSES
A12: Cost of materials consumed | B12: 39567 | C12: 38297
A13: Purchases of stock-in-trade | B13: 1434 | C13: 530
A14: Changes in inventories of finished products, WIP and stock-in-trade | B14: -293 | C14: 697
A15: Employee benefits expense | B15: 6467 | C15: 6264
A16: Finance costs | B16: 2223 | C16: 1478
A17: Depreciation, amortisation and impairment expense | B17: 1311 | C17: 1830
A18: Other expenses (Restated for 2024, refer Note 49) | B18: 17784 | C18: 15955
A19: Total Expenses | B19: 68493 | C19: 65051
A20: Profit before tax | B20: 13006 | C20: 16007
A21: Tax expense
A22: Current tax | B22: 3157 | C22: 2766
A23: Deferred tax | B23: 73 | C23: 609
A24: Total tax expenses | B24: 3230 | C24: 3375
A25: Profit for the year | B25: 9776 | C25: 12632
A26: Other comprehensive income, net of taxes
A27: Remeasurement of defined benefit liability/asset (net of tax) | B27: -19 | C27: -85
A28: Net change in FV of financial instruments through OCI (net of tax) | B28: 65 | C28: 122
A29: Net change in FV of cash flow hedge (net of tax) | B29: -125 | C29: -67
A30: Total other comprehensive income for the year, net of taxes | B30: -79 | C30: -30
A31: Total comprehensive income for the year | B31: 9697 | C31: 12602
A32: Earnings per equity share (par value Rs.10 each)
A33: Weighted average equity shares for computing basic and diluted EPS | B33: 483659648 | C33: 483662163
A34: Basic and diluted EPS (Rs.) | B34: 20.21 | C34: 26.12

Sheet HistoriacalIFLS
B2: ="Historical Financial Statement - "&'[1]Data Sheet'!C1 -> Historical Financial Statement - Wipro Ltd
B3: Years | C3: ='[1]Data Sheet'!E16 -> 43921 | D3: ='[1]Data Sheet'!F16 -> 44286 | E3: ='[1]Data Sheet'!G16 -> 44651 | F3: ='[1]Data Sheet'!H16 -> 45016 | G3: ='[1]Data Sheet'!I16 -> 45382 | H3: ='[1]Data Sheet'!J16 -> 45747
B5: Income Statment
B7: Sales | C7: =IFERROR('PL 2020-21'!C8,0) -> 47775 | D7: =IFERROR('PL 2020-21'!B8,0) -> 51658 | E7: =IFERROR('PL 2022-23'!C8,0) -> 57884 | F7: =IFERROR('PL 2022-23'!B8,0) -> 70052 | G7: =IFERROR('PL 2024-25'!C8,0) -> 71475 | H7: =IFERROR('PL 2024-25'!B8,0) -> 72308
B8: sales Increase | D8: =D7/C7-1 -> 0.081276818 | E8: =E7/D7-1 -> 0.12052344 | F8: =F7/E7-1 -> 0.21021353 | G8: =G7/F7-1 -> 0.020313481 | H8: =H7/G7-1 -> 0.011654425
B9: Other Income | C9: =IFERROR('PL 2020-21'!C9,0) -> 4900 | D9: =IFERROR('PL 2020-21'!B9,0) -> 6905 | E9: =IFERROR('PL 2022-23'!C9,0) -> 5711 | F9: =IFERROR('PL 2022-23'!B9,0) -> 7572 | G9: =IFERROR('PL 2024-25'!C9,0) -> 9583 | H9: =IFERROR('PL 2024-25'!B9,0) -> 9191
D10: =D9/C9-1 -> 0.40918367 | E10: =E9/D9-1 -> -0.17291818 | F10: =F9/E9-1 -> 0.32586237 | G10: =G9/F9-1 -> 0.26558373 | H10: =H9/G9-1 -> -0.040905771
B11: Total Revenue | C11: =IFERROR(SUM(C7,C9),0) -> 52675 | D11: =IFERROR(SUM(D7,D9),0) -> 58563 | E11: =IFERROR(SUM(E7,E9),0) -> 63595 | F11: =IFERROR(SUM(F7,F9),0) -> 77624 | G11: =IFERROR(SUM(G7,G9),0) -> 81058 | H11: =IFERROR(SUM(H7,H9),0) -> 81499
D12: =D11/C11-1 -> 0.11177978 | E12: =E11/D11-1 -> 0.08592456 | F12: =F11/E11-1 -> 0.2205991 | G12: =G11/F11-1 -> 0.044238895 | H12: =H11/G11-1 -> 0.0054405487
B13: COGS | C13: =IFERROR(SUM('PL 2020-21'!C12:C14),0) -> 25307 | D13: =IFERROR(SUM('PL 2020-21'!B12:B14),0) -> 30003 | E13: =IFERROR(SUM('PL 2021-22'!B12:B14),0) -> 34114 | F13: =IFERROR(SUM('PL 2022-23'!B12:B14),0) -> 41330 | G13: =IFERROR(SUM('PL 2024-25'!C12:C14),0) -> 39524 | H13: =IFERROR(SUM('PL 2024-25'!B12:B14),0) -> 40708
B14: COGS%Sales | C14: =C13/C7 -> 0.52971219 | D14: =D13/D7 -> 0.58080065 | E14: =E13/E7 -> 0.58935112 | F14: =F13/F7 -> 0.58999029 | G14: =G13/G7 -> 0.55297657 | H14: =H13/H7 -> 0.56298058
B16: Gross Profit | C16: =C11-C13 -> 27368 | D16: =D11-D13 -> 28560 | E16: =E11-E13 -> 29481 | F16: =F11-F13 -> 36294 | G16: =G11-G13 -> 41534 | H16: =H11-H13 -> 40791
B17: GrossMargins | C17: =C16/C7 -> 0.57285191 | D17: =D16/D7 -> 0.55286693 | E17: =E16/E7 -> 0.50931173 | F17: =F16/F7 -> 0.51810084 | G17: =G16/G7 -> 0.58109829 | H17: =H16/H7 -> 0.56412845
B19: Employee Benefits Expenses | C19: =IFERROR('PL 2020-21'!C15,0) -> 4077 | D19: =IFERROR('PL 2020-21'!B15,0) -> 4518 | E19: =IFERROR('PL 2022-23'!C15,0) -> 4944 | F19: =IFERROR('PL 2022-23'!B15,0) -> 5585 | G19: =IFERROR('PL 2024-25'!C15,0) -> 6264 | H19: =IFERROR('PL 2024-25'!B15,0) -> 6467
B20: Emp Exp%Sales | C20: =C19/C7 -> 0.08533752 | D20: =D19/D7 -> 0.087459832 | E20: =E19/E7 -> 0.085412204 | F20: =F19/F7 -> 0.079726489 | G20: =G19/G7 -> 0.087639035 | H20: =H19/H7 -> 0.089436853
B22: Other exp | C22: =IFERROR('PL 2020-21'!C18,0) -> 11893 | D22: =IFERROR('PL 2020-21'!B18,0) -> 11101 | E22: =IFERROR('PL 2022-23'!C18,0) -> 11844 | F22: =IFERROR('PL 2022-23'!B18,0) -> 15329 | G22: =IFERROR('PL 2024-25'!C18,0) -> 15955 | H22: =IFERROR('PL 2024-25'!B18,0) -> 17784
C23: =C22/C7 -> 0.24893773 | D23: =D22/D7 -> 0.21489411 | E23: =E22/E7 -> 0.20461613 | F23: =F22/F7 -> 0.21882316 | G23: =G22/G7 -> 0.2232249 | H23: =H22/H7 -> 0.24594789
B24: EBITDA | C24: =C16-SUM(C19,C22) -> 11398 | D24: =D16-SUM(D19,D22) -> 12941 | E24: =E16-SUM(E19,E22) -> 12693 | F24: =F16-SUM(F19,F22) -> 15380 | G24: =G16-SUM(G19,G22) -> 19315 | H24: =H16-SUM(H19,H22) -> 16540
B25: EBITDA Margins | C25: =C24/C7 -> 0.23857666 | D25: =D24/D7 -> 0.25051299 | E25: =E24/E7 -> 0.21928339 | F25: =F24/F7 -> 0.21955119 | G25: =G24/G7 -> 0.27023435 | H25: =H24/H7 -> 0.22874371
B27: Interest | C27: =IFERROR('PL 2020-21'!C16,0) -> 113 | D27: =IFERROR('PL 2020-21'!B16,0) -> 762 | E27: =IFERROR('PL 2022-23'!C16,0) -> 1129 | F27: =IFERROR('PL 2022-23'!B16,0) -> 1254 | G27: =IFERROR('PL 2024-25'!C16,0) -> 1478 | H27: =IFERROR('PL 2024-25'!B16,0) -> 2223
B28: interse%sales | C28: =C27/C7 -> 0.0023652538 | D28: =D27/D7 -> 0.014750861 | E28: =E27/E7 -> 0.019504526 | F28: =F27/F7 -> 0.017900988 | G28: =G27/G7 -> 0.020678559 | H28: =H27/H7 -> 0.030743486
B30: D&A impairment expense | C30: =IFERROR('PL 2020-21'!C17,0) -> 956 | D30: =IFERROR('PL 2020-21'!B17,0) -> 914 | E30: =IFERROR('PL 2022-23'!C17,0) -> 990 | F30: =IFERROR('PL 2022-23'!B17,0) -> 1151 | G30: =IFERROR('PL 2024-25'!C17,0) -> 1830 | H30: =IFERROR('PL 2024-25'!B17,0) -> 1311
B31: Deprecation%Sales | C31: =C30/C7 -> 0.020010466 | D31: =D30/D7 -> 0.01769329 | E31: =E30/E7 -> 0.017103172 | F31: =F30/F7 -> 0.016430652 | G31: =G30/G7 -> 0.025603358 | H31: =H30/H7 -> 0.018130774
B33: Earnings Before Tax | C33: =IFERROR(C24-SUM(C27,C30),0) -> 10329 | D33: =IFERROR(D24-SUM(D27,D30),0) -> 11265 | E33: =IFERROR(E24-SUM(E27,E30),0) -> 10574 | F33: =IFERROR(F24-SUM(F27,F30),0) -> 12975 | G33: =IFERROR(G24-SUM(G27,G30),0) -> 16007 | H33: =IFERROR(H24-SUM(H27,H30),0) -> 13006
B34: EBT% Sales | C34: =C33/C7 -> 0.21620094 | D34: =D33/D7 -> 0.21806884 | E34: =E33/E7 -> 0.1826757 | F34: =F33/F7 -> 0.18521955 | G34: =G33/G7 -> 0.22395243 | H34: =H33/H7 -> 0.17986945
B36: Tax | C36: =IFERROR('PL 2020-21'!C24,0) -> 2153 | D36: =IFERROR('PL 2020-21'!B24,0) -> 2135 | E36: =IFERROR('PL 2022-23'!C24,0) -> 2397 | F36: =IFERROR('PL 2022-23'!B24,0) -> 2287 | G36: =IFERROR('PL 2024-25'!C24,0) -> 3375 | H36: =IFERROR('PL 2024-25'!B24,0) -> 3230
B37: Effective Tax Rate | C37: =C36/C33 -> 0.20844225 | D37: =D36/D33 -> 0.18952508 | E37: =E36/E33 -> 0.2266881 | F37: =F36/F33 -> 0.17626204 | G37: =G36/G33 -> 0.21084526 | H37: =H36/H33 -> 0.24834692
B39: Net Profit | C39: =IFERROR(C33-C36,0) -> 8176 | D39: =IFERROR(D33-D36,0) -> 9130 | E39: =IFERROR(E33-E36,0) -> 8177 | F39: =IFERROR(F33-F36,0) -> 10688 | G39: =IFERROR(G33-G36,0) -> 12632 | H39: =IFERROR(H33-H36,0) -> 9776
B40: Net Profit Margins | D40: =D39/D7 -> 0.17673932 | E40: =E39/E7 -> 0.14126529 | F40: =F39/F7 -> 0.15257237 | G40: =G39/G7 -> 0.17673312 | H40: =H39/H7 -> 0.13519942
C41: =C39/C7 -> 0.17113553
B42: No. OF Equity Shares | C42: 483.662 | D42: 483.662 | E42: 483.662 | F42: 483.662 | G42: 483.662 | H42: 483.662
B44: EPS | C44: =IFERROR(C39/C42,0) -> 16.904367 | D44: =IFERROR(D39/D42,0) -> 18.876819 | E44: =IFERROR(E39/E42,0) -> 16.906435 | F44: =IFERROR(F39/F42,0) -> 22.098077 | G44: =IFERROR(G39/G42,0) -> 26.117413 | H44: =IFERROR(H39/H42,0) -> 20.212462
B45: Eps Increase % | C45: =IFERROR(C44/#REF!-1,0) -> 0 | D45: =IFERROR(D44/C44-1,0) -> 0.11668297 | E45: =IFERROR(E44/D44-1,0) -> -0.10438116 | F45: =IFERROR(F44/E44-1,0) -> 0.30708084 | G45: =IFERROR(G44/F44-1,0) -> 0.18188623 | H45: =IFERROR(H44/G44-1,0) -> -0.22609246
B47: Dividend Per Share | C47: 1 | D47: 1 | E47: 6 | F47: 1 | G47: 1 | H47: 11 | J47: Data Source:https://www.moneycontrol.com/company-facts/wipro/dividends/W/
B48: Dicidend payout Ratio | C48: =IFERROR(C47/C44,0) -> 0.059156311 | D48: =IFERROR(D47/D44,0) -> 0.052975027 | E48: =IFERROR(E47/E44,0) -> 0.35489446 | F48: =IFERROR(F47/F44,0) -> 0.045252807 | G48: =IFERROR(G47/G44,0) -> 0.038288632 | H48: =IFERROR(H47/H44,0) -> 0.5442187
B50: Retained Earnings | C50: =IFERROR(IF(C44>C47,1-C48,0),0) -> 0.94084369 | D50: =IFERROR(IF(D44>D47,1-D48,0),0) -> 0.94702497 | E50: =IFERROR(IF(E44>E47,1-E48,0),0) -> 0.64510554 | F50: =IFERROR(IF(F44>F47,1-F48,0),0) -> 0.95474719 | G50: =IFERROR(IF(G44>G47,1-G48,0),0) -> 0.96171137 | H50: =IFERROR(IF(H44>H47,1-H48,0),0) -> 0.4557813
B52: Balance Sheet
B54: Equity Share Capital | C54: =IFERROR(SUM('BS 2020-21'!C33),0) -> 4837 | D54: =IFERROR(SUM('BS 2020-21'!B33),0) -> 4837 | E54: =IFERROR('BS 2022-23'!C36,0) -> 4837 | F54: =IFERROR('BS 2022-23'!B36,0) -> 4837 | G54: =IFERROR('BS 2024-25'!C37,0) -> 4837 | H54: =IFERROR('BS 2024-25'!B37,0) -> 4837
B55: Reserves | C55: =IFERROR(SUM('BS 2020-21'!C34),0) -> 78152 | D55: =IFERROR(SUM('BS 2020-21'!B34),0) -> 87753 | E55: =IFERROR('BS 2022-23'!C37,0) -> 96046 | F55: =IFERROR('BS 2022-23'!B37,0) -> 106557 | G55: =IFERROR('BS 2024-25'!C38,0) -> 119159 | H55: =IFERROR('BS 2024-25'!B38,0) -> 128849
B56: Borrowings | C56: =IFERROR('BS 2020-21'!C37,0) -> 1192 | D56: =IFERROR('BS 2020-21'!B37,0) -> 17375 | E56: =IFERROR('BS 2022-23'!C40,0) -> 18967 | F56: =IFERROR('BS 2022-23'!B40,0) -> 14985 | G56: =IFERROR('BS 2024-25'!C41,0) -> 11967 | H56: =IFERROR('BS 2024-25'!B41,0) -> 21551
B57: Other Non- Current Liabilities | C57: =IFERROR(SUM('BS 2020-21'!C38:C41),0) -> 1565 | D57: =IFERROR(SUM('BS 2020-21'!B38:B41),0) -> 2677 | E57: =IFERROR(SUM('BS 2022-23'!C41:C44),0) -> 1739 | F57: =IFERROR(SUM('BS 2022-23'!B41:B44),0) -> 2621 | G57: =IFERROR(SUM('BS 2024-25'!C42:C45),0) -> 3274 | H57: =IFERROR(SUM('BS 2024-25'!B42:B45),0) -> 1931
B58: Current Borrowings | C58: =IFERROR(SUM('BS 2020-21'!C44,'BS 2020-21'!C49),0) -> 1555 | D58: =IFERROR(SUM('BS 2020-21'!B44,'BS 2020-21'!B49),0) -> 2230 | E58: =IFERROR(SUM('BS 2022-23'!C47),0) -> 2862 | F58: =IFERROR(SUM('BS 2022-23'!B47),0) -> 9850 | G58: =IFERROR(SUM('BS 2024-25'!C48,),0) -> 11032 | H58: =IFERROR(SUM('BS 2024-25'!B48),0) -> 16419
B59: Payables | C59: =IFERROR(SUM('BS 2020-21'!C47:C48),0) -> 8909 | D59: =IFERROR(SUM('BS 2020-21'!B47:B48),0) -> 11208 | E59: =IFERROR(SUM('BS 2022-23'!C50:C51),0) -> 10978 | F59: =IFERROR(SUM('BS 2022-23'!B50:B51),0) -> 12275 | G59: =IFERROR(SUM('BS 2024-25'!C51:C52),0) -> 11103 | H59: =IFERROR(SUM('BS 2024-25'!B51:B52),0) -> 9311
B60: Other current Liabilities | C60: =IFERROR(SUM('BS 2020-21'!C45:C46,'BS 2020-21'!C50:C53),0) -> 2111 | D60: =IFERROR(SUM('BS 2020-21'!B45:B46,'BS 2020-21'!B50:B53),0) -> 2960 | E60: =IFERROR(SUM('BS 2022-23'!C48:C49,'BS 2022-23'!C52:C55),0) -> 4875 | F60: =IFERROR(SUM('BS 2022-23'!B48:B49,'BS 2022-23'!B52:B55),0) -> 4716 | G60: =IFERROR(SUM('BS 2024-25'!C49:C50,'BS 2024-25'!C53:C56),0) -> 4769 | H60: =IFERROR(SUM('BS 2024-25'!B49:B50,'BS 2024-25'!B53:B56),0) -> 6743
B61: Total Liabilities | C61: =IFERROR(SUM(C54:C60),0) -> 98321 | D61: =IFERROR(SUM(D54:D60),0) -> 129040 | E61: =IFERROR(SUM(E54:E60),0) -> 140304 | F61: =IFERROR(SUM(F54:F60),0) -> 155841 | G61: =IFERROR(SUM(G54:G60),0) -> 166141 | H61: =IFERROR(SUM(H54:H60),0) -> 189641
B63: Fixed Assets Net Block | C63: =IFERROR(SUM('BS 2020-21'!C9),0) -> 6866 | D63: =IFERROR(SUM('BS 2020-21'!B9),0) -> 6172 | E63: =IFERROR(SUM('BS 2022-23'!C9),0) -> 8897 | F63: =IFERROR(SUM('BS 2022-23'!B9,),0) -> 9793 | G63: =IFERROR(SUM('BS 2024-25'!C9),0) -> 9724 | H63: =IFERROR(SUM('BS 2024-25'!B9),0) -> 9605
B64: Capital Work in Progress | C64: =IFERROR('BS 2020-21'!C10,0) -> 578 | D64: =IFERROR('BS 2020-21'!B10,0) -> 984 | E64: =IFERROR('BS 2022-23'!C10,0) -> 1200 | F64: =IFERROR('BS 2022-23'!B10,0) -> 304 | G64: =IFERROR(SUM('BS 2024-25'!C10:C11),0) -> 281 | H64: =IFERROR(SUM('BS 2024-25'!B10:B11),0) -> 189
B65: Investments | C65: =IFERROR('BS 2020-21'!C14,0) -> 24560 | D65: =IFERROR('BS 2020-21'!B14,0) -> 30726 | E65: =IFERROR('BS 2022-23'!C14,0) -> 32785 | F65: =IFERROR('BS 2022-23'!B14,0) -> 33415 | G65: =IFERROR('BS 2024-25'!C15,0) -> 33176 | H65: =IFERROR('BS 2024-25'!B15,0) -> 58943
B66: Other Non-current Assets | C66: =IFERROR(SUM('BS 2020-21'!C11:C13,'BS 2020-21'!C15:C17),0) -> 2839 | D66: =IFERROR(SUM('BS 2020-21'!B11:B13,'BS 2020-21'!B15:B17),0) -> 19225 | E66: =IFERROR(SUM('BS 2022-23'!C11:C13,'BS 2022-23'!C15:C20),0) -> 21525 | F66: =IFERROR(SUM('BS 2022-23'!B11:B13,'BS 2022-23'!B15:B20),0) -> 19592 | G66: =IFERROR(SUM('BS 2024-25'!C16:C21,'BS 2024-25'!C12:C14),0) -> 26405 | H66: =IFERROR(SUM('BS 2024-25'!B12:B14,'BS 2024-25'!B16:B21),0) -> 25292
B67: Total Non Current Assests | C67: =IFERROR(SUM(C63:C66),0) -> 34843 | D67: =IFERROR(SUM(D63:D66),0) -> 57107 | E67: =IFERROR(SUM(E63:E66),0) -> 64407 | F67: =IFERROR(SUM(F63:F66),0) -> 63104 | G67: =IFERROR(SUM(G63:G66),0) -> 69586 | H67: =IFERROR(SUM(H63:H66),0) -> 94029
B69: Receivables | C69: =IFERROR('BS 2020-21'!C22,0) -> 4309 | D69: =IFERROR('BS 2020-21'!B22,0) -> 7451 | E69: =IFERROR('BS 2022-23'!C25,0) -> 5784 | F69: =IFERROR('BS 2022-23'!B25,0) -> 6799 | G69: =IFERROR('BS 2024-25'!C26,0) -> 7345 | H69: =IFERROR('BS 2024-25'!B26,0) -> 5932
B70: Inventory | C70: =IFERROR('BS 2020-21'!C20,0) -> 5846 | D70: =IFERROR('BS 2020-21'!B20,0) -> 5778 | E70: =IFERROR('BS 2022-23'!C23,0) -> 8616 | F70: =IFERROR('BS 2022-23'!B23,0) -> 8069 | G70: =IFERROR('BS 2024-25'!C24,0) -> 6402 | H70: =IFERROR('BS 2024-25'!B24,0) -> 7119
B71: Other current Assests | C71: =IFERROR(SUM('BS 2020-21'!C23,'BS 2020-21'!C25:C28),0) -> 4735 | D71: =IFERROR(SUM('BS 2020-21'!B23,'BS 2020-21'!B25:B28),0) -> 7863 | E71: =IFERROR(SUM('BS 2022-23'!C26,'BS 2022-23'!C28:C31),0) -> 3783 | F71: =IFERROR(SUM('BS 2022-23'!B26,'BS 2022-23'!B28:B31),0) -> 9158 | G71: =IFERROR(SUM('BS 2024-25'!C27,'BS 2024-25'!C29:C32),0) -> 6167 | H71: =IFERROR(SUM('BS 2024-25'!B27,'BS 2024-25'!B29:B32),0) -> 8658
B72: Short term Investment | C72: =IFERROR('BS 2020-21'!C21,0) -> 47238 | D72: =IFERROR('BS 2020-21'!B21,0) -> 49294 | E72: =IFERROR('BS 2022-23'!C24,0) -> 54972 | F72: =IFERROR('BS 2022-23'!B24,0) -> 67114 | G72: =IFERROR('BS 2024-25'!C25,0) -> 73332 | H72: =IFERROR('BS 2024-25'!B25,0) -> 70625
B73: Cash & Bank | C73: =IFERROR('BS 2020-21'!C24,0) -> 1350 | D73: =IFERROR('BS 2020-21'!B24,0) -> 1547 | E73: =IFERROR('BS 2022-23'!C27,0) -> 2742 | F73: =IFERROR('BS 2022-23'!B27,0) -> 1597 | G73: =IFERROR('BS 2024-25'!C28,0) -> 3309 | H73: =IFERROR('BS 2024-25'!B28,0) -> 3278
B74: Total Current Assests | C74: =SUM(C69:C73) -> 63478 | D74: =SUM(D69:D73) -> 71933 | E74: =SUM(E69:E73) -> 75897 | F74: =SUM(F69:F73) -> 92737 | G74: =SUM(G69:G73) -> 96555 | H74: =SUM(H69:H73) -> 95612
B76: Total t Assests | C76: =IFERROR(SUM(C74,C67),0) -> 98321 | D76: =IFERROR(SUM(D74,D67),0) -> 129040 | E76: =IFERROR(SUM(E74,E67),0) -> 140304 | F76: =IFERROR(SUM(F74,F67),0) -> 155841 | G76: =IFERROR(SUM(G74,G67),0) -> 166141 | H76: =IFERROR(SUM(H74,H67),0) -> 189641
B78: check | C78: =C76=C61 -> TRUE | D78: =D76=D61 -> TRUE | E78: =E76=E61 -> TRUE | F78: =F76=F61 -> TRUE | G78: =G76=G61 -> TRUE | H78: =H76=H61 -> TRUE
B80: Cash Flow Statement
B81: Particulars
B82: A. Cash flows from operating activities
B83: Profit From operation | C83: =IFERROR(SUM('CF 2020-21'!C8:C17),0) -> 6900 | D83: =IFERROR(SUM('CF 2020-21'!B8:B17),0) -> 6389 | E83: =IFERROR(SUM('CF 2022-23'!C8:C16),0) -> 7393 | F83: =IFERROR(SUM('CF 2022-23'!B8:B16),0) -> 8492 | G83: =IFERROR(SUM('CF 2024-25'!C8:C18,),0) -> 10345 | H83: =IFERROR(SUM('CF 2024-25'!B8:B18,),0) -> 8661
B84: Receivables | C84: =IFERROR('CF 2020-21'!C18,0) -> 1351 | D84: =IFERROR('CF 2020-21'!B18,0) -> -3137 | E84: =IFERROR('CF 2022-23'!C17,0) -> 1181 | F84: =IFERROR('CF 2022-23'!B17,0) -> -595 | G84: =IFERROR('CF 2024-25'!C19,0) -> -439 | H84: =IFERROR('CF 2024-25'!B19,0) -> 764
B85: Inventories | C85: =IFERROR('CF 2020-21'!C20,0) -> 386 | D85: =IFERROR('CF 2020-21'!B20,0) -> 68 | E85: =IFERROR('CF 2022-23'!C19,0) -> -2720 | F85: =IFERROR('CF 2022-23'!B19,0) -> 547 | G85: =IFERROR('CF 2024-25'!C21,0) -> 1667 | H85: =IFERROR('CF 2024-25'!B21,0) -> -717
B86: Other WC items | C86: =IFERROR(SUM('CF 2020-21'!C19,'CF 2020-21'!C21),0) -> -3066 | D86: =IFERROR(SUM('CF 2020-21'!B19,'CF 2020-21'!B21),0) -> 3048 | E86: =IFERROR(SUM('CF 2022-23'!C20,'CF 2022-23'!C18),0) -> -645 | F86: =IFERROR(SUM('CF 2022-23'!B20,'CF 2022-23'!B18),0) -> 943 | G86: =IFERROR(SUM('CF 2024-25'!C20,'CF 2024-25'!C22),0) -> -65 | H86: =IFERROR(SUM('CF 2024-25'!B20,'CF 2024-25'!B22),0) -> -1161
B87: Direct taxes paid, net | C87: =IFERROR('CF 2020-21'!C23,0) -> -1843 | D87: =IFERROR('CF 2020-21'!B23,0) -> -1698 | E87: =IFERROR('CF 2022-23'!C22,0) -> -2088 | F87: =IFERROR('CF 2022-23'!B22,0) -> -2513 | G87: =IFERROR('CF 2024-25'!C24,0) -> -2887 | H87: =IFERROR('CF 2024-25'!B24,0) -> -2989
B88: Net cash generated from operating activities | C88: =IFERROR(SUM(C83:C87),0) -> 3728 | D88: =IFERROR(SUM(D83:D87),0) -> 4670 | E88: =IFERROR(SUM(E83:E87),0) -> 3121 | F88: =IFERROR(SUM(F83:F87),0) -> 6874 | G88: =IFERROR(SUM(G83:G87),0) -> 8621 | H88: =IFERROR(SUM(H83:H87),0) -> 4558
B89: B. Cash flows from investing activities
B90: Fixed Assets Purchased | C90: =IFERROR('CF 2020-21'!C26,0) -> -851 | D90: =IFERROR('CF 2020-21'!B26,0) -> -511 | E90: =IFERROR('CF 2022-23'!C25,0) -> -2158 | F90: =IFERROR('CF 2022-23'!B25,0) -> -1662 | G90: =IFERROR('CF 2024-25'!C27,0) -> -861 | H90: =IFERROR('CF 2024-25'!B27,0) -> -1410
B91: Fixed Assets Sold | C91: =IFERROR('CF 2020-21'!C27,0) -> 2 | D91: =IFERROR('CF 2020-21'!B27,0) -> 32 | E91: =IFERROR('CF 2022-23'!C26,0) -> 31 | F91: =IFERROR('CF 2022-23'!B26,0) -> 13 | G91: =IFERROR('CF 2024-25'!C28,0) -> 28 | H91: =IFERROR('CF 2024-25'!B28,0) -> 125
B92: Investments Purchased | C92: =IFERROR(SUM('CF 2020-21'!C28:C30),0) -> -111437 | D92: =IFERROR(SUM('CF 2020-21'!B28:B30),0) -> -100797 | E92: =IFERROR(SUM('CF 2022-23'!C27:C29),0) -> -90873 | F92: =IFERROR(SUM('CF 2022-23'!B27:B29),0) -> -104596 | G92: =IFERROR(SUM('CF 2024-25'!C29:C30),0) -> -75573 | H92: =IFERROR(SUM('CF 2024-25'!B29:B30),0) -> -159339
B93: Investments Sold | C93: =IFERROR(SUM('CF 2020-21'!C31:C32),0) -> 107569 | D93: =IFERROR(SUM('CF 2020-21'!B31:B32),0) -> 104462 | E93: =IFERROR(SUM('CF 2022-23'!C30:C31),0) -> 88134 | F93: =IFERROR(SUM('CF 2022-23'!B30:B31),0) -> 97988 | G93: =IFERROR(SUM('CF 2024-25'!C31:C32),0) -> 74452 | H93: =IFERROR(SUM('CF 2024-25'!B31:B32),0) -> 145798
B94: Interest Received/Dividends recived | C94: =IFERROR('CF 2020-21'!C36,0) -> 1218 | D94: =IFERROR('CF 2020-21'!B36,0) -> 1047 | E94: =IFERROR('CF 2022-23'!C35,0) -> 2077 | F94: =IFERROR('CF 2022-23'!B35,0) -> 2460 | G94: =IFERROR(SUM('CF 2024-25'!C38:C39),0) -> 3305 | H94: =IFERROR(SUM('CF 2024-25'!B38:B39),0) -> 1626
B95: Investment in Group Companies | C95: =IFERROR(SUM('CF 2020-21'!C33:C34),0) -> -125 | D95: =IFERROR(SUM('CF 2020-21'!B33:B34),0) -> -21846 | E95: =IFERROR(SUM('CF 2022-23'!C32:C33),0) -> -3795 | F95: =IFERROR(SUM('CF 2022-23'!B32:B33),0) -> -3885 | G95: =IFERROR(SUM('CF 2024-25'!C34:C35),0) -> -3820 | H95: =IFERROR(SUM('CF 2024-25'!B34:B35),0) -> -5797
B96: Redemption & Cancellation of Shares
B97: Acquisition of Companies | G97: =IFERROR('CF 2024-25'!C33,0) -> -3388 | H97: =IFERROR('CF 2024-25'!B33,0) -> 0
B98: Inter-Corporate Deposits | C98: =IFERROR('CF 2020-21'!C35,0) -> 0 | D98: =IFERROR('CF 2020-21'!B35,0) -> -3518 | E98: =IFERROR('CF 2022-23'!C34,0) -> 3518 | F98: =IFERROR('CF 2022-23'!B34,0) -> 0 | G98: {=IFERROR('CF 2024-25'!n0,0)} -> 0 | H98: {=IFERROR('CF 2024-25'!n0,0)} -> 0
B99: Other Investing Items | G99: =IFERROR(SUM('CF 2024-25'!C36,'CF 2024-25'!C37),0) -> 3248 | H99: =IFERROR(SUM('CF 2024-25'!B36,'CF 2024-25'!B37),0) -> 1793
B100: Cash From Investing Activities | C100: =IFERROR(SUM(C90:C99),0) -> -3624 | D100: =IFERROR(SUM(D90:D99),0) -> -21131 | E100: =IFERROR(SUM(E90:E99),0) -> -3066 | F100: =IFERROR(SUM(F90:F99),0) -> -9682 | G100: =IFERROR(SUM(G90:G99),0) -> -2609 | H100: =IFERROR(SUM(H90:H99),0) -> -17204
B101: C. Cash flows from financing activities
B102: Proceeds from Shares
B103: Proceeds from Borrowings | C103: =IFERROR('CF 2020-21'!C40,0) -> 161 | D103: =IFERROR('CF 2020-21'!B40,0) -> 17677 | E103: =IFERROR('CF 2022-23'!C39,0) -> 11326 | F103: =IFERROR('CF 2022-23'!B39,0) -> 5520 | G103: =IFERROR('CF 2024-25'!C44,0) -> 7481 | H103: =IFERROR('CF 2024-25'!B44,0) -> 21342
B104: Repayment of Borrowings | C104: =IFERROR('CF 2020-21'!C42,0) -> -310 | D104: =IFERROR('CF 2020-21'!B42,0) -> -201 | E104: =IFERROR('CF 2022-23'!C41,0) -> -9090 | F104: =IFERROR('CF 2022-23'!B41,0) -> -2514 | G104: =IFERROR('CF 2024-25'!C47,0) -> -9317 | H104: =IFERROR('CF 2024-25'!B47,0) -> -6371
B105: Interest Paid | C105: =IFERROR('CF 2020-21'!C39,0) -> -88 | D105: =IFERROR('CF 2020-21'!B39,0) -> -742 | E105: =IFERROR('CF 2022-23'!C38,0) -> -1114 | F105: =IFERROR('CF 2022-23'!B38,0) -> -1242 | G105: =IFERROR('CF 2024-25'!C42,0) -> -1608 | H105: =IFERROR('CF 2024-25'!B42,0) -> -2256
B106: Dividends Paid
B107: Financial Liabilities
B108: Other Financing Items | C108: =IFERROR(SUM('CF 2020-21'!C41),0) -> -86 | D108: =IFERROR(SUM('CF 2020-21'!B41),0) -> -77 | E108: =IFERROR(SUM('CF 2022-23'!C40),0) -> -90 | F108: =IFERROR(SUM('CF 2022-23'!B40),0) -> -101 | G108: =IFERROR(SUM('CF 2024-25'!C43,'CF 2024-25'!C45,'CF 2024-25'!C46),0) -> -856 | H108: =IFERROR(SUM('CF 2024-25'!B43,'CF 2024-25'!B45,'CF 2024-25'!B46),0) -> -100
B109: Cash From Financing Activities | C109: =IFERROR(SUM(C101:C108),0) -> -323 | D109: =IFERROR(SUM(D101:D108),0) -> 16657 | E109: =IFERROR(SUM(E101:E108),0) -> 1032 | F109: =IFERROR(SUM(F101:F108),0) -> 1663 | G109: =IFERROR(SUM(G101:G108),0) -> -4300 | H109: =IFERROR(SUM(H101:H108),0) -> 12615
B110: Components of cash and cash equivalents | C110: =IFERROR(SUM(C88,C100,C109),0) -> -219 | D110: =IFERROR(SUM(D88,D100,D109),0) -> 196 | E110: =IFERROR(SUM(E88,E100,E109),0) -> 1087 | F110: =IFERROR(SUM(F88,F100,F109),0) -> -1145 | G110: =IFERROR(SUM(G88,G100,G109),0) -> 1712 | H110: =IFERROR(SUM(H88,H100,H109),0) -> -31
B113: Market Price Of Share | C113: 196.7 | D113: 414.15 | E113: 591.9 | F113: 365.25 | G113: 480.1 | H113: 262.25
B114: EPS Growth | C114: =AVEDEV(C45:H45) -> 0.15602061 | D114: Growth Rate = Expected EPS Growth (%)
B115: Market Cap | C115: =C113*C42 -> 95136.315 | D115: =D113*D42 -> 200308.62 | E115: =E113*E42 -> 286279.54 | F115: =F113*F42 -> 176657.55 | G115: =G113*G42 -> 232206.13 | H115: =H113*H42 -> 126840.36
B116: Enterprise Value | C116: =IFERROR(C115+C56+C58+D123+D124+D125-C73,0) -> 97575.315 | D116: =IFERROR(D115+D56+D58+E123+E124+E125-D73,0) -> 219373.62 | E116: =IFERROR(E115+E56+E58+F123+F124+F125-E73,0) -> 305517.54 | F116: =IFERROR(F115+F56+F58+G123+G124+G125-F73,0) -> 200000.55 | G116: =IFERROR(G115+G56+G58+H123+H124+H125-G73,0) -> 252002.13 | H116: =IFERROR(H115+H56+H58+I123+I124+I125-H73,0) -> 161656.36
B122: Working Notes no.1 Parameter consider for enterprise value | D122: =C3 -> 43921 | E122: =D3 -> 44286 | F122: =E3 -> 44651 | G122: =F3 -> 45016 | H122: =G3 -> 45382 | I122: =H3 -> 45747
B123: =IFERROR('BS 2020-21'!A45,0) -> Financial liabilities - Lease liabilities | D123: ='BS 2020-21'!C38 -> 130 | E123: ='BS 2020-21'!B38 -> 61 | F123: ='BS 2022-23'!C41 -> 32 | G123: ='BS 2022-23'!B41 -> 22 | H123: ='BS 2024-25'!C42 -> 79 | I123: ='BS 2024-25'!B42 -> 109
B124: ='BS 2020-21'!A49 -> Current maturities of long-term debt | D124: =IFERROR('BS 2020-21'!C49,0) -> 794 | E124: =IFERROR('BS 2020-21'!B49,0) -> 816
B125: ='BS 2020-21'!A38 -> Financial liabilities - Lease liabilities | D125: ='BS 2020-21'!C45 -> 118 | E125: ='BS 2020-21'!B45 -> 130 | F125: ='BS 2022-23'!C48 -> 119 | G125: ='BS 2022-23'!B48 -> 83 | H125: ='BS 2024-25'!C49 -> 27 | I125: ='BS 2024-25'!B49 -> 15
B126: Borrowings | D126: =C56 -> 1192 | E126: =D56 -> 17375 | F126: =E56 -> 18967 | G126: =F56 -> 14985 | H126: =G56 -> 11967 | I126: =H56 -> 21551
B127: Current Borrowings | D127: =C58 -> 1555 | E127: =D58 -> 2230 | F127: =E58 -> 2862 | G127: =F58 -> 9850 | H127: =G58 -> 11032 | I127: =H58 -> 16419
B128: Cash & Bank | D128: =C73 -> 1350 | E128: =D73 -> 1547 | F128: =E73 -> 2742 | G128: =F73 -> 1597 | H128: =G73 -> 3309 | I128: =H73 -> 3278
...

Sheet Ratio Analysis
B1: Ratio Analysis-Wipro Ltd
B2: Years | C2: =HistoriacalIFLS!C3 -> 43921 | D2: =HistoriacalIFLS!D3 -> 44286 | E2: =HistoriacalIFLS!E3 -> 44651 | F2: =HistoriacalIFLS!F3 -> 45016 | G2: =HistoriacalIFLS!G3 -> 45382 | H2: =HistoriacalIFLS!H3 -> 45747 | I2: Trend | J2: Mean | K2: Median
B4: Sales Growth | D4: =HistoriacalIFLS!D8 -> 0.081276818 | E4: =HistoriacalIFLS!E8 -> 0.12052344 | F4: =HistoriacalIFLS!F8 -> 0.21021353 | G4: =HistoriacalIFLS!G8 -> 0.020313481 | H4: =HistoriacalIFLS!H8 -> 0.011654425 | J4: =IFERROR(AVERAGE(D4:H4),0) -> 0.08879634 | K4: =IFERROR(MEDIAN(C4:H4),0) -> 0.081276818
B5: EBITDA Growth | D5: =IFERROR((HistoriacalIFLS!D24/HistoriacalIFLS!C24)-1,0) -> 0.13537463 | E5: =IFERROR((HistoriacalIFLS!E24/HistoriacalIFLS!D24)-1,0) -> -0.019163898 | F5: =IFERROR((HistoriacalIFLS!F24/HistoriacalIFLS!E24)-1,0) -> 0.21169148 | G5: =IFERROR((HistoriacalIFLS!G24/HistoriacalIFLS!F24)-1,0) -> 0.25585176 | H5: =IFERROR((HistoriacalIFLS!H24/HistoriacalIFLS!G24)-1,0) -> -0.14367072 | J5: =IFERROR(AVERAGE(D5:H5),0) -> 0.088016649 | K5: =IFERROR(MEDIAN(C5:H5),0) -> 0.13537463
B6: EBIT Growth | D6: =IFERROR((HistoriacalIFLS!D24-HistoriacalIFLS!D30)/(HistoriacalIFLS!C24-HistoriacalIFLS!C30)-1,0) -> 0.15179084 | E6: =IFERROR((HistoriacalIFLS!E24-HistoriacalIFLS!E30)/(HistoriacalIFLS!D24-HistoriacalIFLS!D30)-1,0) -> -0.026939386 | F6: =IFERROR((HistoriacalIFLS!F24-HistoriacalIFLS!F30)/(HistoriacalIFLS!E24-HistoriacalIFLS!E30)-1,0) -> 0.21584209 | G6: =IFERROR((HistoriacalIFLS!G24-HistoriacalIFLS!G30)/(HistoriacalIFLS!F24-HistoriacalIFLS!F30)-1,0) -> 0.22882845 | H6: =IFERROR((HistoriacalIFLS!H24-HistoriacalIFLS!H30)/(HistoriacalIFLS!G24-HistoriacalIFLS!G30)-1,0) -> -0.12902488 | J6: =IFERROR(AVERAGE(D6:H6),0) -> 0.088099424 | K6: =IFERROR(MEDIAN(C6:H6),0) -> 0.15179084
B7: Net Profit Gowth | D7: =IFERROR((HistoriacalIFLS!D39/HistoriacalIFLS!C39)-1,0) -> 0.11668297 | E7: =IFERROR((HistoriacalIFLS!E39/HistoriacalIFLS!D39)-1,0) -> -0.10438116 | F7: =IFERROR((HistoriacalIFLS!F39/HistoriacalIFLS!E39)-1,0) -> 0.30708084 | G7: =IFERROR((HistoriacalIFLS!G39/HistoriacalIFLS!F39)-1,0) -> 0.18188623 | H7: =IFERROR((HistoriacalIFLS!H39/HistoriacalIFLS!G39)-1,0) -> -0.22609246 | J7: =IFERROR(AVERAGE(D7:H7),0) -> 0.055035283 | K7: =IFERROR(MEDIAN(C7:H7),0) -> 0.11668297
B8: Dividend Growth | D8: =HistoriacalIFLS!D47/HistoriacalIFLS!C47 -> 1 | E8: =HistoriacalIFLS!E47/HistoriacalIFLS!D47 -> 6 | F8: =HistoriacalIFLS!F47/HistoriacalIFLS!E47 -> 0.16666667 | G8: =HistoriacalIFLS!G47/HistoriacalIFLS!F47 -> 1 | H8: =HistoriacalIFLS!H47/HistoriacalIFLS!G47 -> 11 | J8: =IFERROR(AVERAGE(D8:H8),0) -> 3.8333333 | K8: =IFERROR(MEDIAN(C8:H8),0) -> 1
B10: Gross Margin | C10: =IFERROR(HistoriacalIFLS!C17,0) -> 0.57285191 | D10: =IFERROR(HistoriacalIFLS!D17,0) -> 0.55286693 | E10: =IFERROR(HistoriacalIFLS!E17,0) -> 0.50931173 | F10: =IFERROR(HistoriacalIFLS!F17,0) -> 0.51810084 | G10: =IFERROR(HistoriacalIFLS!G17,0) -> 0.58109829 | H10: =IFERROR(HistoriacalIFLS!H17,0) -> 0.56412845 | J10: =IFERROR(AVERAGE(C10:H10),0) -> 0.54972636 | K10: =IFERROR(MEDIAN(C10:H10),0) -> 0.55849769
B11: EBITDA Margin | C11: =IFERROR(HistoriacalIFLS!C25,0) -> 0.23857666 | D11: =IFERROR(HistoriacalIFLS!D25,0) -> 0.25051299 | E11: =IFERROR(HistoriacalIFLS!E25,0) -> 0.21928339 | F11: =IFERROR(HistoriacalIFLS!F25,0) -> 0.21955119 | G11: =IFERROR(HistoriacalIFLS!G25,0) -> 0.27023435 | H11: =IFERROR(HistoriacalIFLS!H25,0) -> 0.22874371 | J11: =IFERROR(AVERAGE(C11:H11),0) -> 0.23781705 | K11: =IFERROR(MEDIAN(C11:H11),0) -> 0.23366018
B12: EBIT Margin | C12: =IFERROR((HistoriacalIFLS!C24-HistoriacalIFLS!C30)/(HistoriacalIFLS!C11),0) -> 0.19823446 | D12: =IFERROR((HistoriacalIFLS!D24-HistoriacalIFLS!D30)/(HistoriacalIFLS!D11),0) -> 0.20536858 | E12: =IFERROR((HistoriacalIFLS!E24-HistoriacalIFLS!E30)/(HistoriacalIFLS!E11),0) -> 0.1840239 | F12: =IFERROR((HistoriacalIFLS!F24-HistoriacalIFLS!F30)/(HistoriacalIFLS!F11),0) -> 0.18330671 | G12: =IFERROR((HistoriacalIFLS!G24-HistoriacalIFLS!G30)/(HistoriacalIFLS!G11),0) -> 0.21570974 | H12: =IFERROR((HistoriacalIFLS!H24-HistoriacalIFLS!H30)/(HistoriacalIFLS!H11),0) -> 0.18686119 | J12: =IFERROR(AVERAGE(C12:H12),0) -> 0.1955841 | K12: =IFERROR(MEDIAN(C12:H12),0) -> 0.19254782
B13: EBT Margin | C13: =IFERROR(HistoriacalIFLS!C34,0) -> 0.21620094 | D13: =IFERROR(HistoriacalIFLS!D34,0) -> 0.21806884 | E13: =IFERROR(HistoriacalIFLS!E34,0) -> 0.1826757 | F13: =IFERROR(HistoriacalIFLS!F34,0) -> 0.18521955 | G13: =IFERROR(HistoriacalIFLS!G34,0) -> 0.22395243 | H13: =IFERROR(HistoriacalIFLS!H34,0) -> 0.17986945 | J13: =IFERROR(AVERAGE(C13:H13),0) -> 0.20099782 | K13: =IFERROR(MEDIAN(C13:H13),0) -> 0.20071025
B14: Net Profit Margin | C14: =IFERROR(HistoriacalIFLS!C41,0) -> 0.17113553 | D14: =IFERROR(HistoriacalIFLS!D40,0) -> 0.17673932 | E14: =IFERROR(HistoriacalIFLS!E40,0) -> 0.14126529 | F14: =IFERROR(HistoriacalIFLS!F40,0) -> 0.15257237 | G14: =IFERROR(HistoriacalIFLS!G40,0) -> 0.17673312 | H14: =IFERROR(HistoriacalIFLS!H40,0) -> 0.13519942 | J14: =IFERROR(AVERAGE(C14:H14),0) -> 0.15894084 | K14: =IFERROR(MEDIAN(C14:H14),0) -> 0.16185395
B16: EmployeeExpenses%Sales | C16: =IFERROR(HistoriacalIFLS!C20,0) -> 0.08533752 | D16: =IFERROR(HistoriacalIFLS!D20,0) -> 0.087459832 | E16: =IFERROR(HistoriacalIFLS!E20,0) -> 0.085412204 | F16: =IFERROR(HistoriacalIFLS!F20,0) -> 0.079726489 | G16: =IFERROR(HistoriacalIFLS!G20,0) -> 0.087639035 | H16: =IFERROR(HistoriacalIFLS!H20,0) -> 0.089436853 | J16: =IFERROR(AVERAGE(C16:H16),0) -> 0.085835322 | K16: =IFERROR(MEDIAN(C16:H16),0) -> 0.086436018
B17: Deprecation&Amortization %Sales | C17: =IFERROR(HistoriacalIFLS!C31,0) -> 0.020010466 | D17: =IFERROR(HistoriacalIFLS!D31,0) -> 0.01769329 | E17: =IFERROR(HistoriacalIFLS!E31,0) -> 0.017103172 | F17: =IFERROR(HistoriacalIFLS!F31,0) -> 0.016430652 | G17: =IFERROR(HistoriacalIFLS!G31,0) -> 0.025603358 | H17: =IFERROR(HistoriacalIFLS!H31,0) -> 0.018130774 | J17: =IFERROR(AVERAGE(C17:H17),0) -> 0.019161952 | K17: =IFERROR(MEDIAN(C17:H17),0) -> 0.017912032
B18: OperatingIncome%Sales | C18: =IFERROR(HistoriacalIFLS!C14,0) -> 0.52971219 | D18: =IFERROR(HistoriacalIFLS!D14,0) -> 0.58080065 | E18: =IFERROR(HistoriacalIFLS!E14,0) -> 0.58935112 | F18: =IFERROR(HistoriacalIFLS!F14,0) -> 0.58999029 | G18: =IFERROR(HistoriacalIFLS!G14,0) -> 0.55297657 | H18: =IFERROR(HistoriacalIFLS!H14,0) -> 0.56298058 | J18: =IFERROR(AVERAGE(C18:H18),0) -> 0.56763523 | K18: =IFERROR(MEDIAN(C18:H18),0) -> 0.57189062
B20: Return On Capital Employed | C20: =IFERROR((HistoriacalIFLS!C24-HistoriacalIFLS!C30)/SUM(HistoriacalIFLS!C54:C56),0) -> 0.12404224 | D20: =IFERROR((HistoriacalIFLS!D24-HistoriacalIFLS!D30)/SUM(HistoriacalIFLS!D54:D56),0) -> 0.10937116 | E20: =IFERROR((HistoriacalIFLS!E24-HistoriacalIFLS!E30)/SUM(HistoriacalIFLS!E54:E56),0) -> 0.097647059 | F20: =IFERROR((HistoriacalIFLS!F24-HistoriacalIFLS!F30)/SUM(HistoriacalIFLS!F54:F56),0) -> 0.11258991 | G20: =IFERROR((HistoriacalIFLS!G24-HistoriacalIFLS!G30)/SUM(HistoriacalIFLS!G54:G56),0) -> 0.12860116 | H20: =IFERROR((HistoriacalIFLS!H24-HistoriacalIFLS!H30)/SUM(HistoriacalIFLS!H54:H56),0) -> 0.098101612 | J20: =IFERROR(AVERAGE(C20:H20),0) -> 0.11172552 | K20: =IFERROR(MEDIAN(C20:H20),0) -> 0.11098054
B21: Retained Earnings% | C21: =IFERROR(HistoriacalIFLS!C50,0) -> 0.94084369 | D21: =IFERROR(HistoriacalIFLS!D50,0) -> 0.94702497 | E21: =IFERROR(HistoriacalIFLS!E50,0) -> 0.64510554 | F21: =IFERROR(HistoriacalIFLS!F50,0) -> 0.95474719 | G21: =IFERROR(HistoriacalIFLS!G50,0) -> 0.96171137 | H21: =IFERROR(HistoriacalIFLS!H50,0) -> 0.4557813 | J21: =IFERROR(AVERAGE(C21:H21),0) -> 0.81753568 | K21: =IFERROR(MEDIAN(C21:H21),0) -> 0.94393433
B22: Return On Equity% | C22: =IFERROR((HistoriacalIFLS!C39/SUM(HistoriacalIFLS!C54:C55)),0) -> 0.098519081 | D22: =IFERROR((HistoriacalIFLS!D39/SUM(HistoriacalIFLS!D54:D55)),0) -> 0.098606761 | E22: =IFERROR((HistoriacalIFLS!E39/SUM(HistoriacalIFLS!E54:E55)),0) -> 0.081054291 | F22: =IFERROR((HistoriacalIFLS!F39/SUM(HistoriacalIFLS!F54:F55)),0) -> 0.095947717 | G22: =IFERROR((HistoriacalIFLS!G39/SUM(HistoriacalIFLS!G54:G55)),0) -> 0.10187425 | H22: =IFERROR((HistoriacalIFLS!H39/SUM(HistoriacalIFLS!H54:H55)),0) -> 0.07312658 | J22: =IFERROR(AVERAGE(C22:H22),0) -> 0.091521447 | K22: =IFERROR(MEDIAN(C22:H22),0) -> 0.097233399
B23: Self Sustained Growth Rate | C23: =IFERROR(C21*C22,0) -> 0.092691055 | D23: =IFERROR(D21*D22,0) -> 0.093383065 | E23: =IFERROR(E21*E22,0) -> 0.052288572 | F23: =IFERROR(F21*F22,0) -> 0.091605814 | G23: =IFERROR(G21*G22,0) -> 0.097973628 | H23: =IFERROR(H21*H22,0) -> 0.033329728 | J23: =IFERROR(AVERAGE(C23:H23),0) -> 0.076878644 | K23: =IFERROR(MEDIAN(C23:H23),0) -> 0.092148435
B24: Return on Assets | C24: =IFERROR(SUM(HistoriacalIFLS!C33,HistoriacalIFLS!C27)/(HistoriacalIFLS!C76),0) -> 0.10620315 | D24: =IFERROR(SUM(HistoriacalIFLS!D33,HistoriacalIFLS!D27)/(HistoriacalIFLS!D76),0) -> 0.093203658 | E24: =IFERROR(SUM(HistoriacalIFLS!E33,HistoriacalIFLS!E27)/(HistoriacalIFLS!E76),0) -> 0.083411735 | F24: =IFERROR(SUM(HistoriacalIFLS!F33,HistoriacalIFLS!F27)/(HistoriacalIFLS!F76),0) -> 0.091304599 | G24: =IFERROR(SUM(HistoriacalIFLS!G33,HistoriacalIFLS!G27)/(HistoriacalIFLS!G76),0) -> 0.10524193 | H24: =IFERROR(SUM(HistoriacalIFLS!H33,HistoriacalIFLS!H27)/(HistoriacalIFLS!H76),0) -> 0.080304365
B25: Interest Coverage Ratio | C25: =IFERROR((HistoriacalIFLS!C24-HistoriacalIFLS!C30)/(HistoriacalIFLS!C11),0) -> 0.19823446 | D25: =IFERROR((HistoriacalIFLS!D24-HistoriacalIFLS!D30)/(HistoriacalIFLS!D11),0) -> 0.20536858 | E25: =IFERROR((HistoriacalIFLS!E24-HistoriacalIFLS!E30)/(HistoriacalIFLS!E11),0) -> 0.1840239 | F25: =IFERROR((HistoriacalIFLS!F24-HistoriacalIFLS!F30)/(HistoriacalIFLS!F11),0) -> 0.18330671 | G25: =IFERROR((HistoriacalIFLS!G24-HistoriacalIFLS!G30)/(HistoriacalIFLS!G11),0) -> 0.21570974 | H25: =IFERROR((HistoriacalIFLS!H24-HistoriacalIFLS!H30)/(HistoriacalIFLS!H11),0) -> 0.18686119 | J25: =IFERROR(AVERAGE(C25:H25),0) -> 0.1955841 | K25: =IFERROR(MEDIAN(C25:H25),0) -> 0.19254782
B27: Debtors Turnover Ratio | C27: =IFERROR(HistoriacalIFLS!C7/HistoriacalIFLS!C69,0) -> 11.087259 | D27: =IFERROR(HistoriacalIFLS!D7/HistoriacalIFLS!D69,0) -> 6.9330291 | E27: =IFERROR(HistoriacalIFLS!E7/HistoriacalIFLS!E69,0) -> 10.007607 | F27: =IFERROR(HistoriacalIFLS!F7/HistoriacalIFLS!F69,0) -> 10.30328 | G27: =IFERROR(HistoriacalIFLS!G7/HistoriacalIFLS!G69,0) -> 9.7311096 | H27: =IFERROR(HistoriacalIFLS!H7/HistoriacalIFLS!H69,0) -> 12.189481 | J27: =IFERROR(AVERAGE(C27:H27),0) -> 10.041961 | K27: =IFERROR(MEDIAN(C27:H27),0) -> 10.155444
B28: Ceditor Turnover Ratio | C28: =IFERROR(HistoriacalIFLS!C7/HistoriacalIFLS!C59,0) -> 5.3625547 | D28: =IFERROR(HistoriacalIFLS!D7/HistoriacalIFLS!D59,0) -> 4.6090293 | E28: =IFERROR(HistoriacalIFLS!E7/HistoriacalIFLS!E59,0) -> 5.2727273 | F28: =IFERROR(HistoriacalIFLS!F7/HistoriacalIFLS!F59,0) -> 5.7068839 | G28: =IFERROR(HistoriacalIFLS!G7/HistoriacalIFLS!G59,0) -> 6.4374493 | H28: =IFERROR(HistoriacalIFLS!H7/HistoriacalIFLS!H59,0) -> 7.7658683 | J28: =IFERROR(AVERAGE(C28:H28),0) -> 5.8590855 | K28: =IFERROR(MEDIAN(C28:H28),0) -> 5.5347193
B29: Inventory Turnover Ratio | C29: =IFERROR(HistoriacalIFLS!C7/HistoriacalIFLS!C70,0) -> 8.1722545 | D29: =IFERROR(HistoriacalIFLS!D7/HistoriacalIFLS!D70,0) -> 8.9404638 | E29: =IFERROR(HistoriacalIFLS!E7/HistoriacalIFLS!E70,0) -> 6.7181987 | F29: =IFERROR(HistoriacalIFLS!F7/HistoriacalIFLS!F70,0) -> 8.681621 | G29: =IFERROR(HistoriacalIFLS!G7/HistoriacalIFLS!G70,0) -> 11.16448 | H29: =IFERROR(HistoriacalIFLS!H7/HistoriacalIFLS!H70,0) -> 10.157045 | J29: =IFERROR(AVERAGE(C29:H29),0) -> 8.9723437 | K29: =IFERROR(MEDIAN(C29:H29),0) -> 8.8110424
B30: Fixed Assets Turnover Ratio | C30: =IFERROR(HistoriacalIFLS!C7/HistoriacalIFLS!C63,0) -> 6.9581998 | D30: =IFERROR(HistoriacalIFLS!D7/HistoriacalIFLS!D63,0) -> 8.3697343 | E30: =IFERROR(HistoriacalIFLS!E7/HistoriacalIFLS!E63,0) -> 6.5060133 | F30: =IFERROR(HistoriacalIFLS!F7/HistoriacalIFLS!F63,0) -> 7.1532727 | G30: =IFERROR(HistoriacalIFLS!G7/HistoriacalIFLS!G63,0) -> 7.3503702 | H30: =IFERROR(HistoriacalIFLS!H7/HistoriacalIFLS!H63,0) -> 7.5281624 | J30: =IFERROR(AVERAGE(C30:H30),0) -> 7.3109588 | K30: =IFERROR(MEDIAN(C30:H30),0) -> 7.2518215
B31: Proprietary Ratio | C31: =IFERROR(SUM(HistoriacalIFLS!C54:C55)/(HistoriacalIFLS!C76),0) -> 0.8440618 | D31: =IFERROR(SUM(HistoriacalIFLS!D54:D55)/(HistoriacalIFLS!D76),0) -> 0.71752945 | E31: =IFERROR(SUM(HistoriacalIFLS!E54:E55)/(HistoriacalIFLS!E76),0) -> 0.71903153 | F31: =IFERROR(SUM(HistoriacalIFLS!F54:F55)/(HistoriacalIFLS!F76),0) -> 0.71479264 | G31: =IFERROR(SUM(HistoriacalIFLS!G54:G55)/(HistoriacalIFLS!G76),0) -> 0.74632992 | H31: =IFERROR(SUM(HistoriacalIFLS!H54:H55)/(HistoriacalIFLS!H76),0) -> 0.7049425 | J31: =IFERROR(AVERAGE(C31:H31),0) -> 0.74111464 | K31: =IFERROR(MEDIAN(C31:H31),0) -> 0.71828049
B32: Captial Turnover Ratio | C32: =IFERROR(HistoriacalIFLS!C7/SUM(HistoriacalIFLS!C54:C55),0) -> 0.5756787 | D32: =IFERROR(HistoriacalIFLS!D7/SUM(HistoriacalIFLS!D54:D55),0) -> 0.55792202 | E32: =IFERROR(HistoriacalIFLS!E7/SUM(HistoriacalIFLS!E54:E55),0) -> 0.57377358 | F32: =IFERROR(HistoriacalIFLS!F7/SUM(HistoriacalIFLS!F54:F55),0) -> 0.6288669 | G32: =IFERROR(HistoriacalIFLS!G7/SUM(HistoriacalIFLS!G54:G55),0) -> 0.57642988 | H32: =IFERROR(HistoriacalIFLS!H7/SUM(HistoriacalIFLS!H54:H55),0) -> 0.54087937 | J32: =IFERROR(AVERAGE(C32:H32),0) -> 0.57559174 | K32: =IFERROR(MEDIAN(C32:H32),0) -> 0.57472614
B34: (In Days)
B35: Debtor Days | C35: =IFERROR(365/C27,0) -> 32.92067 | D35: =IFERROR(365/D27,0) -> 52.646541 | E35: =IFERROR(365/E27,0) -> 36.472255 | F35: =IFERROR(365/F27,0) -> 35.425612 | G35: =IFERROR(365/G27,0) -> 37.508569 | H35: =IFERROR(365/H27,0) -> 29.943851 | J35: =IFERROR(AVERAGE(C35:H35),0) -> 37.48625 | K35: =IFERROR(MEDIAN(C35:H35),0) -> 35.948934
B36: Payable Days | C36: =IFERROR(365/C28,0) -> 68.064574 | D36: =IFERROR(365/D28,0) -> 79.192381 | E36: =IFERROR(365/E28,0) -> 69.224138 | F36: =IFERROR(365/F28,0) -> 63.957846 | G36: =IFERROR(365/G28,0) -> 56.699475 | H36: =IFERROR(365/H28,0) -> 47.000539 | J36: =IFERROR(AVERAGE(C36:H36),0) -> 64.023159 | K36: =IFERROR(MEDIAN(C36:H36),0) -> 66.01121
B37: Inventory Days | C37: =IFERROR(365/C29,0) -> 44.663318 | D37: =IFERROR(365/D29,0) -> 40.825622 | E37: =IFERROR(365/E29,0) -> 54.330039 | F37: =IFERROR(365/F29,0) -> 42.04284 | G37: =IFERROR(365/G29,0) -> 32.69297 | H37: =IFERROR(365/H29,0) -> 35.93565 | J37: =IFERROR(AVERAGE(C37:H37),0) -> 41.748406 | K37: =IFERROR(MEDIAN(C37:H37),0) -> 41.434231
B38: Cash Conversion Cycle | C38: =IFERROR(SUM(C35,C37)-C36,0) -> 9.5194139 | D38: =IFERROR(SUM(D35,D37)-D36,0) -> 14.279782 | E38: =IFERROR(SUM(E35,E37)-E36,0) -> 21.578156 | F38: =IFERROR(SUM(F35,F37)-F36,0) -> 13.510606 | G38: =IFERROR(SUM(G35,G37)-G36,0) -> 13.502064 | H38: =IFERROR(SUM(H35,H37)-H36,0) -> 18.878962 | J38: =IFERROR(AVERAGE(C38:H38),0) -> 15.211497 | K38: =IFERROR(MEDIAN(C38:H38),0) -> 13.895194
B40: CFO/Sales | C40: =IFERROR(HistoriacalIFLS!C88/HistoriacalIFLS!C7,0) -> 0.078032444 | D40: =IFERROR(HistoriacalIFLS!D88/HistoriacalIFLS!D7,0) -> 0.090402261 | E40: =IFERROR(HistoriacalIFLS!E88/HistoriacalIFLS!E7,0) -> 0.053918181 | F40: =IFERROR(HistoriacalIFLS!F88/HistoriacalIFLS!F7,0) -> 0.098127106 | G40: =IFERROR(HistoriacalIFLS!G88/HistoriacalIFLS!G7,0) -> 0.1206156 | H40: =IFERROR(HistoriacalIFLS!H88/HistoriacalIFLS!H7,0) -> 0.063035902 | J40: =IFERROR(AVERAGE(C40:H40),0) -> 0.084021916 | K40: =IFERROR(MEDIAN(C40:H40),0) -> 0.084217352
B41: CFO/Total Assats | C41: =IFERROR(HistoriacalIFLS!C88/HistoriacalIFLS!C76,0) -> 0.03791662 | D41: =IFERROR(HistoriacalIFLS!D88/HistoriacalIFLS!D76,0) -> 0.036190329 | E41: =IFERROR(HistoriacalIFLS!E88/HistoriacalIFLS!E76,0) -> 0.022244555 | F41: =IFERROR(HistoriacalIFLS!F88/HistoriacalIFLS!F76,0) -> 0.04410906 | G41: =IFERROR(HistoriacalIFLS!G88/HistoriacalIFLS!G76,0) -> 0.05188966 | H41: =IFERROR(HistoriacalIFLS!H88/HistoriacalIFLS!H76,0) -> 0.024034887 | J41: =IFERROR(AVERAGE(C41:H41),0) -> 0.036064185 | K41: =IFERROR(MEDIAN(C41:H41),0) -> 0.037053474
B42: CFO/Total Debt | C42: =IFERROR(HistoriacalIFLS!C88/SUM(HistoriacalIFLS!C56,HistoriacalIFLS!C58),0) -> 1.3571169 | D42: =IFERROR(HistoriacalIFLS!D88/SUM(HistoriacalIFLS!D56,HistoriacalIFLS!D58),0) -> 0.23820454 | E42: =IFERROR(HistoriacalIFLS!E88/SUM(HistoriacalIFLS!E56,HistoriacalIFLS!E58),0) -> 0.14297494 | F42: =IFERROR(HistoriacalIFLS!F88/SUM(HistoriacalIFLS!F56,HistoriacalIFLS!F58),0) -> 0.27678679 | G42: =IFERROR(HistoriacalIFLS!G88/SUM(HistoriacalIFLS!G56,HistoriacalIFLS!G58),0) -> 0.37484238 | H42: =IFERROR(HistoriacalIFLS!H88/SUM(HistoriacalIFLS!H56,HistoriacalIFLS!H58),0) -> 0.12004214 | J42: =IFERROR(AVERAGE(C42:H42),0) -> 0.41832794 | K42: =IFERROR(MEDIAN(C42:H42),0) -> 0.25749567
B43: DE | C43: =IFERROR(SUM(HistoriacalIFLS!C56,HistoriacalIFLS!C58)/SUM(HistoriacalIFLS!C54:C55),0) -> 0.033100772 | D43: =IFERROR(SUM(HistoriacalIFLS!D56,HistoriacalIFLS!D58)/SUM(HistoriacalIFLS!D54:D55),0) -> 0.21173993 | E43: =IFERROR(SUM(HistoriacalIFLS!E56,HistoriacalIFLS!E58)/SUM(HistoriacalIFLS!E54:E55),0) -> 0.21637937 | F43: =IFERROR(SUM(HistoriacalIFLS!F56,HistoriacalIFLS!F58)/SUM(HistoriacalIFLS!F54:F55),0) -> 0.22294738 | G43: =IFERROR(SUM(HistoriacalIFLS!G56,HistoriacalIFLS!G58)/SUM(HistoriacalIFLS!G54:G55),0) -> 0.18548179 | H43: =IFERROR(SUM(HistoriacalIFLS!H56,HistoriacalIFLS!H58)/SUM(HistoriacalIFLS!H54:H55),0) -> 0.28402376 | J43: =IFERROR(AVERAGE(C43:H43),0) -> 0.19227883 | K43: =IFERROR(MEDIAN(C43:H43),0) -> 0.21405965
B44: Liquidity Analysis | J44: =IFERROR(AVERAGE(C44:H44),0) -> 0 | K44: =IFERROR(MEDIAN(C44:H44),0) -> 0
B45: Working Capital | C45: {=IFERROR(SUM(HistoriacalIFLS!C74-HistoriacalIFLS!C58:C60),0)} -> 177859 | D45: {=IFERROR(SUM(HistoriacalIFLS!D74-HistoriacalIFLS!D58:D60),0)} -> 199401 | E45: {=IFERROR(SUM(HistoriacalIFLS!E74-HistoriacalIFLS!E58:E60),0)} -> 208976 | F45: {=IFERROR(SUM(HistoriacalIFLS!F74-HistoriacalIFLS!F58:F60),0)} -> 251370 | G45: {=IFERROR(SUM(HistoriacalIFLS!G74-HistoriacalIFLS!G58:G60),0)} -> 262761 | H45: {=IFERROR(SUM(HistoriacalIFLS!H74-HistoriacalIFLS!H58:H60),0)} -> 254363 | J45: =IFERROR(AVERAGE(C45:H45),0) -> 225788.33 | K45: =IFERROR(MEDIAN(C45:H45),0) -> 230173
B46: Current Ratio | C46: =IFERROR(HistoriacalIFLS!C74/SUM(HistoriacalIFLS!C58:C60),0) -> 5.0479523 | D46: =IFERROR(HistoriacalIFLS!D74/SUM(HistoriacalIFLS!D58:D60),0) -> 4.3866935 | E46: =IFERROR(HistoriacalIFLS!E74/SUM(HistoriacalIFLS!E58:E60),0) -> 4.0554101 | F46: =IFERROR(HistoriacalIFLS!F74/SUM(HistoriacalIFLS!F58:F60),0) -> 3.4550501 | G46: =IFERROR(HistoriacalIFLS!G74/SUM(HistoriacalIFLS!G58:G60),0) -> 3.5888715 | H46: =IFERROR(HistoriacalIFLS!H74/SUM(HistoriacalIFLS!H58:H60),0) -> 2.9443538 | J46: =IFERROR(AVERAGE(C46:H46),0) -> 3.9130552 | K46: =IFERROR(MEDIAN(C46:H46),0) -> 3.8221408
B47: Quick Ratio | C47: =IFERROR((HistoriacalIFLS!C74-HistoriacalIFLS!C70)/SUM(HistoriacalIFLS!C58:C60),0) -> 4.5830616 | D47: =IFERROR((HistoriacalIFLS!D74-HistoriacalIFLS!D70)/SUM(HistoriacalIFLS!D58:D60),0) -> 4.0343335 | E47: =IFERROR((HistoriacalIFLS!E74-HistoriacalIFLS!E70)/SUM(HistoriacalIFLS!E58:E60),0) -> 3.5950307 | F47: =IFERROR((HistoriacalIFLS!F74-HistoriacalIFLS!F70)/SUM(HistoriacalIFLS!F58:F60),0) -> 3.1544279 | G47: =IFERROR((HistoriacalIFLS!G74-HistoriacalIFLS!G70)/SUM(HistoriacalIFLS!G58:G60),0) -> 3.3509144 | H47: =IFERROR((HistoriacalIFLS!H74-HistoriacalIFLS!H70)/SUM(HistoriacalIFLS!H58:H60),0) -> 2.7251255 | J47: =IFERROR(AVERAGE(C47:H47),0) -> 3.5738156 | K47: =IFERROR(MEDIAN(C47:H47),0) -> 3.4729725
J48: =IFERROR(AVERAGE(C48:H48),0) -> 0 | K48: =IFERROR(MEDIAN(C48:H48),0) -> 0
B49: Solvency Ratio | J49: =IFERROR(AVERAGE(C49:H49),0) -> 0 | K49: =IFERROR(MEDIAN(C49:H49),0) -> 0
B50: Financial Leverage Ratio | C50: =IFERROR(HistoriacalIFLS!C76/SUM(HistoriacalIFLS!C54:C55),0) -> 1.1847474 | D50: =IFERROR(HistoriacalIFLS!D76/SUM(HistoriacalIFLS!D54:D55),0) -> 1.393671 | E50: =IFERROR(HistoriacalIFLS!E76/SUM(HistoriacalIFLS!E54:E55),0) -> 1.3907596 | F50: =IFERROR(HistoriacalIFLS!F76/SUM(HistoriacalIFLS!F54:F55),0) -> 1.3990071 | G50: =IFERROR(HistoriacalIFLS!G76/SUM(HistoriacalIFLS!G54:G55),0) -> 1.33989 | H50: =IFERROR(HistoriacalIFLS!H76/SUM(HistoriacalIFLS!H54:H55),0) -> 1.4185554 | J50: =IFERROR(AVERAGE(C50:H50),0) -> 1.3544384 | K50: =IFERROR(MEDIAN(C50:H50),0) -> 1.3922153
B51: Debt Service Coverage Ratio | C51: =IFERROR(HistoriacalIFLS!C24/SUM(HistoriacalIFLS!C56,HistoriacalIFLS!C58),0) -> 4.1492537 | D51: =IFERROR(HistoriacalIFLS!D24/SUM(HistoriacalIFLS!D56,HistoriacalIFLS!D58),0) -> 0.66008671 | E51: =IFERROR(HistoriacalIFLS!E24/SUM(HistoriacalIFLS!E56,HistoriacalIFLS!E58),0) -> 0.58147419 | F51: =IFERROR(HistoriacalIFLS!F24/SUM(HistoriacalIFLS!F56,HistoriacalIFLS!F58),0) -> 0.6192873 | G51: =IFERROR(HistoriacalIFLS!G24/SUM(HistoriacalIFLS!G56,HistoriacalIFLS!G58),0) -> 0.83981912 | H51: =IFERROR(HistoriacalIFLS!H24/SUM(HistoriacalIFLS!H56,HistoriacalIFLS!H58),0) -> 0.43560706 | J51: =IFERROR(AVERAGE(C51:H51),0) -> 1.2142547 | K51: =IFERROR(MEDIAN(C51:H51),0) -> 0.639687
B52: Net Debt | C52: =IFERROR(SUM(HistoriacalIFLS!C56,HistoriacalIFLS!C58)-HistoriacalIFLS!C73,0) -> 1397 | D52: =IFERROR(SUM(HistoriacalIFLS!D56,HistoriacalIFLS!D58)-HistoriacalIFLS!D73,0) -> 18058 | E52: =IFERROR(SUM(HistoriacalIFLS!E56,HistoriacalIFLS!E58)-HistoriacalIFLS!E73,0) -> 19087 | F52: =IFERROR(SUM(HistoriacalIFLS!F56,HistoriacalIFLS!F58)-HistoriacalIFLS!F73,0) -> 23238 | G52: =IFERROR(SUM(HistoriacalIFLS!G56,HistoriacalIFLS!G58)-HistoriacalIFLS!G73,0) -> 19690 | H52: =IFERROR(SUM(HistoriacalIFLS!H56,HistoriacalIFLS!H58)-HistoriacalIFLS!H73,0) -> 34692 | J52: =IFERROR(AVERAGE(C52:H52),0) -> 19360.333 | K52: =IFERROR(MEDIAN(C52:H52),0) -> 19388.5
J53: =IFERROR(AVERAGE(C53:H53),0) -> 0 | K53: =IFERROR(MEDIAN(C53:H53),0) -> 0
B54: Ratio Involving Share Information | J54: =IFERROR(AVERAGE(C54:H54),0) -> 0 | K54: =IFERROR(MEDIAN(C54:H54),0) -> 0
B55: Dividend Payout Ratio | C55: =IFERROR(HistoriacalIFLS!C48,0) -> 0.059156311 | D55: =IFERROR(HistoriacalIFLS!D48,0) -> 0.052975027 | E55: =IFERROR(HistoriacalIFLS!E48,0) -> 0.35489446 | F55: =IFERROR(HistoriacalIFLS!F48,0) -> 0.045252807 | G55: =IFERROR(HistoriacalIFLS!G48,0) -> 0.038288632 | H55: =IFERROR(HistoriacalIFLS!H48,0) -> 0.5442187 | J55: =IFERROR(AVERAGE(C55:H55),0) -> 0.18246432 | K55: =IFERROR(MEDIAN(C55:H55),0) -> 0.056065669
B56: Divident Yield Ratio | C56: =IFERROR(HistoriacalIFLS!C47/HistoriacalIFLS!C113,0) -> 0.0050838841 | D56: =IFERROR(HistoriacalIFLS!D47/HistoriacalIFLS!D113,0) -> 0.0024145841 | E56: =IFERROR(HistoriacalIFLS!E47/HistoriacalIFLS!E113,0) -> 0.010136847 | F56: =IFERROR(HistoriacalIFLS!F47/HistoriacalIFLS!F113,0) -> 0.0027378508 | G56: =IFERROR(HistoriacalIFLS!G47/HistoriacalIFLS!G113,0) -> 0.0020828994 | H56: =IFERROR(HistoriacalIFLS!H47/HistoriacalIFLS!H113,0) -> 0.041944709 | J56: =IFERROR(AVERAGE(C56:H56),0) -> 0.010733463 | K56: =IFERROR(MEDIAN(C56:H56),0) -> 0.0039108674
B57: Rententation Ratio | C57: =1-C55 -> 0.94084369 | D57: =1-D55 -> 0.94702497 | E57: =1-E55 -> 0.64510554 | F57: =1-F55 -> 0.95474719 | G57: =1-G55 -> 0.96171137 | H57: =1-H55 -> 0.4557813 | J57: =IFERROR(AVERAGE(C57:H57),0) -> 0.81753568 | K57: =IFERROR(MEDIAN(C57:H57),0) -> 0.94393433
B58: P/E Ratio | C58: =IFERROR(HistoriacalIFLS!C113/HistoriacalIFLS!C44,0) -> 11.636046 | D58: =IFERROR(HistoriacalIFLS!D113/HistoriacalIFLS!D44,0) -> 21.939608 | E58: =IFERROR(HistoriacalIFLS!E113/HistoriacalIFLS!E44,0) -> 35.010338 | F58: =IFERROR(HistoriacalIFLS!F113/HistoriacalIFLS!F44,0) -> 16.528588 | G58: =IFERROR(HistoriacalIFLS!G113/HistoriacalIFLS!G44,0) -> 18.382372 | H58: =IFERROR(HistoriacalIFLS!H113/HistoriacalIFLS!H44,0) -> 12.974669 | J58: =IFERROR(AVERAGE(C58:H58),0) -> 19.411937 | K58: =IFERROR(MEDIAN(C58:H58),0) -> 17.45548
B59: PEG Ratio | C59: =IFERROR(C58/HistoriacalIFLS!$C$114,0)/$L$60 -> 0.74580188 | D59: =IFERROR(D58/HistoriacalIFLS!$C$114,0)/$L$60 -> 1.4061993 | E59: =IFERROR(E58/HistoriacalIFLS!$C$114,0)/$L$60 -> 2.243956 | F59: =IFERROR(F58/HistoriacalIFLS!$C$114,0)/$L$60 -> 1.0593849 | G59: =IFERROR(G58/HistoriacalIFLS!$C$114,0)/$L$60 -> 1.1782015 | H59: =IFERROR(H58/HistoriacalIFLS!$C$114,0)/$L$60 -> 0.83159965 | J59: =IFERROR(AVERAGE(C59:H59),0) -> 1.2441905 | K59: =IFERROR(MEDIAN(C59:H59),0) -> 1.1187932
B60: PEGY Ratio | C60: =IFERROR(C58/SUM(HistoriacalIFLS!$C$114,C56),0)/$L$60 -> 0.72226702 | D60: =IFERROR(D58/SUM(HistoriacalIFLS!$C$114,D56),0)/$L$60 -> 1.3847686 | E60: =IFERROR(E58/SUM(HistoriacalIFLS!$C$114,E56),0)/$L$60 -> 2.1070579 | F60: =IFERROR(F58/SUM(HistoriacalIFLS!$C$114,F56),0)/$L$60 -> 1.0411154 | G60: =IFERROR(G58/SUM(HistoriacalIFLS!$C$114,G56),0)/$L$60 -> 1.1626796 | H60: =IFERROR(H58/SUM(HistoriacalIFLS!$C$114,H56),0)/$L$60 -> 0.65540108 | J60: =IFERROR(AVERAGE(C60:H60),0) -> 1.1788816 | K60: =IFERROR(MEDIAN(C60:H60),0) -> 1.1018975 | L60: 100
J61: =IFERROR(AVERAGE(C61:H61),0) -> 0 | K61: =IFERROR(MEDIAN(C61:H61),0) -> 0
B62: Book value | C62: {=IFERROR(SUM(HistoriacalIFLS!C54:C55/HistoriacalIFLS!C42),0)} -> 171.5847 | D62: {=IFERROR(SUM(HistoriacalIFLS!D54:D55/HistoriacalIFLS!D42),0)} -> 191.43534 | E62: {=IFERROR(SUM(HistoriacalIFLS!E54:E55/HistoriacalIFLS!E42),0)} -> 208.58161 | F62: {=IFERROR(SUM(HistoriacalIFLS!F54:F55/HistoriacalIFLS!F42),0)} -> 230.31373 | G62: {=IFERROR(SUM(HistoriacalIFLS!G54:G55/HistoriacalIFLS!G42),0)} -> 256.36912 | H62: {=IFERROR(SUM(HistoriacalIFLS!H54:H55/HistoriacalIFLS!H42),0)} -> 276.40377 | J62: =IFERROR(AVERAGE(C62:H62),0) -> 222.44805 | K62: =IFERROR(MEDIAN(C62:H62),0) -> 219.44767
B63: Price-to-Book Ratio | C63: =IFERROR(HistoriacalIFLS!C113/'Ratio Analysis'!C62,0) -> 1.1463726 | D63: =IFERROR(HistoriacalIFLS!D113/'Ratio Analysis'!D62,0) -> 2.1633936 | E63: =IFERROR(HistoriacalIFLS!E113/'Ratio Analysis'!E62,0) -> 2.8377382 | F63: =IFERROR(HistoriacalIFLS!F113/'Ratio Analysis'!F62,0) -> 1.5858803 | G63: =IFERROR(HistoriacalIFLS!G113/'Ratio Analysis'!G62,0) -> 1.8726905 | H63: =IFERROR(HistoriacalIFLS!H113/'Ratio Analysis'!H62,0) -> 0.94879314 | J63: =IFERROR(AVERAGE(C63:H63),0) -> 1.7591447 | K63: =IFERROR(MEDIAN(C63:H63),0) -> 1.7292854
B65: Enterpise Multiple
B66: EV/EBITDA | C66: =IFERROR(HistoriacalIFLS!C116/HistoriacalIFLS!C24,0) -> 8.5607401 | D66: =IFERROR(HistoriacalIFLS!D116/HistoriacalIFLS!D24,0) -> 16.951829 | E66: =IFERROR(HistoriacalIFLS!E116/HistoriacalIFLS!E24,0) -> 24.069766 | F66: =IFERROR(HistoriacalIFLS!F116/HistoriacalIFLS!F24,0) -> 13.003937 | G66: =IFERROR(HistoriacalIFLS!G116/HistoriacalIFLS!G24,0) -> 13.046965 | H66: =IFERROR(HistoriacalIFLS!H116/HistoriacalIFLS!H24,0) -> 9.7736614 | J66: =IFERROR(AVERAGE(C66:H66),0) -> 14.234483 | K66: =IFERROR(MEDIAN(C66:H66),0) -> 13.025451
B67: EV/Sales | C67: =IFERROR(HistoriacalIFLS!C116/HistoriacalIFLS!C7,0) -> 2.0423928 | D67: =IFERROR(HistoriacalIFLS!D116/HistoriacalIFLS!D7,0) -> 4.2466533 | E67: =IFERROR(HistoriacalIFLS!E116/HistoriacalIFLS!E7,0) -> 5.2781 | F67: =IFERROR(HistoriacalIFLS!F116/HistoriacalIFLS!F7,0) -> 2.8550298 | G67: =IFERROR(HistoriacalIFLS!G116/HistoriacalIFLS!G7,0) -> 3.525738 | H67: =IFERROR(HistoriacalIFLS!H116/HistoriacalIFLS!H7,0) -> 2.2356635 | J67: =IFERROR(AVERAGE(C67:H67),0) -> 3.3639296 | K67: =IFERROR(MEDIAN(C67:H67),0) -> 3.1903839
B68: EV/EBIT | C68: =IFERROR((HistoriacalIFLS!C116)/(HistoriacalIFLS!C24-HistoriacalIFLS!C27),0) -> 8.6464613 | D68: =IFERROR((HistoriacalIFLS!D116)/(HistoriacalIFLS!D24-HistoriacalIFLS!D27),0) -> 18.012449 | E68: =IFERROR((HistoriacalIFLS!E116)/(HistoriacalIFLS!E24-HistoriacalIFLS!E27),0) -> 26.419711 | F68: =IFERROR((HistoriacalIFLS!F116)/(HistoriacalIFLS!F24-HistoriacalIFLS!F27),0) -> 14.158328 | G68: =IFERROR((HistoriacalIFLS!G116)/(HistoriacalIFLS!G24-HistoriacalIFLS!G27),0) -> 14.128056 | H68: =IFERROR((HistoriacalIFLS!H116)/(HistoriacalIFLS!H24-HistoriacalIFLS!H27),0) -> 11.291217 | J68: =IFERROR(AVERAGE(C68:H68),0) -> 15.442704 | K68: =IFERROR(MEDIAN(C68:H68),0) -> 14.143192

Sheet Commen-Size
B2: Common Size- Balance sheet | J2: Trend
D3: =HistoriacalIFLS!C3 -> 43921 | E3: =HistoriacalIFLS!D3 -> 44286 | F3: =HistoriacalIFLS!E3 -> 44651 | G3: =HistoriacalIFLS!F3 -> 45016 | H3: =HistoriacalIFLS!G3 -> 45382 | I3: =HistoriacalIFLS!H3 -> 45747
B5: =HistoriacalIFLS!B7 -> Sales | D5: =IFERROR(HistoriacalIFLS!C7/HistoriacalIFLS!C$11,0) -> 0.90697674 | E5: =IFERROR(HistoriacalIFLS!D7/HistoriacalIFLS!D$11,0) -> 0.88209279 | F5: =IFERROR(HistoriacalIFLS!E7/HistoriacalIFLS!E$11,0) -> 0.91019734 | G5: =IFERROR(HistoriacalIFLS!F7/HistoriacalIFLS!F$11,0) -> 0.90245285 | H5: =IFERROR(HistoriacalIFLS!G7/HistoriacalIFLS!G$11,0) -> 0.88177601 | I5: =IFERROR(HistoriacalIFLS!H7/HistoriacalIFLS!H$11,0) -> 0.88722561
B6: =HistoriacalIFLS!B9 -> Other Income | D6: =IFERROR(HistoriacalIFLS!C9/HistoriacalIFLS!C$11,0) -> 0.093023256 | E6: =IFERROR(HistoriacalIFLS!D9/HistoriacalIFLS!D$11,0) -> 0.11790721 | F6: =IFERROR(HistoriacalIFLS!E9/HistoriacalIFLS!E$11,0) -> 0.089802657 | G6: =IFERROR(HistoriacalIFLS!F9/HistoriacalIFLS!F$11,0) -> 0.09754715 | H6: =IFERROR(HistoriacalIFLS!G9/HistoriacalIFLS!G$11,0) -> 0.11822399 | I6: =IFERROR(HistoriacalIFLS!H9/HistoriacalIFLS!H$11,0) -> 0.11277439
B7: =HistoriacalIFLS!B11 -> Total Revenue | D7: =IFERROR(HistoriacalIFLS!C11/HistoriacalIFLS!C11,0) -> 1 | E7: =IFERROR(HistoriacalIFLS!D11/HistoriacalIFLS!D11,0) -> 1 | F7: =IFERROR(HistoriacalIFLS!E11/HistoriacalIFLS!E11,0) -> 1 | G7: =IFERROR(HistoriacalIFLS!F11/HistoriacalIFLS!F11,0) -> 1 | H7: =IFERROR(HistoriacalIFLS!G11/HistoriacalIFLS!G11,0) -> 1 | I7: =IFERROR(HistoriacalIFLS!H11/HistoriacalIFLS!H11,0) -> 1
B8: =HistoriacalIFLS!B13 -> COGS | D8: =IFERROR(HistoriacalIFLS!C13/HistoriacalIFLS!C11,0) -> 0.48043664 | E8: =IFERROR(HistoriacalIFLS!D13/HistoriacalIFLS!D11,0) -> 0.51232007 | F8: =IFERROR(HistoriacalIFLS!E13/HistoriacalIFLS!E11,0) -> 0.53642582 | G8: =IFERROR(HistoriacalIFLS!F13/HistoriacalIFLS!F11,0) -> 0.53243842 | H8: =IFERROR(HistoriacalIFLS!G13/HistoriacalIFLS!G11,0) -> 0.48760147 | I8: =IFERROR(HistoriacalIFLS!H13/HistoriacalIFLS!H11,0) -> 0.49949079
B9: OtherExp | D9: =IFERROR(HistoriacalIFLS!C22/HistoriacalIFLS!C11,0) -> 0.22578073 | E9: =IFERROR(HistoriacalIFLS!D22/HistoriacalIFLS!D11,0) -> 0.18955655 | F9: =IFERROR(HistoriacalIFLS!E22/HistoriacalIFLS!E11,0) -> 0.18624106 | G9: =IFERROR(HistoriacalIFLS!F22/HistoriacalIFLS!F11,0) -> 0.19747758 | H9: =IFERROR(HistoriacalIFLS!G22/HistoriacalIFLS!G11,0) -> 0.19683437 | I9: =IFERROR(HistoriacalIFLS!H22/HistoriacalIFLS!H11,0) -> 0.21821127
B10: =HistoriacalIFLS!B19 -> Employee Benefits Expenses | D10: =IFERROR(HistoriacalIFLS!C19/HistoriacalIFLS!C11,0) -> 0.077399146 | E10: =IFERROR(HistoriacalIFLS!D19/HistoriacalIFLS!D11,0) -> 0.077147687 | F10: =IFERROR(HistoriacalIFLS!E19/HistoriacalIFLS!E11,0) -> 0.077741961 | G10: =IFERROR(HistoriacalIFLS!F19/HistoriacalIFLS!F11,0) -> 0.071949397 | H10: =IFERROR(HistoriacalIFLS!G19/HistoriacalIFLS!G11,0) -> 0.077277998 | I10: =IFERROR(HistoriacalIFLS!H19/HistoriacalIFLS!H11,0) -> 0.079350667
B11: =HistoriacalIFLS!B27 -> Interest | D11: =IFERROR(HistoriacalIFLS!C27/HistoriacalIFLS!C$11,0) -> 0.0021452302 | E11: =IFERROR(HistoriacalIFLS!D27/HistoriacalIFLS!D$11,0) -> 0.013011629 | F11: =IFERROR(HistoriacalIFLS!E27/HistoriacalIFLS!E$11,0) -> 0.017752968 | G11: =IFERROR(HistoriacalIFLS!F27/HistoriacalIFLS!F$11,0) -> 0.016154797 | H11: =IFERROR(HistoriacalIFLS!G27/HistoriacalIFLS!G$11,0) -> 0.018233857 | I11: =IFERROR(HistoriacalIFLS!H27/HistoriacalIFLS!H$11,0) -> 0.027276408
B12: =HistoriacalIFLS!B30 -> D&A impairment expense | D12: =IFERROR(HistoriacalIFLS!C30/HistoriacalIFLS!C11,0) -> 0.018149027 | E12: =IFERROR(HistoriacalIFLS!D30/HistoriacalIFLS!D11,0) -> 0.015607124 | F12: =IFERROR(HistoriacalIFLS!E30/HistoriacalIFLS!E11,0) -> 0.015567262 | G12: =IFERROR(HistoriacalIFLS!F30/HistoriacalIFLS!F11,0) -> 0.014827888 | H12: =IFERROR(HistoriacalIFLS!G30/HistoriacalIFLS!G11,0) -> 0.022576427 | I12: =IFERROR(HistoriacalIFLS!H30/HistoriacalIFLS!H11,0) -> 0.016086087
B13: =HistoriacalIFLS!B36 -> Tax | D13: =IFERROR(HistoriacalIFLS!C36/HistoriacalIFLS!C11,0) -> 0.04087328 | E13: =IFERROR(HistoriacalIFLS!D36/HistoriacalIFLS!D11,0) -> 0.036456466 | F13: =IFERROR(HistoriacalIFLS!E36/HistoriacalIFLS!E11,0) -> 0.037691642 | G13: =IFERROR(HistoriacalIFLS!F36/HistoriacalIFLS!F11,0) -> 0.029462537 | H13: =IFERROR(HistoriacalIFLS!G36/HistoriacalIFLS!G11,0) -> 0.041636853 | I13: =IFERROR(HistoriacalIFLS!H36/HistoriacalIFLS!H11,0) -> 0.039632388
B14: =HistoriacalIFLS!B24 -> EBITDA | D14: =IFERROR(HistoriacalIFLS!C24/HistoriacalIFLS!C11,0) -> 0.21638348 | E14: =IFERROR(HistoriacalIFLS!D24/HistoriacalIFLS!D11,0) -> 0.2209757 | F14: =IFERROR(HistoriacalIFLS!E24/HistoriacalIFLS!E11,0) -> 0.19959116 | G14: =IFERROR(HistoriacalIFLS!F24/HistoriacalIFLS!F11,0) -> 0.1981346 | H14: =IFERROR(HistoriacalIFLS!G24/HistoriacalIFLS!G11,0) -> 0.23828617 | I14: =IFERROR(HistoriacalIFLS!H24/HistoriacalIFLS!H11,0) -> 0.20294728
B15: =HistoriacalIFLS!B33 -> Earnings Before Tax | D15: =IFERROR(HistoriacalIFLS!C33/HistoriacalIFLS!C11,0) -> 0.19608923 | E15: =IFERROR(HistoriacalIFLS!D33/HistoriacalIFLS!D11,0) -> 0.19235695 | F15: =IFERROR(HistoriacalIFLS!E33/HistoriacalIFLS!E11,0) -> 0.16627093 | G15: =IFERROR(HistoriacalIFLS!F33/HistoriacalIFLS!F11,0) -> 0.16715191 | H15: =IFERROR(HistoriacalIFLS!G33/HistoriacalIFLS!G11,0) -> 0.19747588 | I15: =IFERROR(HistoriacalIFLS!H33/HistoriacalIFLS!H11,0) -> 0.15958478
B16: =HistoriacalIFLS!B39 -> Net Profit | D16: =IFERROR(HistoriacalIFLS!C39/HistoriacalIFLS!C11,0) -> 0.15521595 | E16: =IFERROR(HistoriacalIFLS!D39/HistoriacalIFLS!D11,0) -> 0.15590048 | F16: =IFERROR(HistoriacalIFLS!E39/HistoriacalIFLS!E11,0) -> 0.12857929 | G16: =IFERROR(HistoriacalIFLS!F39/HistoriacalIFLS!F11,0) -> 0.13768937 | H16: =IFERROR(HistoriacalIFLS!G39/HistoriacalIFLS!G11,0) -> 0.15583903 | I16: =IFERROR(HistoriacalIFLS!H39/HistoriacalIFLS!H11,0) -> 0.11995239
B26: Common Size-Balance Sheet | J26: Trend
D27: =HistoriacalIFLS!C3 -> 43921 | E27: =HistoriacalIFLS!D3 -> 44286 | F27: =HistoriacalIFLS!E3 -> 44651 | G27: =HistoriacalIFLS!F3 -> 45016 | H27: =HistoriacalIFLS!G3 -> 45382 | I27: =HistoriacalIFLS!H3 -> 45747
B29: =IFERROR(HistoriacalIFLS!B54,0) -> Equity Share Capital | D29: =IFERROR(HistoriacalIFLS!C54/HistoriacalIFLS!C$61,0) -> 0.049196001 | E29: =IFERROR(HistoriacalIFLS!D54/HistoriacalIFLS!D$61,0) -> 0.037484501 | F29: =IFERROR(HistoriacalIFLS!E54/HistoriacalIFLS!E$61,0) -> 0.03447514 | G29: =IFERROR(HistoriacalIFLS!F54/HistoriacalIFLS!F$61,0) -> 0.031038045 | H29: =IFERROR(HistoriacalIFLS!G54/HistoriacalIFLS!G$61,0) -> 0.029113825 | I29: =IFERROR(HistoriacalIFLS!H54/HistoriacalIFLS!H$61,0) -> 0.025506088
B30: =IFERROR(HistoriacalIFLS!B55,0) -> Reserves | D30: =IFERROR(HistoriacalIFLS!C55/HistoriacalIFLS!C$61,0) -> 0.7948658 | E30: =IFERROR(HistoriacalIFLS!D55/HistoriacalIFLS!D$61,0) -> 0.68004495 | F30: =IFERROR(HistoriacalIFLS!E55/HistoriacalIFLS!E$61,0) -> 0.68455639 | G30: =IFERROR(HistoriacalIFLS!F55/HistoriacalIFLS!F$61,0) -> 0.6837546 | H30: =IFERROR(HistoriacalIFLS!G55/HistoriacalIFLS!G$61,0) -> 0.7172161 | I30: =IFERROR(HistoriacalIFLS!H55/HistoriacalIFLS!H$61,0) -> 0.67943641
B31: =IFERROR(HistoriacalIFLS!B56,0) -> Borrowings | D31: =IFERROR(HistoriacalIFLS!C56/HistoriacalIFLS!C$61,0) -> 0.012123554 | E31: =IFERROR(HistoriacalIFLS!D56/HistoriacalIFLS!D$61,0) -> 0.13464817 | F31: =IFERROR(HistoriacalIFLS!E56/HistoriacalIFLS!E$61,0) -> 0.13518503 | G31: =IFERROR(HistoriacalIFLS!F56/HistoriacalIFLS!F$61,0) -> 0.096155697 | H31: =IFERROR(HistoriacalIFLS!G56/HistoriacalIFLS!G$61,0) -> 0.07202918 | I31: =IFERROR(HistoriacalIFLS!H56/HistoriacalIFLS!H$61,0) -> 0.11364104
B32: =IFERROR(HistoriacalIFLS!B57,0) -> Other Non- Current Liabilities | D32: =IFERROR(HistoriacalIFLS!C57/HistoriacalIFLS!C$61,0) -> 0.015917251 | E32: =IFERROR(HistoriacalIFLS!D57/HistoriacalIFLS!D$61,0) -> 0.020745505 | F32: =IFERROR(HistoriacalIFLS!E57/HistoriacalIFLS!E$61,0) -> 0.012394515 | G32: =IFERROR(HistoriacalIFLS!F57/HistoriacalIFLS!F$61,0) -> 0.016818424 | H32: =IFERROR(HistoriacalIFLS!G57/HistoriacalIFLS!G$61,0) -> 0.019706153 | I32: =IFERROR(HistoriacalIFLS!H57/HistoriacalIFLS!H$61,0) -> 0.010182397
B33: =IFERROR(HistoriacalIFLS!B58,0) -> Current Borrowings | D33: =IFERROR(HistoriacalIFLS!C58/HistoriacalIFLS!C$61,0) -> 0.015815543 | E33: =IFERROR(HistoriacalIFLS!D58/HistoriacalIFLS!D$61,0) -> 0.017281463 | F33: =IFERROR(HistoriacalIFLS!E58/HistoriacalIFLS!E$61,0) -> 0.020398563 | G33: =IFERROR(HistoriacalIFLS!F58/HistoriacalIFLS!F$61,0) -> 0.063205447 | H33: =IFERROR(HistoriacalIFLS!G58/HistoriacalIFLS!G$61,0) -> 0.06640143 | I33: =IFERROR(HistoriacalIFLS!H58/HistoriacalIFLS!H$61,0) -> 0.086579379
B34: =IFERROR(HistoriacalIFLS!B59,0) -> Payables | D34: =IFERROR(HistoriacalIFLS!C59/HistoriacalIFLS!C$61,0) -> 0.090611365 | E34: =IFERROR(HistoriacalIFLS!D59/HistoriacalIFLS!D$61,0) -> 0.086856789 | F34: =IFERROR(HistoriacalIFLS!E59/HistoriacalIFLS!E$61,0) -> 0.078244384 | G34: =IFERROR(HistoriacalIFLS!F59/HistoriacalIFLS!F$61,0) -> 0.078766178 | H34: =IFERROR(HistoriacalIFLS!G59/HistoriacalIFLS!G$61,0) -> 0.066828778 | I34: =IFERROR(HistoriacalIFLS!H59/HistoriacalIFLS!H$61,0) -> 0.049098033
B35: =IFERROR(HistoriacalIFLS!B60,0) -> Other current Liabilities | D35: =IFERROR(HistoriacalIFLS!C60/HistoriacalIFLS!C$61,0) -> 0.02147049 | E35: =IFERROR(HistoriacalIFLS!D60/HistoriacalIFLS!D$61,0) -> 0.022938624 | F35: =IFERROR(HistoriacalIFLS!E60/HistoriacalIFLS!E$61,0) -> 0.03474598 | G35: =IFERROR(HistoriacalIFLS!F60/HistoriacalIFLS!F$61,0) -> 0.030261613 | H35: =IFERROR(HistoriacalIFLS!G60/HistoriacalIFLS!G$61,0) -> 0.028704534 | I35: =IFERROR(HistoriacalIFLS!H60/HistoriacalIFLS!H$61,0) -> 0.035556657
B36: =IFERROR(HistoriacalIFLS!B61,0) -> Total Liabilities | D36: =IFERROR(HistoriacalIFLS!C61/HistoriacalIFLS!C$61,0) -> 1 | E36: =IFERROR(HistoriacalIFLS!D61/HistoriacalIFLS!D$61,0) -> 1 | F36: =IFERROR(HistoriacalIFLS!E61/HistoriacalIFLS!E$61,0) -> 1 | G36: =IFERROR(HistoriacalIFLS!F61/HistoriacalIFLS!F$61,0) -> 1 | H36: =IFERROR(HistoriacalIFLS!G61/HistoriacalIFLS!G$61,0) -> 1 | I36: =IFERROR(HistoriacalIFLS!H61/HistoriacalIFLS!H$61,0) -> 1
B38: =IFERROR(HistoriacalIFLS!B63,0) -> Fixed Assets Net Block | D38: =IFERROR(HistoriacalIFLS!C63/HistoriacalIFLS!C$76,0) -> 0.069832487 | E38: =IFERROR(HistoriacalIFLS!D63/HistoriacalIFLS!D$76,0) -> 0.04783013 | F38: =IFERROR(HistoriacalIFLS!E63/HistoriacalIFLS!E$76,0) -> 0.063412305 | G38: =IFERROR(HistoriacalIFLS!F63/HistoriacalIFLS!F$76,0) -> 0.062839689 | H38: =IFERROR(HistoriacalIFLS!G63/HistoriacalIFLS!G$76,0) -> 0.058528599 | I38: =IFERROR(HistoriacalIFLS!H63/HistoriacalIFLS!H$76,0) -> 0.05064833
B39: =IFERROR(HistoriacalIFLS!B64,0) -> Capital Work in Progress | D39: =IFERROR(HistoriacalIFLS!C64/HistoriacalIFLS!C$76,0) -> 0.0058787034 | E39: =IFERROR(HistoriacalIFLS!D64/HistoriacalIFLS!D$76,0) -> 0.0076255425 | F39: =IFERROR(HistoriacalIFLS!E64/HistoriacalIFLS!E$76,0) -> 0.0085528567 | G39: =IFERROR(HistoriacalIFLS!F64/HistoriacalIFLS!F$76,0) -> 0.0019507062 | H39: =IFERROR(HistoriacalIFLS!G64/HistoriacalIFLS!G$76,0) -> 0.0016913345 | I39: =IFERROR(HistoriacalIFLS!H64/HistoriacalIFLS!H$76,0) -> 0.00099661993
B40: =IFERROR(HistoriacalIFLS!B65,0) -> Investments | D40: =IFERROR(HistoriacalIFLS!C65/HistoriacalIFLS!C$76,0) -> 0.24979404 | E40: =IFERROR(HistoriacalIFLS!D65/HistoriacalIFLS!D$76,0) -> 0.23811221 | F40: =IFERROR(HistoriacalIFLS!E65/HistoriacalIFLS!E$76,0) -> 0.23367117 | G40: =IFERROR(HistoriacalIFLS!F65/HistoriacalIFLS!F$76,0) -> 0.21441726 | H40: =IFERROR(HistoriacalIFLS!G65/HistoriacalIFLS!G$76,0) -> 0.19968581 | I40: =IFERROR(HistoriacalIFLS!H65/HistoriacalIFLS!H$76,0) -> 0.31081359
B41: =IFERROR(HistoriacalIFLS!B66,0) -> Other Non-current Assets | D41: =IFERROR(HistoriacalIFLS!C66/HistoriacalIFLS!C$76,0) -> 0.028874808 | E41: =IFERROR(HistoriacalIFLS!D66/HistoriacalIFLS!D$76,0) -> 0.14898481 | F41: =IFERROR(HistoriacalIFLS!E66/HistoriacalIFLS!E$76,0) -> 0.15341687 | G41: =IFERROR(HistoriacalIFLS!F66/HistoriacalIFLS!F$76,0) -> 0.12571788 | H41: =IFERROR(HistoriacalIFLS!G66/HistoriacalIFLS!G$76,0) -> 0.15893127 | I41: =IFERROR(HistoriacalIFLS!H66/HistoriacalIFLS!H$76,0) -> 0.13336778
B42: =IFERROR(HistoriacalIFLS!B67,0) -> Total Non Current Assests | D42: =IFERROR(HistoriacalIFLS!C67/HistoriacalIFLS!C$76,0) -> 0.35438004 | E42: =IFERROR(HistoriacalIFLS!D67/HistoriacalIFLS!D$76,0) -> 0.4425527 | F42: =IFERROR(HistoriacalIFLS!E67/HistoriacalIFLS!E$76,0) -> 0.4590532 | G42: =IFERROR(HistoriacalIFLS!F67/HistoriacalIFLS!F$76,0) -> 0.40492553 | H42: =IFERROR(HistoriacalIFLS!G67/HistoriacalIFLS!G$76,0) -> 0.41883701 | I42: =IFERROR(HistoriacalIFLS!H67/HistoriacalIFLS!H$76,0) -> 0.49582632
B44: =IFERROR(HistoriacalIFLS!B69,0) -> Receivables | D44: =IFERROR(HistoriacalIFLS!C69/HistoriacalIFLS!C$76,0) -> 0.043825836 | E44: =IFERROR(HistoriacalIFLS!D69/HistoriacalIFLS!D$76,0) -> 0.057741785 | F44: =IFERROR(HistoriacalIFLS!E69/HistoriacalIFLS!E$76,0) -> 0.041224769 | G44: =IFERROR(HistoriacalIFLS!F69/HistoriacalIFLS!F$76,0) -> 0.0436278 | H44: =IFERROR(HistoriacalIFLS!G69/HistoriacalIFLS!G$76,0) -> 0.044209437 | I44: =IFERROR(HistoriacalIFLS!H69/HistoriacalIFLS!H$76,0) -> 0.031280156
B45: =IFERROR(HistoriacalIFLS!B70,0) -> Inventory | D45: =IFERROR(HistoriacalIFLS!C70/HistoriacalIFLS!C$76,0) -> 0.059458305 | E45: =IFERROR(HistoriacalIFLS!D70/HistoriacalIFLS!D$76,0) -> 0.044776813 | F45: =IFERROR(HistoriacalIFLS!E70/HistoriacalIFLS!E$76,0) -> 0.061409511 | G45: =IFERROR(HistoriacalIFLS!F70/HistoriacalIFLS!F$76,0) -> 0.051777132 | H45: =IFERROR(HistoriacalIFLS!G70/HistoriacalIFLS!G$76,0) -> 0.038533535 | I45: =IFERROR(HistoriacalIFLS!H70/HistoriacalIFLS!H$76,0) -> 0.037539351
B46: =IFERROR(HistoriacalIFLS!B71,0) -> Other current Assests | D46: =IFERROR(HistoriacalIFLS!C71/HistoriacalIFLS!C$76,0) -> 0.048158583 | E46: =IFERROR(HistoriacalIFLS!D71/HistoriacalIFLS!D$76,0) -> 0.060934594 | F46: =IFERROR(HistoriacalIFLS!E71/HistoriacalIFLS!E$76,0) -> 0.026962881 | G46: =IFERROR(HistoriacalIFLS!F71/HistoriacalIFLS!F$76,0) -> 0.058765023 | H46: =IFERROR(HistoriacalIFLS!G71/HistoriacalIFLS!G$76,0) -> 0.037119074 | I46: =IFERROR(HistoriacalIFLS!H71/HistoriacalIFLS!H$76,0) -> 0.045654684
B47: =IFERROR(HistoriacalIFLS!B72,0) -> Short term Investment | D47: =IFERROR(HistoriacalIFLS!C72/HistoriacalIFLS!C$76,0) -> 0.4804467 | E47: =IFERROR(HistoriacalIFLS!D72/HistoriacalIFLS!D$76,0) -> 0.38200558 | F47: =IFERROR(HistoriacalIFLS!E72/HistoriacalIFLS!E$76,0) -> 0.39180636 | G47: =IFERROR(HistoriacalIFLS!F72/HistoriacalIFLS!F$76,0) -> 0.43065689 | H47: =IFERROR(HistoriacalIFLS!G72/HistoriacalIFLS!G$76,0) -> 0.44138413 | I47: =IFERROR(HistoriacalIFLS!H72/HistoriacalIFLS!H$76,0) -> 0.37241419
B48: =IFERROR(HistoriacalIFLS!B73,0) -> Cash & Bank | D48: =IFERROR(HistoriacalIFLS!C73/HistoriacalIFLS!C$76,0) -> 0.013730536 | E48: =IFERROR(HistoriacalIFLS!D73/HistoriacalIFLS!D$76,0) -> 0.011988531 | F48: =IFERROR(HistoriacalIFLS!E73/HistoriacalIFLS!E$76,0) -> 0.019543277 | G48: =IFERROR(HistoriacalIFLS!F73/HistoriacalIFLS!F$76,0) -> 0.010247624 | H48: =IFERROR(HistoriacalIFLS!G73/HistoriacalIFLS!G$76,0) -> 0.019916818 | I48: =IFERROR(HistoriacalIFLS!H73/HistoriacalIFLS!H$76,0) -> 0.017285292
B49: =IFERROR(HistoriacalIFLS!B74,0) -> Total Current Assests | D49: =IFERROR(HistoriacalIFLS!C74/HistoriacalIFLS!C$76,0) -> 0.64561996 | E49: =IFERROR(HistoriacalIFLS!D74/HistoriacalIFLS!D$76,0) -> 0.5574473 | F49: =IFERROR(HistoriacalIFLS!E74/HistoriacalIFLS!E$76,0) -> 0.5409468 | G49: =IFERROR(HistoriacalIFLS!F74/HistoriacalIFLS!F$76,0) -> 0.59507447 | H49: =IFERROR(HistoriacalIFLS!G74/HistoriacalIFLS!G$76,0) -> 0.58116299 | I49: =IFERROR(HistoriacalIFLS!H74/HistoriacalIFLS!H$76,0) -> 0.50417368
B51: =IFERROR(HistoriacalIFLS!B76,0) -> Total t Assests | D51: =IFERROR(HistoriacalIFLS!C76/HistoriacalIFLS!C$76,0) -> 1 | E51: =IFERROR(HistoriacalIFLS!D76/HistoriacalIFLS!D$76,0) -> 1 | F51: =IFERROR(HistoriacalIFLS!E76/HistoriacalIFLS!E$76,0) -> 1 | G51: =IFERROR(HistoriacalIFLS!F76/HistoriacalIFLS!F$76,0) -> 1 | H51: =IFERROR(HistoriacalIFLS!G76/HistoriacalIFLS!G$76,0) -> 1 | I51: =IFERROR(HistoriacalIFLS!H76/HistoriacalIFLS!H$76,0) -> 1
B59: Common Size-Balance Sheet | J59: Trend
D60: =HistoriacalIFLS!C36 -> 2153 | E60: =HistoriacalIFLS!D36 -> 2135 | F60: =HistoriacalIFLS!E36 -> 2397 | G60: =HistoriacalIFLS!F36 -> 2287 | H60: =HistoriacalIFLS!G36 -> 3375 | I60: =HistoriacalIFLS!H36 -> 3230
B62: =IFERROR(HistoriacalIFLS!B87,0) -> Direct taxes paid, net | D62: =IFERROR(HistoriacalIFLS!C87/HistoriacalIFLS!C$61,0) -> -0.018744724 | E62: =IFERROR(HistoriacalIFLS!D87/HistoriacalIFLS!D$61,0) -> -0.01315871 | F62: =IFERROR(HistoriacalIFLS!E87/HistoriacalIFLS!E$61,0) -> -0.014881971 | G62: =IFERROR(HistoriacalIFLS!F87/HistoriacalIFLS!F$61,0) -> -0.01612541 | H62: =IFERROR(HistoriacalIFLS!G87/HistoriacalIFLS!G$61,0) -> -0.017376806 | I62: =IFERROR(HistoriacalIFLS!H87/HistoriacalIFLS!H$61,0) -> -0.01576136
B63: =IFERROR(HistoriacalIFLS!B88,0) -> Net cash generated from operating activities | D63: =IFERROR(HistoriacalIFLS!C88/HistoriacalIFLS!C$61,0) -> 0.03791662 | E63: =IFERROR(HistoriacalIFLS!D88/HistoriacalIFLS!D$61,0) -> 0.036190329 | F63: =IFERROR(HistoriacalIFLS!E88/HistoriacalIFLS!E$61,0) -> 0.022244555 | G63: =IFERROR(HistoriacalIFLS!F88/HistoriacalIFLS!F$61,0) -> 0.04410906 | H63: =IFERROR(HistoriacalIFLS!G88/HistoriacalIFLS!G$61,0) -> 0.05188966 | I63: =IFERROR(HistoriacalIFLS!H88/HistoriacalIFLS!H$61,0) -> 0.024034887
B64: =IFERROR(HistoriacalIFLS!B89,0) -> B. Cash flows from investing activities | D64: =IFERROR(HistoriacalIFLS!C89/HistoriacalIFLS!C$61,0) -> 0 | E64: =IFERROR(HistoriacalIFLS!D89/HistoriacalIFLS!D$61,0) -> 0 | F64: =IFERROR(HistoriacalIFLS!E89/HistoriacalIFLS!E$61,0) -> 0 | G64: =IFERROR(HistoriacalIFLS!F89/HistoriacalIFLS!F$61,0) -> 0 | H64: =IFERROR(HistoriacalIFLS!G89/HistoriacalIFLS!G$61,0) -> 0 | I64: =IFERROR(HistoriacalIFLS!H89/HistoriacalIFLS!H$61,0) -> 0
B65: =IFERROR(HistoriacalIFLS!B90,0) -> Fixed Assets Purchased | D65: =IFERROR(HistoriacalIFLS!C90/HistoriacalIFLS!C$61,0) -> -0.0086553229 | E65: =IFERROR(HistoriacalIFLS!D90/HistoriacalIFLS!D$61,0) -> -0.0039600124 | F65: =IFERROR(HistoriacalIFLS!E90/HistoriacalIFLS!E$61,0) -> -0.015380887 | G65: =IFERROR(HistoriacalIFLS!F90/HistoriacalIFLS!F$61,0) -> -0.010664716 | H65: =IFERROR(HistoriacalIFLS!G90/HistoriacalIFLS!G$61,0) -> -0.0051823451 | I65: =IFERROR(HistoriacalIFLS!H90/HistoriacalIFLS!H$61,0) -> -0.0074351011
B66: =IFERROR(HistoriacalIFLS!B91,0) -> Fixed Assets Sold | D66: =IFERROR(HistoriacalIFLS!C91/HistoriacalIFLS!C$61,0) -> 2.0341534e-05 | E66: =IFERROR(HistoriacalIFLS!D91/HistoriacalIFLS!D$61,0) -> 0.00024798512 | F66: =IFERROR(HistoriacalIFLS!E91/HistoriacalIFLS!E$61,0) -> 0.0002209488 | G66: =IFERROR(HistoriacalIFLS!F91/HistoriacalIFLS!F$61,0) -> 8.3418356e-05 | H66: =IFERROR(HistoriacalIFLS!G91/HistoriacalIFLS!G$61,0) -> 0.00016853155 | I66: =IFERROR(HistoriacalIFLS!H91/HistoriacalIFLS!H$61,0) -> 0.00065914016
B67: =IFERROR(HistoriacalIFLS!B92,0) -> Investments Purchased | D67: =IFERROR(HistoriacalIFLS!C92/HistoriacalIFLS!C$61,0) -> -1.1333998 | E67: =IFERROR(HistoriacalIFLS!D92/HistoriacalIFLS!D$61,0) -> -0.78112988 | F67: =IFERROR(HistoriacalIFLS!E92/HistoriacalIFLS!E$61,0) -> -0.64768645 | G67: =IFERROR(HistoriacalIFLS!F92/HistoriacalIFLS!F$61,0) -> -0.67117126 | H67: =IFERROR(HistoriacalIFLS!G92/HistoriacalIFLS!G$61,0) -> -0.45487267 | I67: =IFERROR(HistoriacalIFLS!H92/HistoriacalIFLS!H$61,0) -> -0.84021388
B68: =IFERROR(HistoriacalIFLS!B93,0) -> Investments Sold | D68: =IFERROR(HistoriacalIFLS!C93/HistoriacalIFLS!C$61,0) -> 1.0940593 | E68: =IFERROR(HistoriacalIFLS!D93/HistoriacalIFLS!D$61,0) -> 0.80953193 | F68: =IFERROR(HistoriacalIFLS!E93/HistoriacalIFLS!E$61,0) -> 0.62816456 | G68: =IFERROR(HistoriacalIFLS!F93/HistoriacalIFLS!F$61,0) -> 0.62876907 | H68: =IFERROR(HistoriacalIFLS!G93/HistoriacalIFLS!G$61,0) -> 0.44812539 | I68: =IFERROR(HistoriacalIFLS!H93/HistoriacalIFLS!H$61,0) -> 0.76881054
B69: =IFERROR(HistoriacalIFLS!B94,0) -> Interest Received/Dividends recived | D69: =IFERROR(HistoriacalIFLS!C94/HistoriacalIFLS!C$61,0) -> 0.012387994 | E69: =IFERROR(HistoriacalIFLS!D94/HistoriacalIFLS!D$61,0) -> 0.0081137632 | F69: =IFERROR(HistoriacalIFLS!E94/HistoriacalIFLS!E$61,0) -> 0.014803569 | G69: =IFERROR(HistoriacalIFLS!F94/HistoriacalIFLS!F$61,0) -> 0.01578532 | H69: =IFERROR(HistoriacalIFLS!G94/HistoriacalIFLS!G$61,0) -> 0.019892742 | I69: =IFERROR(HistoriacalIFLS!H94/HistoriacalIFLS!H$61,0) -> 0.0085740953
B71: =IFERROR(HistoriacalIFLS!B96,0) -> Redemption & Cancellation of Shares | D71: =IFERROR(HistoriacalIFLS!C96/HistoriacalIFLS!C$76,0) -> 0 | E71: =IFERROR(HistoriacalIFLS!D96/HistoriacalIFLS!D$76,0) -> 0 | F71: =IFERROR(HistoriacalIFLS!E96/HistoriacalIFLS!E$76,0) -> 0 | G71: =IFERROR(HistoriacalIFLS!F96/HistoriacalIFLS!F$76,0) -> 0 | H71: =IFERROR(HistoriacalIFLS!G96/HistoriacalIFLS!G$76,0) -> 0 | I71: =IFERROR(HistoriacalIFLS!H96/HistoriacalIFLS!H$76,0) -> 0
B72: =IFERROR(HistoriacalIFLS!B97,0) -> Acquisition of Companies | D72: =IFERROR(HistoriacalIFLS!C97/HistoriacalIFLS!C$76,0) -> 0 | E72: =IFERROR(HistoriacalIFLS!D97/HistoriacalIFLS!D$76,0) -> 0 | F72: =IFERROR(HistoriacalIFLS!E97/HistoriacalIFLS!E$76,0) -> 0 | G72: =IFERROR(HistoriacalIFLS!F97/HistoriacalIFLS!F$76,0) -> 0 | H72: =IFERROR(HistoriacalIFLS!G97/HistoriacalIFLS!G$76,0) -> -0.020392317 | I72: =IFERROR(HistoriacalIFLS!H97/HistoriacalIFLS!H$76,0) -> 0
B73: =IFERROR(HistoriacalIFLS!B98,0) -> Inter-Corporate Deposits | D73: =IFERROR(HistoriacalIFLS!C98/HistoriacalIFLS!C$76,0) -> 0 | E73: =IFERROR(HistoriacalIFLS!D98/HistoriacalIFLS!D$76,0) -> -0.027262864 | F73: =IFERROR(HistoriacalIFLS!E98/HistoriacalIFLS!E$76,0) -> 0.025074125 | G73: =IFERROR(HistoriacalIFLS!F98/HistoriacalIFLS!F$76,0) -> 0 | H73: =IFERROR(HistoriacalIFLS!G98/HistoriacalIFLS!G$76,0) -> 0 | I73: =IFERROR(HistoriacalIFLS!H98/HistoriacalIFLS!H$76,0) -> 0
B74: =IFERROR(HistoriacalIFLS!B99,0) -> Other Investing Items | D74: =IFERROR(HistoriacalIFLS!C99/HistoriacalIFLS!C$76,0) -> 0 | E74: =IFERROR(HistoriacalIFLS!D99/HistoriacalIFLS!D$76,0) -> 0 | F74: =IFERROR(HistoriacalIFLS!E99/HistoriacalIFLS!E$76,0) -> 0 | G74: =IFERROR(HistoriacalIFLS!F99/HistoriacalIFLS!F$76,0) -> 0 | H74: =IFERROR(HistoriacalIFLS!G99/HistoriacalIFLS!G$76,0) -> 0.01954966 | I74: =IFERROR(HistoriacalIFLS!H99/HistoriacalIFLS!H$76,0) -> 0.0094547065
B75: =IFERROR(HistoriacalIFLS!B100,0) -> Cash From Investing Activities | D75: =IFERROR(HistoriacalIFLS!C100/HistoriacalIFLS!C$76,0) -> -0.03685886 | E75: =IFERROR(HistoriacalIFLS!D100/HistoriacalIFLS!D$76,0) -> -0.16375542 | F75: =IFERROR(HistoriacalIFLS!E100/HistoriacalIFLS!E$76,0) -> -0.021852549 | G75: =IFERROR(HistoriacalIFLS!F100/HistoriacalIFLS!F$76,0) -> -0.062127425 | H75: =IFERROR(HistoriacalIFLS!G100/HistoriacalIFLS!G$76,0) -> -0.015703529 | I75: =IFERROR(HistoriacalIFLS!H100/HistoriacalIFLS!H$76,0) -> -0.090718779
B77: =IFERROR(HistoriacalIFLS!B102,0) -> Proceeds from Shares | D77: =IFERROR(HistoriacalIFLS!C102/HistoriacalIFLS!C$76,0) -> 0 | E77: =IFERROR(HistoriacalIFLS!D102/HistoriacalIFLS!D$76,0) -> 0 | F77: =IFERROR(HistoriacalIFLS!E102/HistoriacalIFLS!E$76,0) -> 0 | G77: =IFERROR(HistoriacalIFLS!F102/HistoriacalIFLS!F$76,0) -> 0 | H77: =IFERROR(HistoriacalIFLS!G102/HistoriacalIFLS!G$76,0) -> 0 | I77: =IFERROR(HistoriacalIFLS!H102/HistoriacalIFLS!H$76,0) -> 0
B78: =IFERROR(HistoriacalIFLS!B103,0) -> Proceeds from Borrowings | D78: =IFERROR(HistoriacalIFLS!C103/HistoriacalIFLS!C$76,0) -> 0.0016374935 | E78: =IFERROR(HistoriacalIFLS!D103/HistoriacalIFLS!D$76,0) -> 0.13698853 | F78: =IFERROR(HistoriacalIFLS!E103/HistoriacalIFLS!E$76,0) -> 0.080724712 | G78: =IFERROR(HistoriacalIFLS!F103/HistoriacalIFLS!F$76,0) -> 0.035420717 | H78: =IFERROR(HistoriacalIFLS!G103/HistoriacalIFLS!G$76,0) -> 0.045028018 | I78: =IFERROR(HistoriacalIFLS!H103/HistoriacalIFLS!H$76,0) -> 0.11253896
B79: =IFERROR(HistoriacalIFLS!B104,0) -> Repayment of Borrowings | D79: =IFERROR(HistoriacalIFLS!C104/HistoriacalIFLS!C$76,0) -> -0.0031529378 | E79: =IFERROR(HistoriacalIFLS!D104/HistoriacalIFLS!D$76,0) -> -0.0015576565 | F79: =IFERROR(HistoriacalIFLS!E104/HistoriacalIFLS!E$76,0) -> -0.064787889 | G79: =IFERROR(HistoriacalIFLS!F104/HistoriacalIFLS!F$76,0) -> -0.016131827 | H79: =IFERROR(HistoriacalIFLS!G104/HistoriacalIFLS!G$76,0) -> -0.056078873 | I79: =IFERROR(HistoriacalIFLS!H104/HistoriacalIFLS!H$76,0) -> -0.033595056
B80: =IFERROR(HistoriacalIFLS!B105,0) -> Interest Paid | D80: =IFERROR(HistoriacalIFLS!C105/HistoriacalIFLS!C$76,0) -> -0.00089502751 | E80: =IFERROR(HistoriacalIFLS!D105/HistoriacalIFLS!D$76,0) -> -0.005750155 | F80: =IFERROR(HistoriacalIFLS!E105/HistoriacalIFLS!E$76,0) -> -0.0079399019 | G80: =IFERROR(HistoriacalIFLS!F105/HistoriacalIFLS!F$76,0) -> -0.0079696614 | H80: =IFERROR(HistoriacalIFLS!G105/HistoriacalIFLS!G$76,0) -> -0.0096785261 | I80: =IFERROR(HistoriacalIFLS!H105/HistoriacalIFLS!H$76,0) -> -0.011896162
B81: =IFERROR(HistoriacalIFLS!B106,0) -> Dividends Paid | D81: =IFERROR(HistoriacalIFLS!C106/HistoriacalIFLS!C$76,0) -> 0 | E81: =IFERROR(HistoriacalIFLS!D106/HistoriacalIFLS!D$76,0) -> 0 | F81: =IFERROR(HistoriacalIFLS!E106/HistoriacalIFLS!E$76,0) -> 0 | G81: =IFERROR(HistoriacalIFLS!F106/HistoriacalIFLS!F$76,0) -> 0 | H81: =IFERROR(HistoriacalIFLS!G106/HistoriacalIFLS!G$76,0) -> 0 | I81: =IFERROR(HistoriacalIFLS!H106/HistoriacalIFLS!H$76,0) -> 0
B82: =IFERROR(HistoriacalIFLS!B107,0) -> Financial Liabilities | D82: =IFERROR(HistoriacalIFLS!C107/HistoriacalIFLS!C$76,0) -> 0 | E82: =IFERROR(HistoriacalIFLS!D107/HistoriacalIFLS!D$76,0) -> 0 | F82: =IFERROR(HistoriacalIFLS!E107/HistoriacalIFLS!E$76,0) -> 0 | G82: =IFERROR(HistoriacalIFLS!F107/HistoriacalIFLS!F$76,0) -> 0 | H82: =IFERROR(HistoriacalIFLS!G107/HistoriacalIFLS!G$76,0) -> 0 | I82: =IFERROR(HistoriacalIFLS!H107/HistoriacalIFLS!H$76,0) -> 0
B84: =IFERROR(HistoriacalIFLS!B109,0) -> Cash From Financing Activities | D84: =IFERROR(HistoriacalIFLS!C109/HistoriacalIFLS!C$76,0) -> -0.0032851578 | E84: =IFERROR(HistoriacalIFLS!D109/HistoriacalIFLS!D$76,0) -> 0.129084 | F84: =IFERROR(HistoriacalIFLS!E109/HistoriacalIFLS!E$76,0) -> 0.0073554567 | G84: =IFERROR(HistoriacalIFLS!F109/HistoriacalIFLS!F$76,0) -> 0.010671133 | H84: =IFERROR(HistoriacalIFLS!G109/HistoriacalIFLS!G$76,0) -> -0.025881631 | I84: =IFERROR(HistoriacalIFLS!H109/HistoriacalIFLS!H$76,0) -> 0.066520425

Sheet Wacc
B2: Wipro Enterprises (P) Limited (Standalone)
B4: Wegithr Average Cost Of Capital
B6: All Figure are in INR unless Stated Otherwise
K8: Weighted Average Cost of Capital
G9: Equity / | H9: Debt/ | I9: Cost of | J9: Cost of
B10: Name oF Company | C10: Country | D10: Total Equity | E10: Total Debt | F10: Tax Rate 1 | G10: Weights | H10: Weights | I10: Equity | J10: Debt | K10: Cost of Equity | N10: =I11 -> 0.059971991
B11: Wipro Enterprises (P) Limited | C11: Iindia | D11: =IFERROR(SUM(HistoriacalIFLS!H54:H55),0) -> 133686 | E11: =IFERROR(SUM(HistoriacalIFLS!H56:H57),0) -> 23482 | F11: 0.3 | G11: =IFERROR(D11/SUM(D11:E11),0) -> 0.850593 | H11: =IFERROR(E11/(SUM(D11:E11)),0) -> 0.149407 | I11: =C40 -> 0.059971991 | J11: =L26 -> 0.06626778 | K11: Equity Weight | N11: =G11 -> 0.850593
K12: Cost of Debt | N12: =J11 -> 0.06626778
B13: Total Capital | D13: =SUM(D11:E11) -> 157168 | G13: =G11+H11 -> 1 | K13: Debt Weight | N13: =H11 -> 0.149407
K14: WACC | N14: =(N10*N11)+(N12*N13) -> 0.060912626
B16: 1. Tax Rate considered as Marginal Tax Rate for the country
B19: Working Notes -No.1
B20: STEEL AUTHORITY OF INDIA LIMITED Dividends | H20: Working Note No .2 Kd
B22: Announcement Date | C22: Final Dividend (Rs) | D22: Interim Dividend (Rs | E22: Total Dividend (Rs) | F22: Yearly Growth rate | I22: Cost of Debt | M22: Calculation oF Interest
B23: 2026 | C23: 8 | D23: – | E23: 8 | F23: =LN(E23/E24) -> -0.31845373
B24: 2025 | C24: 11 | D24: – | E24: 11 | F24: =LN(E24/E25) -> 2.3978953 | I24: Pre-Tax Cost of Debt | L24: =O24 -> 0.094668257 | N24: Interest | O24: =IFERROR(HistoriacalIFLS!H27/Wacc!E11,0) -> 0.094668257
B25: 2024 | C25: 1 | D25: – | E25: 1 | F25: =LN(E25/E26) -> 0 | I25: Tax | L25: =F11 -> 0.3
B26: 2023 | C26: 1 | D26: – | E26: 1 | F26: =LN(E26/E27) -> -1.7917595 | I26: After Tax Cost Debt | L26: =L24*(1-L25) -> 0.06626778
B27: 2022 | C27: 6 | D27: – | E27: 6 | F27: =LN(E27/E28) -> 1.7917595
B28: 2021 | C28: 1 | D28: – | E28: 1 | F28: =LN(E28/E29) -> 0
B29: 2020 | C29: 1 | D29: – | E29: 1 | F29: =LN(E29/E30) -> 0
B30: 2019 | C30: 1 | D30: – | E30: 1 | F30: =LN(E30/E31) -> 0
B31: 2018 | C31: 1 | D31: – | E31: 1 | F31: =LN(E31/E32) -> -0.69314718
B32: 2017 | C32: 2 | D32: – | E32: 2 | F32: =LN(E32/E33) -> -1.0986123
B33: 2016 | C33: 5 | D33: 1 | E33: 6 | F33: =LN(E33/E34) -> -0.69314718
B34: 2015 | C34: 5 | D34: 7 | E34: 12 | F34: =LN(E34/E35) -> 0.40546511 | I34: Avearge Growth | J34: =AVERAGE(F23:F35) -> 0.036154125
B35: 2014 | C35: 3 | D35: 5 | E35: 8 | F35: =LN(E35/E36) -> 0.47000363 | I35: CAGR | J35: =_xlfn.RRI(14,E23,E36) -> -0.033014412 | K35: =-1*J35 -> 0.033014412
B36: 2013 | C36: – | D36: 5 | E36: 5 | I36: Median | J36: =MEDIAN(F23:F35) -> 0
I37: Market Price | J37: 191.6
B38: Working Note.1(a) | G38: Taken From Nse
B39: D1 | C39: =IFERROR(E36*(1+K35),0) -> 5.1650721
B40: Ke | C40: =IFERROR((C39/J37)+K35,0) -> 0.059971991
